Workbook

Sheet Sales
A1: country | B1: order_value_GBP | C1: cost | D1: date | E1: category | F1: customer_name | G1: sales_manager | H1: sales_rep | I1: device_type | J1: order_id | K1: profit | L1: Unique | M1: Order Size Bin | N1: Order Size Classification | O1: Bin Floor
A2: Sweden | B2: 17524.02 | C2: 14122.61 | D2: 43873 | E2: Books | F2: Goldner-Dibbert | G2: Maxie Marrow | H2: Madelon Bront | I2: Mobile | J2: 70-0511466 | K2: =Sales_Export_2019_2020__2[[#This Row],[order_value_GBP]]-Sales_Export_2019_2020__2[[#This Row],[ cost ]] -> 3401.41 | L2: =COUNTIF(Sales_Export_2019_2020__2[order_id],Sales_Export_2019_2020__2[[#This Row],[order_id]])>1 -> FALSE | M2: =TEXT(FLOOR(B2,5000),"£#,##0")&" - "&TEXT(FLOOR(B2,5000)+4999,"£#,##0") -> £15,000 - £19,999 | N2: {=_xlfn.IFS(Sales_Export_2019_2020__2[[#This Row],[order_value_GBP]]>Summary!$E$3+Summary!$I$4,"Large",Sales_Export_2019_2020__2[[#This Row],[order_value_GBP]]<Summary!$E$3-Summary!$I$4,"Small",AND(Sales_Export_2019_2020__2[[#This Row],[order_value_GBP]]<Summary!$E$3+Summary!$I$4,Sales_Export_2019_2020__2[[#This Row],[order_value_GBP]]>Summary!$E$3-Summary!$I$4),"Average")} -> Small | O2: =FLOOR(Sales_Export_2019_2020__2[[#This Row],[order_value_GBP]],5000) -> 15000
A3: Finland | B3: 116563.4 | C3: 92807.78 | D3: 43734 | E3: Games | F3: Hilll-Vandervort | G3: Hube Corey | H3: Wat Bowkley | I3: Mobile | J3: 28-6585323 | K3: =Sales_Export_2019_2020__2[[#This Row],[order_value_GBP]]-Sales_Export_2019_2020__2[[#This Row],[ cost ]] -> 23755.62 | L3: =COUNTIF(Sales_Export_2019_2020__2[order_id],Sales_Export_2019_2020__2[[#This Row],[order_id]])>1 -> FALSE | M3: =TEXT(FLOOR(B3,5000),"£#,##0")&" - "&TEXT(FLOOR(B3,5000)+4999,"£#,##0") -> £115,000 - £119,999 | N3: {=_xlfn.IFS(Sales_Export_2019_2020__2[[#This Row],[order_value_GBP]]>Summary!$E$3+Summary!$I$4,"Large",Sales_Export_2019_2020__2[[#This Row],[order_value_GBP]]<Summary!$E$3-Summary!$I$4,"Small",AND(Sales_Export_2019_2020__2[[#This Row],[order_value_GBP]]<Summary!$E$3+Summary!$I$4,Sales_Export_2019_2020__2[[#This Row],[order_value_GBP]]>Summary!$E$3-Summary!$I$4),"Average")} -> Average | O3: =FLOOR(Sales_Export_2019_2020__2[[#This Row],[order_value_GBP]],5000) -> 115000
A4: Portugal | B4: 296465.56 | C4: 257480.34 | D4: 43657 | E4: Clothing | F4: Larkin-Collier | G4: Celine Tumasian | H4: Smitty Culverhouse | I4: PC | J4: 58-7703341 | K4: =Sales_Export_2019_2020__2[[#This Row],[order_value_GBP]]-Sales_Export_2019_2020__2[[#This Row],[ cost ]] -> 38985.22 | L4: =COUNTIF(Sales_Export_2019_2020__2[order_id],Sales_Export_2019_2020__2[[#This Row],[order_id]])>1 -> FALSE | M4: =TEXT(FLOOR(B4,5000),"£#,##0")&" - "&TEXT(FLOOR(B4,5000)+4999,"£#,##0") -> £295,000 - £299,999 | N4: {=_xlfn.IFS(Sales_Export_2019_2020__2[[#This Row],[order_value_GBP]]>Summary!$E$3+Summary!$I$4,"Large",Sales_Export_2019_2020__2[[#This Row],[order_value_GBP]]<Summary!$E$3-Summary!$I$4,"Small",AND(Sales_Export_2019_2020__2[[#This Row],[order_value_GBP]]<Summary!$E$3+Summary!$I$4,Sales_Export_2019_2020__2[[#This Row],[order_value_GBP]]>Summary!$E$3-Summary!$I$4),"Average")} -> Large | O4: =FLOOR(Sales_Export_2019_2020__2[[#This Row],[order_value_GBP]],5000) -> 295000
A5: Portugal | B5: 74532.02 | C5: 59752.32 | D5: 43923 | E5: Beauty | F5: Hessel-Stiedemann | G5: Celine Tumasian | H5: Aurelie Wren | I5: PC | J5: 14-6700183 | K5: =Sales_Export_2019_2020__2[[#This Row],[order_value_GBP]]-Sales_Export_2019_2020__2[[#This Row],[ cost ]] -> 14779.7 | L5: =COUNTIF(Sales_Export_2019_2020__2[order_id],Sales_Export_2019_2020__2[[#This Row],[order_id]])>1 -> FALSE | M5: =TEXT(FLOOR(B5,5000),"£#,##0")&" - "&TEXT(FLOOR(B5,5000)+4999,"£#,##0") -> £70,000 - £74,999 | N5: {=_xlfn.IFS(Sales_Export_2019_2020__2[[#This Row],[order_value_GBP]]>Summary!$E$3+Summary!$I$4,"Large",Sales_Export_2019_2020__2[[#This Row],[order_value_GBP]]<Summary!$E$3-Summary!$I$4,"Small",AND(Sales_Export_2019_2020__2[[#This Row],[order_value_GBP]]<Summary!$E$3+Summary!$I$4,Sales_Export_2019_2020__2[[#This Row],[order_value_GBP]]>Summary!$E$3-Summary!$I$4),"Average")} -> Average | O5: =FLOOR(Sales_Export_2019_2020__2[[#This Row],[order_value_GBP]],5000) -> 70000
A6: Spain | B6: 178763.42 | C6: 146621.76 | D6: 43821 | E6: Games | F6: Johns and Sons | G6: Emalia Dinse | H6: Bertha Walbrook | I6: Tablet | J6: 15-8765160 | K6: =Sales_Export_2019_2020__2[[#This Row],[order_value_GBP]]-Sales_Export_2019_2020__2[[#This Row],[ cost ]] -> 32141.66 | L6: =COUNTIF(Sales_Export_2019_2020__2[order_id],Sales_Export_2019_2020__2[[#This Row],[order_id]])>1 -> FALSE | M6: =TEXT(FLOOR(B6,5000),"£#,##0")&" - "&TEXT(FLOOR(B6,5000)+4999,"£#,##0") -> £175,000 - £179,999 | N6: {=_xlfn.IFS(Sales_Export_2019_2020__2[[#This Row],[order_value_GBP]]>Summary!$E$3+Summary!$I$4,"Large",Sales_Export_2019_2020__2[[#This Row],[order_value_GBP]]<Summary!$E$3-Summary!$I$4,"Small",AND(Sales_Export_2019_2020__2[[#This Row],[order_value_GBP]]<Summary!$E$3+Summary!$I$4,Sales_Export_2019_2020__2[[#This Row],[order_value_GBP]]>Summary!$E$3-Summary!$I$4),"Average")} -> Large | O6: =FLOOR(Sales_Export_2019_2020__2[[#This Row],[order_value_GBP]],5000) -> 175000
A7: Spain | B7: 84900.24 | C7: 73701.9 | D7: 44026 | E7: Clothing | F7: Farrell, Swaniawski and Crist | G7: Emalia Dinse | H7: Perri Aldersley | I7: PC | J7: 60-6998932 | K7: =Sales_Export_2019_2020__2[[#This Row],[order_value_GBP]]-Sales_Export_2019_2020__2[[#This Row],[ cost ]] -> 11198.34 | L7: =COUNTIF(Sales_Export_2019_2020__2[order_id],Sales_Export_2019_2020__2[[#This Row],[order_id]])>1 -> FALSE | M7: =TEXT(FLOOR(B7,5000),"£#,##0")&" - "&TEXT(FLOOR(B7,5000)+4999,"£#,##0") -> £80,000 - £84,999 | N7: {=_xlfn.IFS(Sales_Export_2019_2020__2[[#This Row],[order_value_GBP]]>Summary!$E$3+Summary!$I$4,"Large",Sales_Export_2019_2020__2[[#This Row],[order_value_GBP]]<Summary!$E$3-Summary!$I$4,"Small",AND(Sales_Export_2019_2020__2[[#This Row],[order_value_GBP]]<Summary!$E$3+Summary!$I$4,Sales_Export_2019_2020__2[[#This Row],[order_value_GBP]]>Summary!$E$3-Summary!$I$4),"Average")} -> Average | O7: =FLOOR(Sales_Export_2019_2020__2[[#This Row],[order_value_GBP]],5000) -> 80000
A8: Portugal | B8: 71620.08 | C8: 62245.01 | D8: 43501 | E8: Books | F8: Schoen-Keeling | G8: Celine Tumasian | H8: Smitty Culverhouse | I8: PC | J8: 69-6259390 | K8: =Sales_Export_2019_2020__2[[#This Row],[order_value_GBP]]-Sales_Export_2019_2020__2[[#This Row],[ cost ]] -> 9375.07 | L8: =COUNTIF(Sales_Export_2019_2020__2[order_id],Sales_Export_2019_2020__2[[#This Row],[order_id]])>1 -> FALSE | M8: =TEXT(FLOOR(B8,5000),"£#,##0")&" - "&TEXT(FLOOR(B8,5000)+4999,"£#,##0") -> £70,000 - £74,999 | N8: {=_xlfn.IFS(Sales_Export_2019_2020__2[[#This Row],[order_value_GBP]]>Summary!$E$3+Summary!$I$4,"Large",Sales_Export_2019_2020__2[[#This Row],[order_value_GBP]]<Summary!$E$3-Summary!$I$4,"Small",AND(Sales_Export_2019_2020__2[[#This Row],[order_value_GBP]]<Summary!$E$3+Summary!$I$4,Sales_Export_2019_2020__2[[#This Row],[order_value_GBP]]>Summary!$E$3-Summary!$I$4),"Average")} -> Average | O8: =FLOOR(Sales_Export_2019_2020__2[[#This Row],[order_value_GBP]],5000) -> 70000
A9: UK | B9: 156585.22 | C9: 126599.15 | D9: 44073 | E9: Accessories | F9: Hermiston, Simonis and Wisoky | G9: Jessamine Apark | H9: Winny Agnolo | I9: PC | J9: 64-5761908 | K9: =Sales_Export_2019_2020__2[[#This Row],[order_value_GBP]]-Sales_Export_2019_2020__2[[#This Row],[ cost ]] -> 29986.07 | L9: =COUNTIF(Sales_Export_2019_2020__2[order_id],Sales_Export_2019_2020__2[[#This Row],[order_id]])>1 -> FALSE | M9: =TEXT(FLOOR(B9,5000),"£#,##0")&" - "&TEXT(FLOOR(B9,5000)+4999,"£#,##0") -> £155,000 - £159,999 | N9: {=_xlfn.IFS(Sales_Export_2019_2020__2[[#This Row],[order_value_GBP]]>Summary!$E$3+Summary!$I$4,"Large",Sales_Export_2019_2020__2[[#This Row],[order_value_GBP]]<Summary!$E$3-Summary!$I$4,"Small",AND(Sales_Export_2019_2020__2[[#This Row],[order_value_GBP]]<Summary!$E$3+Summary!$I$4,Sales_Export_2019_2020__2[[#This Row],[order_value_GBP]]>Summary!$E$3-Summary!$I$4),"Average")} -> Average | O9: =FLOOR(Sales_Export_2019_2020__2[[#This Row],[order_value_GBP]],5000) -> 155000
A10: Portugal | B10: 78461.13 | C10: 63537.82 | D10: 43961 | E10: Appliances | F10: Hessel-Stiedemann | G10: Celine Tumasian | H10: Smitty Culverhouse | I10: Mobile | J10: 91-4126746 | K10: =Sales_Export_2019_2020__2[[#This Row],[order_value_GBP]]-Sales_Export_2019_2020__2[[#This Row],[ cost ]] -> 14923.31 | L10: =COUNTIF(Sales_Export_2019_2020__2[order_id],Sales_Export_2019_2020__2[[#This Row],[order_id]])>1 -> FALSE | M10: =TEXT(FLOOR(B10,5000),"£#,##0")&" - "&TEXT(FLOOR(B10,5000)+4999,"£#,##0") -> £75,000 - £79,999 | N10: {=_xlfn.IFS(Sales_Export_2019_2020__2[[#This Row],[order_value_GBP]]>Summary!$E$3+Summary!$I$4,"Large",Sales_Export_2019_2020__2[[#This Row],[order_value_GBP]]<Summary!$E$3-Summary!$I$4,"Small",AND(Sales_Export_2019_2020__2[[#This Row],[order_value_GBP]]<Summary!$E$3+Summary!$I$4,Sales_Export_2019_2020__2[[#This Row],[order_value_GBP]]>Summary!$E$3-Summary!$I$4),"Average")} -> Average | O10: =FLOOR(Sales_Export_2019_2020__2[[#This Row],[order_value_GBP]],5000) -> 75000
A11: France | B11: 64827.8 | C11: 56043.63 | D11: 43485 | E11: Appliances | F11: Gislason-Stanton | G11: Othello Bowes | H11: Maighdiln Upcraft | I11: PC | J11: 62-3312495 | K11: =Sales_Export_2019_2020__2[[#This Row],[order_value_GBP]]-Sales_Export_2019_2020__2[[#This Row],[ cost ]] -> 8784.17 | L11: =COUNTIF(Sales_Export_2019_2020__2[order_id],Sales_Export_2019_2020__2[[#This Row],[order_id]])>1 -> FALSE | M11: =TEXT(FLOOR(B11,5000),"£#,##0")&" - "&TEXT(FLOOR(B11,5000)+4999,"£#,##0") -> £60,000 - £64,999 | N11: {=_xlfn.IFS(Sales_Export_2019_2020__2[[#This Row],[order_value_GBP]]>Summary!$E$3+Summary!$I$4,"Large",Sales_Export_2019_2020__2[[#This Row],[order_value_GBP]]<Summary!$E$3-Summary!$I$4,"Small",AND(Sales_Export_2019_2020__2[[#This Row],[order_value_GBP]]<Summary!$E$3+Summary!$I$4,Sales_Export_2019_2020__2[[#This Row],[order_value_GBP]]>Summary!$E$3-Summary!$I$4),"Average")} -> Average | O11: =FLOOR(Sales_Export_2019_2020__2[[#This Row],[order_value_GBP]],5000) -> 60000
A12: Sweden | B12: 142664.34 | C12: 120808.16 | D12: 43589 | E12: Appliances | F12: Swaniawski, Runolfsson and Green | G12: Maxie Marrow | H12: Madelon Bront | I12: PC | J12: 85-6625096 | K12: =Sales_Export_2019_2020__2[[#This Row],[order_value_GBP]]-Sales_Export_2019_2020__2[[#This Row],[ cost ]] -> 21856.18 | L12: =COUNTIF(Sales_Export_2019_2020__2[order_id],Sales_Export_2019_2020__2[[#This Row],[order_id]])>1 -> FALSE | M12: =TEXT(FLOOR(B12,5000),"£#,##0")&" - "&TEXT(FLOOR(B12,5000)+4999,"£#,##0") -> £140,000 - £144,999 | N12: {=_xlfn.IFS(Sales_Export_2019_2020__2[[#This Row],[order_value_GBP]]>Summary!$E$3+Summary!$I$4,"Large",Sales_Export_2019_2020__2[[#This Row],[order_value_GBP]]<Summary!$E$3-Summary!$I$4,"Small",AND(Sales_Export_2019_2020__2[[#This Row],[order_value_GBP]]<Summary!$E$3+Summary!$I$4,Sales_Export_2019_2020__2[[#This Row],[order_value_GBP]]>Summary!$E$3-Summary!$I$4),"Average")} -> Average | O12: =FLOOR(Sales_Export_2019_2020__2[[#This Row],[order_value_GBP]],5000) -> 140000
A13: UK | B13: 66673.19 | C13: 52811.83 | D13: 43519 | E13: Smartphones | F13: Gislason-Stanton | G13: Jessamine Apark | H13: Winny Agnolo | I13: PC | J13: 25-6368157 | K13: =Sales_Export_2019_2020__2[[#This Row],[order_value_GBP]]-Sales_Export_2019_2020__2[[#This Row],[ cost ]] -> 13861.36 | L13: =COUNTIF(Sales_Export_2019_2020__2[order_id],Sales_Export_2019_2020__2[[#This Row],[order_id]])>1 -> FALSE | M13: =TEXT(FLOOR(B13,5000),"£#,##0")&" - "&TEXT(FLOOR(B13,5000)+4999,"£#,##0") -> £65,000 - £69,999 | N13: {=_xlfn.IFS(Sales_Export_2019_2020__2[[#This Row],[order_value_GBP]]>Summary!$E$3+Summary!$I$4,"Large",Sales_Export_2019_2020__2[[#This Row],[order_value_GBP]]<Summary!$E$3-Summary!$I$4,"Small",AND(Sales_Export_2019_2020__2[[#This Row],[order_value_GBP]]<Summary!$E$3+Summary!$I$4,Sales_Export_2019_2020__2[[#This Row],[order_value_GBP]]>Summary!$E$3-Summary!$I$4),"Average")} -> Average | O13: =FLOOR(Sales_Export_2019_2020__2[[#This Row],[order_value_GBP]],5000) -> 65000
... A1001: Portugal | B1001: 107716.72 | C1001: 86679.64 | D1001: 43848 | E1001: Accessories | F1001: Jacobson, Marvin and Brown | G1001: Celine Tumasian | H1001: Brynn Dempster | I1001: Mobile | J1001: 61-3294149 | K1001: =Sales_Export_2019_2020__2[[#This Row],[order_value_GBP]]-Sales_Export_2019_2020__2[[#This Row],[ cost ]] -> 21037.08 | L1001: =COUNTIF(Sales_Export_2019_2020__2[order_id],Sales_Export_2019_2020__2[[#This Row],[order_id]])>1 -> FALSE | M1001: =TEXT(FLOOR(B1001,5000),"£#,##0")&" - "&TEXT(FLOOR(B1001,5000)+4999,"£#,##0") -> £105,000 - £109,999 | N1001: {=_xlfn.IFS(Sales_Export_2019_2020__2[[#This Row],[order_value_GBP]]>Summary!$E$3+Summary!$I$4,"Large",Sales_Export_2019_2020__2[[#This Row],[order_value_GBP]]<Summary!$E$3-Summary!$I$4,"Small",AND(Sales_Export_2019_2020__2[[#This Row],[order_value_GBP]]<Summary!$E$3+Summary!$I$4,Sales_Export_2019_2020__2[[#This Row],[order_value_GBP]]>Summary!$E$3-Summary!$I$4),"Average")} -> Average | O1001: =FLOOR(Sales_Export_2019_2020__2[[#This Row],[order_value_GBP]],5000) -> 105000

Sheet Summary
D1: Summary Table
C2: 2 | D2: 3 | E2: 4 | F2: 5 | G2: 6 | H2: 7 | I2: 8 | R2: Order Size Bin | S2: Count | T2: Bin Floor (sort key)
B3: Total Revenue | C3: =SUM(Sales_Export_2019_2020__2[order_value_GBP]) -> 1.1336174e+08 | D3: Avg Order Size | E3: =AVERAGE(Sales_Export_2019_2020__2[order_value_GBP]) -> 113361.74 | F3: Number of Categories | G3: =COUNTA(_xlfn.ANCHORARRAY(I9)) -> 10 | H3: Customer with the most orders | I3: =INDEX(B27:B101,MATCH(MAX($D$27:$D$101),D27:D101,0)) -> Johns and Sons | R3: {=_xlfn.XLOOKUP(_xlfn.ANCHORARRAY(T3),Sales_Export_2019_2020__2[Bin Floor],Sales_Export_2019_2020__2[Order Size Bin])} -> £15,000 - £19,999 | S3: {=COUNTIFS(Sales_Export_2019_2020__2[Bin Floor],_xlfn.ANCHORARRAY(T3))} -> 12 | T3: {=_xlfn._xlws.SORT(_xlfn.UNIQUE(Sales_Export_2019_2020__2[Bin Floor]))} -> 15000
B4: Total Cost | C4: =SUM(Sales_Export_2019_2020__2[[ cost ]]) -> 94369311 | D4: Largest Order | E4: =MAX(Sales_Export_2019_2020__2[order_value_GBP]) -> 383996.76 | F4: Number of Sales Reps | G4: =COUNTA(_xlfn.ANCHORARRAY(F9)) -> 35 | H4: STD of order size | I4: =_xlfn.STDEV.P(Sales_Export_2019_2020__2[order_value_GBP]) -> 61744.44 | R4: £20,000 - £24,999 | S4: 7 | T4: 20000
B5: Total Profit | C5: =SUM(Sales_Export_2019_2020__2[profit]) -> 18992428 | D5: Smallest Order | E5: =MIN(Sales_Export_2019_2020__2[order_value_GBP]) -> 15100.57 | F5: Number of Sales Managers | G5: =COUNTA(_xlfn.ANCHORARRAY(B10)) -> 15 | H5: Median Order Value | I5: =MEDIAN(Sales_Export_2019_2020__2[order_value_GBP]) -> 105419.43 | R5: £25,000 - £29,999 | S5: 20 | T5: 25000
B6: Number of Sales | C6: =ROWS(_xlfn.UNIQUE(Sales_Export_2019_2020__2[order_id])) -> 1000 | D6: Avg Profit per Order | E6: =C5/C6 -> 18992.428 | F6: Number of Customers | G6: =COUNTA(_xlfn.ANCHORARRAY(B27)) -> 75 | R6: £30,000 - £34,999 | S6: 19 | T6: 30000
R7: £35,000 - £39,999 | S7: 34 | T7: 35000
F8: Sales Rep | G8: Associated Sales Manager | I8: Categories | J8: Orders of each category | K8: Average Profit per Order | L8: Revenue per Order | M8: Cost per Order | N8: STD of order size | O8: Correlation between profit and order size | R8: £40,000 - £44,999 | S8: 30 | T8: 40000
B9: Sales Managers | C9: Number of Sales Reps | F9: {=_xlfn.UNIQUE(Sales_Export_2019_2020__2[sales_rep])} -> Madelon Bront | G9: =_xlfn.XLOOKUP(F9,Sales_Export_2019_2020__2[sales_rep],Sales_Export_2019_2020__2[sales_manager]) -> Maxie Marrow | I9: {=_xlfn.UNIQUE(Sales_Export_2019_2020__2[category])} -> Books | J9: =COUNTIF(Sales_Export_2019_2020__2[category],I9) -> 117 | K9: =AVERAGEIF(Sales_Export_2019_2020__2[category],I9,Sales_Export_2019_2020__2[profit]) -> 19024.905 | L9: =AVERAGEIF(Sales_Export_2019_2020__2[category],I9,Sales_Export_2019_2020__2[order_value_GBP]) -> 112649.39 | M9: =AVERAGEIF(Sales_Export_2019_2020__2[category],I9,Sales_Export_2019_2020__2[[ cost ]]) -> 93624.487 | N9: {=_xlfn.STDEV.P(_xlfn._xlws.FILTER(Sales_Export_2019_2020__2[order_value_GBP],Sales_Export_2019_2020__2[category]=I9))} -> 61004.334 | O9: {=CORREL(_xlfn._xlws.FILTER(Sales_Export_2019_2020__2[order_value_GBP],Sales_Export_2019_2020__2[category]=I9),_xlfn._xlws.FILTER(Sales_Export_2019_2020__2[profit],Sales_Export_2019_2020__2[category]=I9))} -> 0.93453593 | R9: £45,000 - £49,999 | S9: 26 | T9: 45000
B10: {=_xlfn.UNIQUE(Sales_Export_2019_2020__2[sales_manager])} -> Maxie Marrow | C10: =COUNTIF($G$9:$G$43,B10) -> 5 | F10: Wat Bowkley | G10: =_xlfn.XLOOKUP(F10,Sales_Export_2019_2020__2[sales_rep],Sales_Export_2019_2020__2[sales_manager]) -> Hube Corey | I10: Games | J10: =COUNTIF(Sales_Export_2019_2020__2[category],I10) -> 139 | K10: =AVERAGEIF(Sales_Export_2019_2020__2[category],I10,Sales_Export_2019_2020__2[profit]) -> 18415.797 | L10: =AVERAGEIF(Sales_Export_2019_2020__2[category],I10,Sales_Export_2019_2020__2[order_value_GBP]) -> 110227.51 | M10: =AVERAGEIF(Sales_Export_2019_2020__2[category],I10,Sales_Export_2019_2020__2[[ cost ]]) -> 91811.71 | N10: {=_xlfn.STDEV.P(_xlfn._xlws.FILTER(Sales_Export_2019_2020__2[order_value_GBP],Sales_Export_2019_2020__2[category]=I10))} -> 57187.476 | O10: {=CORREL(_xlfn._xlws.FILTER(Sales_Export_2019_2020__2[order_value_GBP],Sales_Export_2019_2020__2[category]=I10),_xlfn._xlws.FILTER(Sales_Export_2019_2020__2[profit],Sales_Export_2019_2020__2[category]=I10))} -> 0.9478257 | R10: £50,000 - £54,999 | S10: 31 | T10: 50000
B11: Hube Corey | C11: =COUNTIF($G$9:$G$43,B11) -> 2 | F11: Smitty Culverhouse | G11: =_xlfn.XLOOKUP(F11,Sales_Export_2019_2020__2[sales_rep],Sales_Export_2019_2020__2[sales_manager]) -> Celine Tumasian | I11: Clothing | J11: =COUNTIF(Sales_Export_2019_2020__2[category],I11) -> 155 | K11: =AVERAGEIF(Sales_Export_2019_2020__2[category],I11,Sales_Export_2019_2020__2[profit]) -> 18980.246 | L11: =AVERAGEIF(Sales_Export_2019_2020__2[category],I11,Sales_Export_2019_2020__2[order_value_GBP]) -> 113946.34 | M11: =AVERAGEIF(Sales_Export_2019_2020__2[category],I11,Sales_Export_2019_2020__2[[ cost ]]) -> 94966.091 | N11: {=_xlfn.STDEV.P(_xlfn._xlws.FILTER(Sales_Export_2019_2020__2[order_value_GBP],Sales_Export_2019_2020__2[category]=I11))} -> 64003.443 | O11: {=CORREL(_xlfn._xlws.FILTER(Sales_Export_2019_2020__2[order_value_GBP],Sales_Export_2019_2020__2[category]=I11),_xlfn._xlws.FILTER(Sales_Export_2019_2020__2[profit],Sales_Export_2019_2020__2[category]=I11))} -> 0.95203436 | R11: £55,000 - £59,999 | S11: 41 | T11: 55000
B12: Celine Tumasian | C12: =COUNTIF($G$9:$G$43,B12) -> 5 | F12: Aurelie Wren | G12: =_xlfn.XLOOKUP(F12,Sales_Export_2019_2020__2[sales_rep],Sales_Export_2019_2020__2[sales_manager]) -> Celine Tumasian | I12: Beauty | J12: =COUNTIF(Sales_Export_2019_2020__2[category],I12) -> 115 | K12: =AVERAGEIF(Sales_Export_2019_2020__2[category],I12,Sales_Export_2019_2020__2[profit]) -> 18421.108 | L12: =AVERAGEIF(Sales_Export_2019_2020__2[category],I12,Sales_Export_2019_2020__2[order_value_GBP]) -> 109296.21 | M12: =AVERAGEIF(Sales_Export_2019_2020__2[category],I12,Sales_Export_2019_2020__2[[ cost ]]) -> 90875.1 | N12: {=_xlfn.STDEV.P(_xlfn._xlws.FILTER(Sales_Export_2019_2020__2[order_value_GBP],Sales_Export_2019_2020__2[category]=I12))} -> 59060.631 | O12: {=CORREL(_xlfn._xlws.FILTER(Sales_Export_2019_2020__2[order_value_GBP],Sales_Export_2019_2020__2[category]=I12),_xlfn._xlws.FILTER(Sales_Export_2019_2020__2[profit],Sales_Export_2019_2020__2[category]=I12))} -> 0.94702137 | R12: £60,000 - £64,999 | S12: 25 | T12: 60000
B13: Emalia Dinse | C13: =COUNTIF($G$9:$G$43,B13) -> 3 | F13: Bertha Walbrook | G13: =_xlfn.XLOOKUP(F13,Sales_Export_2019_2020__2[sales_rep],Sales_Export_2019_2020__2[sales_manager]) -> Emalia Dinse | I13: Accessories | J13: =COUNTIF(Sales_Export_2019_2020__2[category],I13) -> 35 | K13: =AVERAGEIF(Sales_Export_2019_2020__2[category],I13,Sales_Export_2019_2020__2[profit]) -> 22397.038 | L13: =AVERAGEIF(Sales_Export_2019_2020__2[category],I13,Sales_Export_2019_2020__2[order_value_GBP]) -> 134398.02 | M13: =AVERAGEIF(Sales_Export_2019_2020__2[category],I13,Sales_Export_2019_2020__2[[ cost ]]) -> 112000.98 | N13: {=_xlfn.STDEV.P(_xlfn._xlws.FILTER(Sales_Export_2019_2020__2[order_value_GBP],Sales_Export_2019_2020__2[category]=I13))} -> 63784.53 | O13: {=CORREL(_xlfn._xlws.FILTER(Sales_Export_2019_2020__2[order_value_GBP],Sales_Export_2019_2020__2[category]=I13),_xlfn._xlws.FILTER(Sales_Export_2019_2020__2[profit],Sales_Export_2019_2020__2[category]=I13))} -> 0.92391288 | R13: £65,000 - £69,999 | S13: 35 | T13: 65000
B14: Jessamine Apark | C14: =COUNTIF($G$9:$G$43,B14) -> 3 | F14: Perri Aldersley | G14: =_xlfn.XLOOKUP(F14,Sales_Export_2019_2020__2[sales_rep],Sales_Export_2019_2020__2[sales_manager]) -> Emalia Dinse | I14: Appliances | J14: =COUNTIF(Sales_Export_2019_2020__2[category],I14) -> 131 | K14: =AVERAGEIF(Sales_Export_2019_2020__2[category],I14,Sales_Export_2019_2020__2[profit]) -> 19350.224 | L14: =AVERAGEIF(Sales_Export_2019_2020__2[category],I14,Sales_Export_2019_2020__2[order_value_GBP]) -> 115569.99 | M14: =AVERAGEIF(Sales_Export_2019_2020__2[category],I14,Sales_Export_2019_2020__2[[ cost ]]) -> 96219.766 | N14: {=_xlfn.STDEV.P(_xlfn._xlws.FILTER(Sales_Export_2019_2020__2[order_value_GBP],Sales_Export_2019_2020__2[category]=I14))} -> 62639.063 | O14: {=CORREL(_xlfn._xlws.FILTER(Sales_Export_2019_2020__2[order_value_GBP],Sales_Export_2019_2020__2[category]=I14),_xlfn._xlws.FILTER(Sales_Export_2019_2020__2[profit],Sales_Export_2019_2020__2[category]=I14))} -> 0.95461071 | R14: £70,000 - £74,999 | S14: 29 | T14: 70000
B15: Othello Bowes | C15: =COUNTIF($G$9:$G$43,B15) -> 5 | F15: Winny Agnolo | G15: =_xlfn.XLOOKUP(F15,Sales_Export_2019_2020__2[sales_rep],Sales_Export_2019_2020__2[sales_manager]) -> Jessamine Apark | I15: Smartphones | J15: =COUNTIF(Sales_Export_2019_2020__2[category],I15) -> 95 | K15: =AVERAGEIF(Sales_Export_2019_2020__2[category],I15,Sales_Export_2019_2020__2[profit]) -> 19164.712 | L15: =AVERAGEIF(Sales_Export_2019_2020__2[category],I15,Sales_Export_2019_2020__2[order_value_GBP]) -> 116859.52 | M15: =AVERAGEIF(Sales_Export_2019_2020__2[category],I15,Sales_Export_2019_2020__2[[ cost ]]) -> 97694.811 | N15: {=_xlfn.STDEV.P(_xlfn._xlws.FILTER(Sales_Export_2019_2020__2[order_value_GBP],Sales_Export_2019_2020__2[category]=I15))} -> 62201.29 | O15: {=CORREL(_xlfn._xlws.FILTER(Sales_Export_2019_2020__2[order_value_GBP],Sales_Export_2019_2020__2[category]=I15),_xlfn._xlws.FILTER(Sales_Export_2019_2020__2[profit],Sales_Export_2019_2020__2[category]=I15))} -> 0.94130651 | R15: £75,000 - £79,999 | S15: 35 | T15: 75000
B16: Denice Amberg | C16: =COUNTIF($G$9:$G$43,B16) -> 1 | F16: Maighdiln Upcraft | G16: =_xlfn.XLOOKUP(F16,Sales_Export_2019_2020__2[sales_rep],Sales_Export_2019_2020__2[sales_manager]) -> Othello Bowes | I16: Outdoors | J16: =COUNTIF(Sales_Export_2019_2020__2[category],I16) -> 50 | K16: =AVERAGEIF(Sales_Export_2019_2020__2[category],I16,Sales_Export_2019_2020__2[profit]) -> 21135.25 | L16: =AVERAGEIF(Sales_Export_2019_2020__2[category],I16,Sales_Export_2019_2020__2[order_value_GBP]) -> 118781.51 | M16: =AVERAGEIF(Sales_Export_2019_2020__2[category],I16,Sales_Export_2019_2020__2[[ cost ]]) -> 97646.259 | N16: {=_xlfn.STDEV.P(_xlfn._xlws.FILTER(Sales_Export_2019_2020__2[order_value_GBP],Sales_Export_2019_2020__2[category]=I16))} -> 58577.397 | O16: {=CORREL(_xlfn._xlws.FILTER(Sales_Export_2019_2020__2[order_value_GBP],Sales_Export_2019_2020__2[category]=I16),_xlfn._xlws.FILTER(Sales_Export_2019_2020__2[profit],Sales_Export_2019_2020__2[category]=I16))} -> 0.96207249 | R16: £80,000 - £84,999 | S16: 38 | T16: 80000
B17: Lambert Norheny | C17: =COUNTIF($G$9:$G$43,B17) -> 1 | F17: Genevra Charrisson | G17: =_xlfn.XLOOKUP(F17,Sales_Export_2019_2020__2[sales_rep],Sales_Export_2019_2020__2[sales_manager]) -> Jessamine Apark | I17: Electronics | J17: =COUNTIF(Sales_Export_2019_2020__2[category],I17) -> 134 | K17: =AVERAGEIF(Sales_Export_2019_2020__2[category],I17,Sales_Export_2019_2020__2[profit]) -> 17918.903 | L17: =AVERAGEIF(Sales_Export_2019_2020__2[category],I17,Sales_Export_2019_2020__2[order_value_GBP]) -> 108075.21 | M17: =AVERAGEIF(Sales_Export_2019_2020__2[category],I17,Sales_Export_2019_2020__2[[ cost ]]) -> 90156.303 | N17: {=_xlfn.STDEV.P(_xlfn._xlws.FILTER(Sales_Export_2019_2020__2[order_value_GBP],Sales_Export_2019_2020__2[category]=I17))} -> 57277.623 | O17: {=CORREL(_xlfn._xlws.FILTER(Sales_Export_2019_2020__2[order_value_GBP],Sales_Export_2019_2020__2[category]=I17),_xlfn._xlws.FILTER(Sales_Export_2019_2020__2[profit],Sales_Export_2019_2020__2[category]=I17))} -> 0.95132379 | R17: £85,000 - £89,999 | S17: 37 | T17: 85000
B18: Charil Alpe | C18: =COUNTIF($G$9:$G$43,B18) -> 2 | F18: Anita Woakes | G18: =_xlfn.XLOOKUP(F18,Sales_Export_2019_2020__2[sales_rep],Sales_Export_2019_2020__2[sales_manager]) -> Maxie Marrow | I18: Other | J18: =COUNTIF(Sales_Export_2019_2020__2[category],I18) -> 29 | K18: =AVERAGEIF(Sales_Export_2019_2020__2[category],I18,Sales_Export_2019_2020__2[profit]) -> 18932.197 | L18: =AVERAGEIF(Sales_Export_2019_2020__2[category],I18,Sales_Export_2019_2020__2[order_value_GBP]) -> 112516.66 | M18: =AVERAGEIF(Sales_Export_2019_2020__2[category],I18,Sales_Export_2019_2020__2[[ cost ]]) -> 93584.465 | N18: {=_xlfn.STDEV.P(_xlfn._xlws.FILTER(Sales_Export_2019_2020__2[order_value_GBP],Sales_Export_2019_2020__2[category]=I18))} -> 88131.727 | O18: {=CORREL(_xlfn._xlws.FILTER(Sales_Export_2019_2020__2[order_value_GBP],Sales_Export_2019_2020__2[category]=I18),_xlfn._xlws.FILTER(Sales_Export_2019_2020__2[profit],Sales_Export_2019_2020__2[category]=I18))} -> 0.97466059 | R18: £90,000 - £94,999 | S18: 21 | T18: 90000
B19: Ilsa Kob | C19: =COUNTIF($G$9:$G$43,B19) -> 1 | F19: Amelina Piscopiello | G19: =_xlfn.XLOOKUP(F19,Sales_Export_2019_2020__2[sales_rep],Sales_Export_2019_2020__2[sales_manager]) -> Othello Bowes | R19: £95,000 - £99,999 | S19: 33 | T19: 95000
B20: Piggy Roscrigg | C20: =COUNTIF($G$9:$G$43,B20) -> 1 | F20: Jay Morefield | G20: =_xlfn.XLOOKUP(F20,Sales_Export_2019_2020__2[sales_rep],Sales_Export_2019_2020__2[sales_manager]) -> Jessamine Apark | I20: Year | J20: Total Revenue | K20: Total Sales | L20: Share of Revenue | M20: Difference in share of profits and sales | N20: Avg Profit per Sale | O20: Profit Margin | P20: Total Profit | R20: £100,000 - £104,999 | S20: 24 | T20: 100000
B21: Glenine Suttaby | C21: =COUNTIF($G$9:$G$43,B21) -> 2 | F21: Corene Shirer | G21: =_xlfn.XLOOKUP(F21,Sales_Export_2019_2020__2[sales_rep],Sales_Export_2019_2020__2[sales_manager]) -> Celine Tumasian | I21: 2019 | J21: 56617524 | K21: 490 | L21: 0.49944121 | M21: 0.0095294983 | N21: 19361.792 | O21: 0.16756787 | P21: 9487277.9 | R21: £105,000 - £109,999 | S21: 32 | T21: 105000
B22: Rickard Doogood | C22: =COUNTIF($G$9:$G$43,B22) -> 1 | F22: Alyosha Meah | G22: =_xlfn.XLOOKUP(F22,Sales_Export_2019_2020__2[sales_rep],Sales_Export_2019_2020__2[sales_manager]) -> Maxie Marrow | I22: 2020 | J22: 56744214 | K22: 510 | L22: 0.50055879 | M22: -0.0095294983 | N22: 18637.549 | O22: 0.1675087 | P22: 9505149.8 | R22: £110,000 - £114,999 | S22: 21 | T22: 110000
B23: Modestia Byfford | C23: =COUNTIF($G$9:$G$43,B23) -> 2 | F23: Nero Harbisher | G23: =_xlfn.XLOOKUP(F23,Sales_Export_2019_2020__2[sales_rep],Sales_Export_2019_2020__2[sales_manager]) -> Denice Amberg | I23: Grand Total | J23: 1.1336174e+08 | K23: 1000 | L23: 1 | M23: 0 | N23: 18992.428 | O23: 0.16753825 | P23: 18992428 | R23: £115,000 - £119,999 | S23: 34 | T23: 115000
B24: Orsa Geekin | C24: =COUNTIF($G$9:$G$43,B24) -> 1 | F24: Hortense Gerring | G24: =_xlfn.XLOOKUP(F24,Sales_Export_2019_2020__2[sales_rep],Sales_Export_2019_2020__2[sales_manager]) -> Celine Tumasian | R24: £120,000 - £124,999 | S24: 35 | T24: 120000
F25: Collin Mackness | G25: =_xlfn.XLOOKUP(F25,Sales_Export_2019_2020__2[sales_rep],Sales_Export_2019_2020__2[sales_manager]) -> Lambert Norheny | R25: £125,000 - £129,999 | S25: 32 | T25: 125000
B26: Customers | C26: Avg Order Size | D26: Number of Orders | F26: Shermy McGready | G26: =_xlfn.XLOOKUP(F26,Sales_Export_2019_2020__2[sales_rep],Sales_Export_2019_2020__2[sales_manager]) -> Charil Alpe | R26: £130,000 - £134,999 | S26: 24 | T26: 130000
B27: {=_xlfn.UNIQUE(Sales_Export_2019_2020__2[customer_name])} -> Goldner-Dibbert | C27: =AVERAGEIF(Sales_Export_2019_2020__2[customer_name],B27,Sales_Export_2019_2020__2[order_value_GBP]) -> 100941.25 | D27: =COUNTIF(Sales_Export_2019_2020__2[customer_name],B27) -> 9 | F27: Jocelyn Laurentino | G27: =_xlfn.XLOOKUP(F27,Sales_Export_2019_2020__2[sales_rep],Sales_Export_2019_2020__2[sales_manager]) -> Ilsa Kob | R27: £135,000 - £139,999 | S27: 21 | T27: 135000
B28: Hilll-Vandervort | C28: =AVERAGEIF(Sales_Export_2019_2020__2[customer_name],B28,Sales_Export_2019_2020__2[order_value_GBP]) -> 114416.18 | D28: =COUNTIF(Sales_Export_2019_2020__2[customer_name],B28) -> 16 | F28: Caro Morfield | G28: =_xlfn.XLOOKUP(F28,Sales_Export_2019_2020__2[sales_rep],Sales_Export_2019_2020__2[sales_manager]) -> Maxie Marrow | R28: £140,000 - £144,999 | S28: 22 | T28: 140000
B29: Larkin-Collier | C29: =AVERAGEIF(Sales_Export_2019_2020__2[customer_name],B29,Sales_Export_2019_2020__2[order_value_GBP]) -> 122216.66 | D29: =COUNTIF(Sales_Export_2019_2020__2[customer_name],B29) -> 21 | F29: Crysta Halls | G29: =_xlfn.XLOOKUP(F29,Sales_Export_2019_2020__2[sales_rep],Sales_Export_2019_2020__2[sales_manager]) -> Othello Bowes | R29: £145,000 - £149,999 | S29: 27 | T29: 145000
B30: Hessel-Stiedemann | C30: =AVERAGEIF(Sales_Export_2019_2020__2[customer_name],B30,Sales_Export_2019_2020__2[order_value_GBP]) -> 118401.16 | D30: =COUNTIF(Sales_Export_2019_2020__2[customer_name],B30) -> 55 | F30: Ora Grennan | G30: =_xlfn.XLOOKUP(F30,Sales_Export_2019_2020__2[sales_rep],Sales_Export_2019_2020__2[sales_manager]) -> Othello Bowes | R30: £150,000 - £154,999 | S30: 25 | T30: 150000
B31: Johns and Sons | C31: =AVERAGEIF(Sales_Export_2019_2020__2[customer_name],B31,Sales_Export_2019_2020__2[order_value_GBP]) -> 115213.08 | D31: =COUNTIF(Sales_Export_2019_2020__2[customer_name],B31) -> 142 | F31: Joshua Prevost | G31: =_xlfn.XLOOKUP(F31,Sales_Export_2019_2020__2[sales_rep],Sales_Export_2019_2020__2[sales_manager]) -> Piggy Roscrigg | R31: £155,000 - £159,999 | S31: 24 | T31: 155000
B32: Farrell, Swaniawski and Crist | C32: =AVERAGEIF(Sales_Export_2019_2020__2[customer_name],B32,Sales_Export_2019_2020__2[order_value_GBP]) -> 94214.645 | D32: =COUNTIF(Sales_Export_2019_2020__2[customer_name],B32) -> 17 | F32: Avrit Chanders | G32: =_xlfn.XLOOKUP(F32,Sales_Export_2019_2020__2[sales_rep],Sales_Export_2019_2020__2[sales_manager]) -> Othello Bowes | R32: £160,000 - £164,999 | S32: 25 | T32: 160000
B33: Schoen-Keeling | C33: =AVERAGEIF(Sales_Export_2019_2020__2[customer_name],B33,Sales_Export_2019_2020__2[order_value_GBP]) -> 83383.017 | D33: =COUNTIF(Sales_Export_2019_2020__2[customer_name],B33) -> 10 | F33: Bernadine Fullagar | G33: =_xlfn.XLOOKUP(F33,Sales_Export_2019_2020__2[sales_rep],Sales_Export_2019_2020__2[sales_manager]) -> Charil Alpe | R33: £165,000 - £169,999 | S33: 26 | T33: 165000
B34: Hermiston, Simonis and Wisoky | C34: =AVERAGEIF(Sales_Export_2019_2020__2[customer_name],B34,Sales_Export_2019_2020__2[order_value_GBP]) -> 107191.42 | D34: =COUNTIF(Sales_Export_2019_2020__2[customer_name],B34) -> 10 | F34: Tarrah Castelletti | G34: =_xlfn.XLOOKUP(F34,Sales_Export_2019_2020__2[sales_rep],Sales_Export_2019_2020__2[sales_manager]) -> Maxie Marrow | R34: £170,000 - £174,999 | S34: 25 | T34: 170000
B35: Gislason-Stanton | C35: =AVERAGEIF(Sales_Export_2019_2020__2[customer_name],B35,Sales_Export_2019_2020__2[order_value_GBP]) -> 118254.4 | D35: =COUNTIF(Sales_Export_2019_2020__2[customer_name],B35) -> 17 | F35: Bunnie Tonbridge | G35: =_xlfn.XLOOKUP(F35,Sales_Export_2019_2020__2[sales_rep],Sales_Export_2019_2020__2[sales_manager]) -> Glenine Suttaby | R35: £175,000 - £179,999 | S35: 22 | T35: 175000
B36: Swaniawski, Runolfsson and Green | C36: =AVERAGEIF(Sales_Export_2019_2020__2[customer_name],B36,Sales_Export_2019_2020__2[order_value_GBP]) -> 100245.38 | D36: =COUNTIF(Sales_Export_2019_2020__2[customer_name],B36) -> 25 | F36: Palm Wetherald | G36: =_xlfn.XLOOKUP(F36,Sales_Export_2019_2020__2[sales_rep],Sales_Export_2019_2020__2[sales_manager]) -> Glenine Suttaby | R36: £180,000 - £184,999 | S36: 8 | T36: 180000
B37: Wisoky Inc | C37: =AVERAGEIF(Sales_Export_2019_2020__2[customer_name],B37,Sales_Export_2019_2020__2[order_value_GBP]) -> 108462.59 | D37: =COUNTIF(Sales_Export_2019_2020__2[customer_name],B37) -> 21 | F37: Casie MacBain | G37: =_xlfn.XLOOKUP(F37,Sales_Export_2019_2020__2[sales_rep],Sales_Export_2019_2020__2[sales_manager]) -> Rickard Doogood | R37: £185,000 - £189,999 | S37: 4 | T37: 185000
B38: Tillman and Sons | C38: =AVERAGEIF(Sales_Export_2019_2020__2[customer_name],B38,Sales_Export_2019_2020__2[order_value_GBP]) -> 99014.511 | D38: =COUNTIF(Sales_Export_2019_2020__2[customer_name],B38) -> 21 | F38: Brynn Dempster | G38: =_xlfn.XLOOKUP(F38,Sales_Export_2019_2020__2[sales_rep],Sales_Export_2019_2020__2[sales_manager]) -> Celine Tumasian | R38: £190,000 - £194,999 | S38: 4 | T38: 190000
B39: Rowe, Hermiston and Kessler | C39: =AVERAGEIF(Sales_Export_2019_2020__2[customer_name],B39,Sales_Export_2019_2020__2[order_value_GBP]) -> 105114.77 | D39: =COUNTIF(Sales_Export_2019_2020__2[customer_name],B39) -> 22 | F39: Case Desorts | G39: =_xlfn.XLOOKUP(F39,Sales_Export_2019_2020__2[sales_rep],Sales_Export_2019_2020__2[sales_manager]) -> Modestia Byfford | R39: £195,000 - £199,999 | S39: 3 | T39: 195000
... B43: Jacobson, Marvin and Brown | C43: =AVERAGEIF(Sales_Export_2019_2020__2[customer_name],B43,Sales_Export_2019_2020__2[order_value_GBP]) -> 155424 | D43: =COUNTIF(Sales_Export_2019_2020__2[customer_name],B43) -> 7 | F43: Cobby Andersen | G43: =_xlfn.XLOOKUP(F43,Sales_Export_2019_2020__2[sales_rep],Sales_Export_2019_2020__2[sales_manager]) -> Modestia Byfford | R43: £215,000 - £219,999 | S43: 2 | T43: 215000
B44: Armstrong-Little | C44: =AVERAGEIF(Sales_Export_2019_2020__2[customer_name],B44,Sales_Export_2019_2020__2[order_value_GBP]) -> 108330.92 | D44: =COUNTIF(Sales_Export_2019_2020__2[customer_name],B44) -> 19 | R44: £220,000 - £224,999 | S44: 5 | T44: 220000
B45: Murray, Reichel and Nolan | C45: =AVERAGEIF(Sales_Export_2019_2020__2[customer_name],B45,Sales_Export_2019_2020__2[order_value_GBP]) -> 84271.484 | D45: =COUNTIF(Sales_Export_2019_2020__2[customer_name],B45) -> 23 | R45: £225,000 - £229,999 | S45: 4 | T45: 225000
B46: Considine-Fisher | C46: =AVERAGEIF(Sales_Export_2019_2020__2[customer_name],B46,Sales_Export_2019_2020__2[order_value_GBP]) -> 120611.02 | D46: =COUNTIF(Sales_Export_2019_2020__2[customer_name],B46) -> 11 | R46: £230,000 - £234,999 | S46: 6 | T46: 230000
B47: Kirlin and Sons | C47: =AVERAGEIF(Sales_Export_2019_2020__2[customer_name],B47,Sales_Export_2019_2020__2[order_value_GBP]) -> 123571.41 | D47: =COUNTIF(Sales_Export_2019_2020__2[customer_name],B47) -> 12 | R47: £235,000 - £239,999 | S47: 7 | T47: 235000
B48: Friesen-Rath | C48: =AVERAGEIF(Sales_Export_2019_2020__2[customer_name],B48,Sales_Export_2019_2020__2[order_value_GBP]) -> 110306.75 | D48: =COUNTIF(Sales_Export_2019_2020__2[customer_name],B48) -> 19 | R48: £240,000 - £244,999 | S48: 6 | T48: 240000
B49: Keeling, Monahan and Pollich | C49: =AVERAGEIF(Sales_Export_2019_2020__2[customer_name],B49,Sales_Export_2019_2020__2[order_value_GBP]) -> 126333.61 | D49: =COUNTIF(Sales_Export_2019_2020__2[customer_name],B49) -> 11 | R49: £245,000 - £249,999 | S49: 4 | T49: 245000
B50: Dibbert Inc | C50: =AVERAGEIF(Sales_Export_2019_2020__2[customer_name],B50,Sales_Export_2019_2020__2[order_value_GBP]) -> 104188.68 | D50: =COUNTIF(Sales_Export_2019_2020__2[customer_name],B50) -> 18 | R50: £250,000 - £254,999 | S50: 9 | T50: 250000
B51: Labadie and Sons | C51: =AVERAGEIF(Sales_Export_2019_2020__2[customer_name],B51,Sales_Export_2019_2020__2[order_value_GBP]) -> 113961.31 | D51: =COUNTIF(Sales_Export_2019_2020__2[customer_name],B51) -> 19 | R51: £255,000 - £259,999 | S51: 3 | T51: 255000
B52: Wiza and Sons | C52: =AVERAGEIF(Sales_Export_2019_2020__2[customer_name],B52,Sales_Export_2019_2020__2[order_value_GBP]) -> 100857.84 | D52: =COUNTIF(Sales_Export_2019_2020__2[customer_name],B52) -> 13 | R52: £260,000 - £264,999 | S52: 3 | T52: 260000
B53: Schmitt, Purdy and Johnson | C53: =AVERAGEIF(Sales_Export_2019_2020__2[customer_name],B53,Sales_Export_2019_2020__2[order_value_GBP]) -> 135923.22 | D53: =COUNTIF(Sales_Export_2019_2020__2[customer_name],B53) -> 11 | R53: £265,000 - £269,999 | S53: 1 | T53: 265000
B54: Hamill, Kulas and Roob | C54: =AVERAGEIF(Sales_Export_2019_2020__2[customer_name],B54,Sales_Export_2019_2020__2[order_value_GBP]) -> 110790.79 | D54: =COUNTIF(Sales_Export_2019_2020__2[customer_name],B54) -> 13 | R54: £270,000 - £274,999 | S54: 3 | T54: 270000
B55: Fisher, Morar and Skiles | C55: =AVERAGEIF(Sales_Export_2019_2020__2[customer_name],B55,Sales_Export_2019_2020__2[order_value_GBP]) -> 96254.501 | D55: =COUNTIF(Sales_Export_2019_2020__2[customer_name],B55) -> 9 | R55: £275,000 - £279,999 | S55: 1 | T55: 275000
... B65: Zieme, Bailey and Herzog | C65: =AVERAGEIF(Sales_Export_2019_2020__2[customer_name],B65,Sales_Export_2019_2020__2[order_value_GBP]) -> 106722.8 | D65: =COUNTIF(Sales_Export_2019_2020__2[customer_name],B65) -> 15 | R65: £380,000 - £384,999 | S65: 1 | T65: 380000
B66: Bashirian, Okuneva and Bechtelar | C66: =AVERAGEIF(Sales_Export_2019_2020__2[customer_name],B66,Sales_Export_2019_2020__2[order_value_GBP]) -> 104150.05 | D66: =COUNTIF(Sales_Export_2019_2020__2[customer_name],B66) -> 13
B67: McGlynn-Prosacco | C67: =AVERAGEIF(Sales_Export_2019_2020__2[customer_name],B67,Sales_Export_2019_2020__2[order_value_GBP]) -> 118770.31 | D67: =COUNTIF(Sales_Export_2019_2020__2[customer_name],B67) -> 16
B68: O'Connell-Mitchell | C68: =AVERAGEIF(Sales_Export_2019_2020__2[customer_name],B68,Sales_Export_2019_2020__2[order_value_GBP]) -> 166888.43 | D68: =COUNTIF(Sales_Export_2019_2020__2[customer_name],B68) -> 10
B69: West-Cummings | C69: =AVERAGEIF(Sales_Export_2019_2020__2[customer_name],B69,Sales_Export_2019_2020__2[order_value_GBP]) -> 139313.32 | D69: =COUNTIF(Sales_Export_2019_2020__2[customer_name],B69) -> 11
B70: Shanahan, Schaden and Parker | C70: =AVERAGEIF(Sales_Export_2019_2020__2[customer_name],B70,Sales_Export_2019_2020__2[order_value_GBP]) -> 116152.97 | D70: =COUNTIF(Sales_Export_2019_2020__2[customer_name],B70) -> 5
B71: Lubowitz, McLaughlin and Erdman | C71: =AVERAGEIF(Sales_Export_2019_2020__2[customer_name],B71,Sales_Export_2019_2020__2[order_value_GBP]) -> 89681.443 | D71: =COUNTIF(Sales_Export_2019_2020__2[customer_name],B71) -> 7
B72: Rath-Schroeder | C72: =AVERAGEIF(Sales_Export_2019_2020__2[customer_name],B72,Sales_Export_2019_2020__2[order_value_GBP]) -> 69664.885 | D72: =COUNTIF(Sales_Export_2019_2020__2[customer_name],B72) -> 2
B73: Dickinson, Hyatt and Berge | C73: =AVERAGEIF(Sales_Export_2019_2020__2[customer_name],B73,Sales_Export_2019_2020__2[order_value_GBP]) -> 112780.43 | D73: =COUNTIF(Sales_Export_2019_2020__2[customer_name],B73) -> 24
B74: McClure Inc | C74: =AVERAGEIF(Sales_Export_2019_2020__2[customer_name],B74,Sales_Export_2019_2020__2[order_value_GBP]) -> 111636.82 | D74: =COUNTIF(Sales_Export_2019_2020__2[customer_name],B74) -> 11
B75: Hane Inc | C75: =AVERAGEIF(Sales_Export_2019_2020__2[customer_name],B75,Sales_Export_2019_2020__2[order_value_GBP]) -> 115277.34 | D75: =COUNTIF(Sales_Export_2019_2020__2[customer_name],B75) -> 4
B76: Kihn Inc | C76: =AVERAGEIF(Sales_Export_2019_2020__2[customer_name],B76,Sales_Export_2019_2020__2[order_value_GBP]) -> 91057.222 | D76: =COUNTIF(Sales_Export_2019_2020__2[customer_name],B76) -> 22
B77: Schowalter, Lesch and Beahan | C77: =AVERAGEIF(Sales_Export_2019_2020__2[customer_name],B77,Sales_Export_2019_2020__2[order_value_GBP]) -> 126085.7 | D77: =COUNTIF(Sales_Export_2019_2020__2[customer_name],B77) -> 16
... B101: Lind, Mueller and Stoltenberg | C101: =AVERAGEIF(Sales_Export_2019_2020__2[customer_name],B101,Sales_Export_2019_2020__2[order_value_GBP]) -> 57115.99 | D101: =COUNTIF(Sales_Export_2019_2020__2[customer_name],B101) -> 1

Sheet MOMP Tables
W1: Monthly Ratings
C2: Monthly Summary | P2: Yearly Supporting Statistics | Q2: 2019 | R2: 2020 | S2: Total | W2: 2019 | X2: 2020 | AF2: Product Summary
C3: 2019 | G3: 2020 | K3: Total Orders | L3: Total Revenue | M3: Total Cost | N3: Total Profit | V3: Jan | W3: {=IF(INDEX(W$21:W$32,_xlfn.XMATCH($V3,$V$21:$V$32,0))<$S$19,"Below Average",IF(INDEX(W$21:W$32,_xlfn.XMATCH($V21,$V$21:$V$32,0))>$S$21,"Above Average", "Average"))} -> Average | X3: {=IF(INDEX(X$21:X$32,_xlfn.XMATCH($V3,$V$21:$V$32,0))<$S$19,"Below Average",IF(INDEX(X$21:X$32,_xlfn.XMATCH($V21,$V$21:$V$32,0))>$S$21,"Above Average", "Average"))} -> Average | AF3: 2019 | AJ3: 2020 | AN3: Total Total Number of Sales | AO3: Total Average Cost | AP3: Total Average Order Value | AQ3: Total Average of Profit
B4: Month | C4: Orders | D4: Revenue | E4: Cost | F4: Profit | G4: Orders | H4: Revenue | I4: Cost | J4: Profit | P4: Correlation between orders and profits | Q4: =CORREL(C5:C16,F5:F16) -> 0.45204688 | R4: =CORREL(G5:G16,J5:J16) -> 0.37399861 | S4: =CORREL(K5:K16,N5:N16) -> 0.14238539 | V4: Feb | W4: {=IF(INDEX($W$21:$W$32,_xlfn.XMATCH(V4,$V$21:$V$32,0))<$S$19,"Below Average",IF(INDEX($W$21:$W$32,_xlfn.XMATCH(V22,$V$21:$V$32,0))>$S$21,"Above Average", "Average"))} -> Average | X4: {=IF(INDEX(X$21:X$32,_xlfn.XMATCH($V4,$V$21:$V$32,0))<$S$19,"Below Average",IF(INDEX(X$21:X$32,_xlfn.XMATCH($V22,$V$21:$V$32,0))>$S$21,"Above Average", "Average"))} -> Below Average | AE4: Category Breakdown | AF4: Total Number of Sales | AG4: Average Cost | AH4: Average Order Value | AI4: Average of Profit | AJ4: Total Number of Sales | AK4: Average Cost | AL4: Average Order Value | AM4: Average of Profit
B5: Jan | C5: 44 | D5: 4516614.8 | E5: 3792383.5 | F5: 724231.31 | G5: 51 | H5: 5215699.8 | I5: 4291060.8 | J5: 924639.02 | K5: 95 | L5: 9732314.7 | M5: 8083444.3 | N5: 1648870.3 | P5: Standard Deviation of Profit Margin (Percentage Points) | Q5: =100*_xlfn.STDEV.P(Q39:Q50) -> 0.40545845 | R5: =100*_xlfn.STDEV.P(R39:R50) -> 0.52165337 | S5: =_xlfn.STDEV.P(S39:S50) -> 0.0024180522 | V5: Mar | W5: {=IF(INDEX($W$21:$W$32,_xlfn.XMATCH(V5,$V$21:$V$32,0))<$S$19,"Below Average",IF(INDEX($W$21:$W$32,_xlfn.XMATCH(V23,$V$21:$V$32,0))>$S$21,"Above Average", "Average"))} -> Below Average | X5: {=IF(INDEX(X$21:X$32,_xlfn.XMATCH($V5,$V$21:$V$32,0))<$S$19,"Below Average",IF(INDEX(X$21:X$32,_xlfn.XMATCH($V23,$V$21:$V$32,0))>$S$21,"Above Average", "Average"))} -> Average | AE5: Accessories | AF5: 16 | AG5: 115805.45 | AH5: 139551.06 | AI5: 23745.609 | AJ5: 19 | AK5: 108797.22 | AL5: 130058.61 | AM5: 21261.399 | AN5: 35 | AO5: 112000.98 | AP5: 134398.02 | AQ5: 22397.038
B6: Feb | C6: 44 | D6: 2895563.9 | E6: 2402359 | F6: 493204.9 | G6: 28 | H6: 1959413 | I6: 1643662.5 | J6: 315750.51 | K6: 72 | L6: 4854976.9 | M6: 4046021.5 | N6: 808955.41 | P6: Standard Deviation of Orders | Q6: =_xlfn.STDEV.P(C5:C16) -> 5.2413951 | R6: =_xlfn.STDEV.P(G5:G16) -> 8.2815055 | S6: =_xlfn.STDEV.P(K5:K16) -> 8.4294457 | V6: Apr | W6: {=IF(INDEX($W$21:$W$32,_xlfn.XMATCH(V6,$V$21:$V$32,0))<$S$19,"Below Average",IF(INDEX($W$21:$W$32,_xlfn.XMATCH(V24,$V$21:$V$32,0))>$S$21,"Above Average", "Average"))} -> Average | X6: {=IF(INDEX(X$21:X$32,_xlfn.XMATCH($V6,$V$21:$V$32,0))<$S$19,"Below Average",IF(INDEX(X$21:X$32,_xlfn.XMATCH($V24,$V$21:$V$32,0))>$S$21,"Above Average", "Average"))} -> Average | AE6: Appliances | AF6: 62 | AG6: 95395.716 | AH6: 114719.13 | AI6: 19323.413 | AJ6: 69 | AK6: 96960.217 | AL6: 116334.53 | AM6: 19374.315 | AN6: 131 | AO6: 96219.766 | AP6: 115569.99 | AQ6: 19350.224
B7: Mar | C7: 41 | D7: 2521828 | E7: 2092407.4 | F7: 429420.62 | G7: 52 | H7: 3579943.8 | I7: 2983600.1 | J7: 596343.77 | K7: 93 | L7: 6101771.8 | M7: 5076007.4 | N7: 1025764.4 | P7: Avg in Difference between profit and sales share | Q7: =AVERAGE(H38:H49) -> 0.00079412486 | R7: =AVERAGE(I38:I49) -> -0.00079412486 | S7: 0 | V7: May | W7: {=IF(INDEX($W$21:$W$32,_xlfn.XMATCH(V7,$V$21:$V$32,0))<$S$19,"Below Average",IF(INDEX($W$21:$W$32,_xlfn.XMATCH(V25,$V$21:$V$32,0))>$S$21,"Above Average", "Average"))} -> Average | X7: {=IF(INDEX(X$21:X$32,_xlfn.XMATCH($V7,$V$21:$V$32,0))<$S$19,"Below Average",IF(INDEX(X$21:X$32,_xlfn.XMATCH($V25,$V$21:$V$32,0))>$S$21,"Above Average", "Average"))} -> Average | AE7: Beauty | AF7: 61 | AG7: 99161.231 | AH7: 118270.98 | AI7: 19109.75 | AJ7: 54 | AK7: 81514.839 | AL7: 99158.037 | AM7: 17643.197 | AN7: 115 | AO7: 90875.1 | AP7: 109296.21 | AQ7: 18421.108
B8: Apr | C8: 36 | D8: 4172236.8 | E8: 3479483.1 | F8: 692753.62 | G8: 38 | H8: 4069097.8 | I8: 3372878.3 | J8: 696219.46 | K8: 74 | L8: 8241334.5 | M8: 6852361.5 | N8: 1388973.1 | P8: STD of profit share - sales share | Q8: =_xlfn.STDEV.P(H38:H49) -> 0.015481995 | R8: =_xlfn.STDEV.P(I38:I49) -> 0.010967011 | S8: =_xlfn.STDEV.P(J38:J49) -> 0.02596975 | V8: Jun | W8: {=IF(INDEX($W$21:$W$32,_xlfn.XMATCH(V8,$V$21:$V$32,0))<$S$19,"Below Average",IF(INDEX($W$21:$W$32,_xlfn.XMATCH(V26,$V$21:$V$32,0))>$S$21,"Above Average", "Average"))} -> Above Average | X8: {=IF(INDEX(X$21:X$32,_xlfn.XMATCH($V8,$V$21:$V$32,0))<$S$19,"Below Average",IF(INDEX(X$21:X$32,_xlfn.XMATCH($V26,$V$21:$V$32,0))>$S$21,"Above Average", "Average"))} -> Above Average | AE8: Books | AF8: 46 | AG8: 96982.911 | AH8: 117734.88 | AI8: 20751.97 | AJ8: 71 | AK8: 91448.607 | AL8: 109354.57 | AM8: 17905.962 | AN8: 117 | AO8: 93624.487 | AP8: 112649.39 | AQ8: 19024.905
B9: May | C9: 38 | D9: 3825682 | E9: 3177423.7 | F9: 648258.3 | G9: 55 | H9: 5537943.8 | I9: 4623092.1 | J9: 914851.65 | K9: 93 | L9: 9363625.7 | M9: 7800515.8 | N9: 1563109.9 | P9: Correlation between avg order val and avg profit per sale | V9: Jul | W9: {=IF(INDEX($W$21:$W$32,_xlfn.XMATCH(V9,$V$21:$V$32,0))<$S$19,"Below Average",IF(INDEX($W$21:$W$32,_xlfn.XMATCH(V27,$V$21:$V$32,0))>$S$21,"Above Average", "Average"))} -> Average | X9: {=IF(INDEX(X$21:X$32,_xlfn.XMATCH($V9,$V$21:$V$32,0))<$S$19,"Below Average",IF(INDEX(X$21:X$32,_xlfn.XMATCH($V27,$V$21:$V$32,0))>$S$21,"Above Average", "Average"))} -> Average | AE9: Clothing | AF9: 85 | AG9: 100050.27 | AH9: 119936.93 | AI9: 19886.657 | AJ9: 70 | AK9: 88792.446 | AL9: 106672.05 | AM9: 17879.604 | AN9: 155 | AO9: 94966.091 | AP9: 113946.34 | AQ9: 18980.246
B10: Jun | C10: 47 | D10: 7692234.9 | E10: 6386956.5 | F10: 1305278.4 | G10: 43 | H10: 7158137.9 | I10: 5971093.4 | J10: 1187044.5 | K10: 90 | L10: 14850373 | M10: 12358050 | N10: 2492322.8 | P10: Correlation between avg order val and avg profit per sale | Q10: =CORREL(M21:M32,C38:C49) -> 0.99727848 | R10: =CORREL(D38:D49,N21:N32) -> 0.99455161 | V10: Aug | W10: {=IF(INDEX($W$21:$W$32,_xlfn.XMATCH(V10,$V$21:$V$32,0))<$S$19,"Below Average",IF(INDEX($W$21:$W$32,_xlfn.XMATCH(V28,$V$21:$V$32,0))>$S$21,"Above Average", "Average"))} -> Average | X10: {=IF(INDEX(X$21:X$32,_xlfn.XMATCH($V10,$V$21:$V$32,0))<$S$19,"Below Average",IF(INDEX(X$21:X$32,_xlfn.XMATCH($V28,$V$21:$V$32,0))>$S$21,"Above Average", "Average"))} -> Average | AE10: Electronics | AF10: 68 | AG10: 83612.752 | AH10: 100864.41 | AI10: 17251.656 | AJ10: 66 | AK10: 96898.143 | AL10: 115504.51 | AM10: 18606.37 | AN10: 134 | AO10: 90156.303 | AP10: 108075.21 | AQ10: 17918.903
B11: Jul | C11: 40 | D11: 6638609.2 | E11: 5554381.8 | F11: 1084227.4 | G11: 36 | H11: 5242556.5 | I11: 4402567.1 | J11: 839989.39 | K11: 76 | L11: 11881166 | M11: 9956948.9 | N11: 1924216.8 | P11: Avg Monthly Profit | Q11: =AVERAGE(F5:F16) -> 790606.49 | R11: =AVERAGE(J5:J16) -> 792095.82 | S11: =AVERAGE(N5:N16) -> 1582702.3 | V11: Sep | W11: {=IF(INDEX($W$21:$W$32,_xlfn.XMATCH(V11,$V$21:$V$32,0))<$S$19,"Below Average",IF(INDEX($W$21:$W$32,_xlfn.XMATCH(V29,$V$21:$V$32,0))>$S$21,"Above Average", "Average"))} -> Average | X11: {=IF(INDEX(X$21:X$32,_xlfn.XMATCH($V11,$V$21:$V$32,0))<$S$19,"Below Average",IF(INDEX(X$21:X$32,_xlfn.XMATCH($V29,$V$21:$V$32,0))>$S$21,"Above Average", "Average"))} -> Average | AE11: Games | AF11: 74 | AG11: 91794.38 | AH11: 109785.44 | AI11: 17991.058 | AJ11: 65 | AK11: 91831.439 | AL11: 110730.78 | AM11: 18899.345 | AN11: 139 | AO11: 91811.71 | AP11: 110227.51 | AQ11: 18415.797
B12: Aug | C12: 31 | D12: 3437450.1 | E12: 2857134 | F12: 580316.12 | G12: 45 | H12: 4714525.2 | I12: 3945548.9 | J12: 768976.36 | K12: 76 | L12: 8151975.3 | M12: 6802682.9 | N12: 1349292.5 | P12: STD of monthly profit | Q12: =_xlfn.STDEV.P(F5:F16) -> 325312.74 | R12: =_xlfn.STDEV.P(J5:J16) -> 207506.54 | S12: =_xlfn.STDEV.P(N5:N16) -> 489875 | V12: Oct | W12: {=IF(INDEX($W$21:$W$32,_xlfn.XMATCH(V12,$V$21:$V$32,0))<$S$19,"Below Average",IF(INDEX($W$21:$W$32,_xlfn.XMATCH(V30,$V$21:$V$32,0))>$S$21,"Above Average", "Average"))} -> Average | X12: {=IF(INDEX(X$21:X$32,_xlfn.XMATCH($V12,$V$21:$V$32,0))<$S$19,"Below Average",IF(INDEX(X$21:X$32,_xlfn.XMATCH($V30,$V$21:$V$32,0))>$S$21,"Above Average", "Average"))} -> Average | AE12: Other | AF12: 10 | AG12: 98834.291 | AH12: 120111.05 | AI12: 21276.763 | AJ12: 19 | AK12: 90821.399 | AL12: 108519.61 | AM12: 17698.215 | AN12: 29 | AO12: 93584.465 | AP12: 112516.66 | AQ12: 18932.197
B13: Sep | C13: 49 | D13: 4870060.5 | E13: 4081869 | F13: 788191.58 | G13: 34 | H13: 3778141.4 | I13: 3114973.7 | J13: 663167.65 | K13: 83 | L13: 8648201.9 | M13: 7196842.7 | N13: 1451359.2 | P13: Corr between total sales and avg profit per sale | Q13: =CORREL(AB21:AB32,C38:C49) -> 0.17781761 | R13: =CORREL(AC21:AC32,D38:D49) -> -0.27722849 | V13: Nov | W13: {=IF(INDEX($W$21:$W$32,_xlfn.XMATCH(V13,$V$21:$V$32,0))<$S$19,"Below Average",IF(INDEX($W$21:$W$32,_xlfn.XMATCH(V31,$V$21:$V$32,0))>$S$21,"Above Average", "Average"))} -> Average | X13: {=IF(INDEX(X$21:X$32,_xlfn.XMATCH($V13,$V$21:$V$32,0))<$S$19,"Below Average",IF(INDEX(X$21:X$32,_xlfn.XMATCH($V31,$V$21:$V$32,0))>$S$21,"Above Average", "Average"))} -> Average | AE13: Outdoors | AF13: 21 | AG13: 90273.627 | AH13: 109635.75 | AI13: 19362.128 | AJ13: 29 | AK13: 102985.06 | AL13: 125404.3 | AM13: 22419.236 | AN13: 50 | AO13: 97646.259 | AP13: 118781.51 | AQ13: 21135.25
B14: Oct | C14: 43 | D14: 4372149.5 | E14: 3627715.1 | F14: 744434.48 | G14: 50 | H14: 4869726.8 | I14: 4030025.9 | J14: 839700.96 | K14: 93 | L14: 9241876.4 | M14: 7657741 | N14: 1584135.4 | V14: Dec | W14: {=IF(INDEX($W$21:$W$32,_xlfn.XMATCH(V14,$V$21:$V$32,0))<$S$19,"Below Average",IF(INDEX($W$21:$W$32,_xlfn.XMATCH(V32,$V$21:$V$32,0))>$S$21,"Above Average", "Average"))} -> Above Average | X14: {=IF(INDEX(X$21:X$32,_xlfn.XMATCH($V14,$V$21:$V$32,0))<$S$19,"Below Average",IF(INDEX(X$21:X$32,_xlfn.XMATCH($V32,$V$21:$V$32,0))>$S$21,"Above Average", "Average"))} -> Average | AE14: Smartphones | AF14: 47 | AG14: 106084.31 | AH14: 126825.21 | AI14: 20740.896 | AJ14: 48 | AK14: 89480.091 | AL14: 107101.46 | AM14: 17621.366 | AN14: 95 | AO14: 97694.811 | AP14: 116859.52 | AQ14: 19164.712
B15: Nov | C15: 33 | D15: 2961318.6 | E15: 2479031 | F15: 482287.62 | G15: 45 | H15: 4734730.1 | I15: 3947059.7 | J15: 787670.37 | K15: 78 | L15: 7696048.7 | M15: 6426090.7 | N15: 1269958 | Q15: =Q11+Q12 -> 1115919.2 | R15: =SUM(R11,R12) -> 999602.36 | AE15: Grand Total | AF15: 490 | AG15: 96184.177 | AH15: 115545.97 | AI15: 19361.792 | AJ15: 510 | AK15: 92625.617 | AL15: 111263.17 | AM15: 18637.549 | AN15: 1000 | AO15: 94369.311 | AP15: 113361.74 | AQ15: 18992.428
B16: Dec | C16: 44 | D16: 8713776 | E16: 7199102.5 | F16: 1514673.6 | G16: 33 | H16: 5884298.3 | I16: 4913502 | J16: 970796.22 | K16: 77 | L16: 14598074 | M16: 12112605 | N16: 2485469.8
B17: Grand Total | C17: 490 | D17: 56617524 | E17: 47130247 | F17: 9487277.9 | G17: 510 | H17: 56744214 | I17: 47239064 | J17: 9505149.8 | K17: 1000 | L17: 1.1336174e+08 | M17: 94369311 | N17: 18992428
S18: 2019 | T18: 2020 | AF18: Categories by Month
B19: Monthly Revenue | C19: Year | L19: Average Order Value by Month | M19: Year | R19: Below Average | S19: =Q11-Q12 -> 465293.75 | T19: =R11-R12 -> 584589.28 | V19: Profit per Month | W19: Column Labels | AA19: Sales by Month | AB19: Year | AF19: Jan | AJ19: Feb | AN19: Mar | AR19: Apr | AV19: May | AZ19: Jun | BD19: Jul | BH19: Aug | BL19: Sep | BP19: Oct | BT19: Nov | BX19: Dec | CB19: Total Makeup of Monthly Orders | CC19: Total Average Order Value
B20: Month | C20: 2019 | D20: 2020 | E20: Grand Total | L20: Month | M20: 2019 | N20: 2020 | O20: Grand Total | R20: Average | S20: =Q11 -> 790606.49 | T20: =R11 -> 792095.82 | V20: Row Labels | W20: 2019 | X20: 2020 | Y20: Grand Total | AA20: Month | AB20: 2019 | AC20: 2020 | AD20: Grand Total | AF20: Makeup of Monthly Orders | AH20: Average Order Value | AJ20: Makeup of Monthly Orders | AL20: Average Order Value | AN20: Makeup of Monthly Orders | AP20: Average Order Value | AR20: Makeup of Monthly Orders | AT20: Average Order Value | AV20: Makeup of Monthly Orders | AX20: Average Order Value | AZ20: Makeup of Monthly Orders | BB20: Average Order Value | BD20: Makeup of Monthly Orders | BF20: Average Order Value | BH20: Makeup of Monthly Orders | BJ20: Average Order Value | BL20: Makeup of Monthly Orders | BN20: Average Order Value | BP20: Makeup of Monthly Orders | BR20: Average Order Value | BT20: Makeup of Monthly Orders | BV20: Average Order Value | BX20: Makeup of Monthly Orders | BZ20: Average Order Value
B21: Jan | C21: 4516614.8 | D21: 5215699.8 | E21: 9732314.7 | L21: Jan | M21: 102650.34 | N21: 102268.62 | O21: 102445.42 | R21: Above Average | S21: =Q11+Q12 -> 1115919.2 | T21: =R11+R12 -> 999602.36 | V21: Jan | W21: 724231.31 | X21: 924639.02 | Y21: 1648870.3 | AA21: Jan | AB21: 44 | AC21: 51 | AD21: 95 | AE21: Category | AF21: 2019 | AG21: 2020 | AH21: 2019 | AI21: 2020 | AJ21: 2019 | AK21: 2020 | AL21: 2019 | AM21: 2020 | AN21: 2019 | AO21: 2020 | AP21: 2019 | AQ21: 2020 | AR21: 2019 | AS21: 2020 | AT21: 2019 | AU21: 2020 | AV21: 2019 | AW21: 2020 | AX21: 2019 | AY21: 2020 | AZ21: 2019 | BA21: 2020 | BB21: 2019 | BC21: 2020 | BD21: 2019 | BE21: 2020 | BF21: 2019 | BG21: 2020 | BH21: 2019 | BI21: 2020 | BJ21: 2019 | BK21: 2020 | BL21: 2019 | BM21: 2020 | BN21: 2019 | BO21: 2020 | BP21: 2019 | BQ21: 2020 | BR21: 2019 | BS21: 2020 | BT21: 2019 | BU21: 2020 | BV21: 2019 | BW21: 2020 | BX21: 2019 | BY21: 2020 | BZ21: 2019 | CA21: 2020
B22: Feb | C22: 2895563.9 | D22: 1959413 | E22: 4854976.9 | L22: Feb | M22: 65808.27 | N22: 69979.036 | O22: 67430.235 | V22: Feb | W22: 493204.9 | X22: 315750.51 | Y22: 808955.41 | AA22: Feb | AB22: 44 | AC22: 28 | AD22: 72 | AE22: Accessories | AF22: 1 | AG22: 1 | AH22: 36747.24 | AI22: 107716.72 | AJ22: 1 | AL22: 60592.4 | AN22: 1 | AO22: 1 | AP22: 76543.36 | AQ22: 46311.34 | AR22: 2 | AS22: 1 | AT22: 82860.585 | AU22: 178465.4 | AW22: 1 | AY22: 121736.23 | AZ22: 3 | BA22: 1 | BB22: 183687.76 | BC22: 122035.93 | BD22: 3 | BE22: 3 | BF22: 211061.69 | BG22: 163701.1 | BI22: 5 | BK22: 144243.13 | BL22: 1 | BM22: 2 | BN22: 94925 | BO22: 167759.02 | BP22: 1 | BQ22: 3 | BR22: 62947.82 | BS22: 104771.91 | BT22: 1 | BU22: 1 | BV22: 102771.44 | BW22: 32695.37 | BX22: 2 | BZ22: 224160.12 | CB22: 35 | CC22: 134398.02
B23: Mar | C23: 2521828 | D23: 3579943.8 | E23: 6101771.8 | L23: Mar | M23: 61508 | N23: 68845.074 | O23: 65610.45 | V23: Mar | W23: 429420.62 | X23: 596343.77 | Y23: 1025764.4 | AA23: Mar | AB23: 41 | AC23: 52 | AD23: 93 | AE23: Appliances | AF23: 6 | AG23: 6 | AH23: 117021.59 | AI23: 100486.17 | AJ23: 3 | AK23: 5 | AL23: 85879.317 | AM23: 91053.23 | AN23: 4 | AO23: 8 | AP23: 57945.445 | AQ23: 66500.464 | AR23: 6 | AS23: 7 | AT23: 137186.63 | AU23: 77208.951 | AV23: 3 | AW23: 9 | AX23: 135488.12 | AY23: 121417.55 | AZ23: 6 | BA23: 7 | BB23: 159086.14 | BC23: 196754.84 | BD23: 3 | BE23: 6 | BF23: 111631.72 | BG23: 139828.24 | BH23: 3 | BI23: 5 | BJ23: 70026.167 | BK23: 99976.53 | BL23: 10 | BM23: 3 | BN23: 106811.08 | BO23: 108435.87 | BP23: 3 | BQ23: 7 | BR23: 95949.58 | BS23: 93236.027 | BT23: 8 | BU23: 1 | BV23: 62464.864 | BW23: 149938.36 | BX23: 7 | BY23: 5 | BZ23: 190897.68 | CA23: 191928.22 | CB23: 131 | CC23: 115569.99
B24: Apr | C24: 4172236.8 | D24: 4069097.8 | E24: 8241334.5 | L24: Apr | M24: 115895.47 | N24: 107081.52 | O24: 111369.39 | V24: Apr | W24: 692753.62 | X24: 696219.46 | Y24: 1388973.1 | AA24: Apr | AB24: 36 | AC24: 38 | AD24: 74 | AE24: Beauty | AF24: 4 | AG24: 6 | AH24: 91790.695 | AI24: 94858.863 | AJ24: 6 | AK24: 3 | AL24: 65861.493 | AM24: 93563.487 | AN24: 4 | AO24: 3 | AP24: 65300.442 | AQ24: 71895.297 | AR24: 3 | AS24: 5 | AT24: 120516.26 | AU24: 141973.84 | AV24: 6 | AW24: 7 | AX24: 84972.35 | AY24: 75271.331 | AZ24: 4 | BA24: 6 | BB24: 150137.92 | BC24: 152779.16 | BD24: 9 | BE24: 3 | BF24: 169797.17 | BG24: 86745.057 | BH24: 7 | BI24: 4 | BJ24: 108305.81 | BK24: 66760.777 | BL24: 7 | BM24: 5 | BN24: 113780.85 | BO24: 103028.73 | BP24: 4 | BQ24: 3 | BR24: 119230.14 | BS24: 35161.397 | BT24: 4 | BU24: 5 | BV24: 124370.89 | BW24: 92074.64 | BX24: 3 | BY24: 4 | BZ24: 220625.51 | CA24: 131820.42 | CB24: 115 | CC24: 109296.21
B25: May | C25: 3825682 | D25: 5537943.8 | E25: 9363625.7 | L25: May | M25: 100675.84 | N25: 100689.89 | O25: 100684.15 | V25: May | W25: 648258.3 | X25: 914851.65 | Y25: 1563109.9 | AA25: May | AB25: 38 | AC25: 55 | AD25: 93 | AE25: Books | AF25: 1 | AG25: 5 | AH25: 173478.65 | AI25: 108100.68 | AJ25: 6 | AK25: 4 | AL25: 60870.328 | AM25: 65042.295 | AN25: 6 | AO25: 4 | AP25: 65617.933 | AQ25: 89002.577 | AR25: 3 | AS25: 5 | AT25: 98486.76 | AU25: 107973.15 | AV25: 1 | AW25: 5 | AX25: 49374.25 | AY25: 101677.3 | AZ25: 3 | BA25: 4 | BB25: 212801.78 | BC25: 192073.39 | BD25: 4 | BE25: 5 | BF25: 156870.69 | BG25: 147342.85 | BH25: 3 | BI25: 10 | BJ25: 144892.47 | BK25: 93513.124 | BL25: 3 | BM25: 9 | BN25: 101838.26 | BO25: 115130.78 | BP25: 6 | BQ25: 9 | BR25: 93440.65 | BS25: 74464.538 | BT25: 4 | BU25: 6 | BV25: 87393.643 | BW25: 110007.76 | BX25: 6 | BY25: 5 | BZ25: 203710.5 | CA25: 150539.13 | CB25: 117 | CC25: 112649.39
B26: Jun | C26: 7692234.9 | D26: 7158137.9 | E26: 14850373 | L26: Jun | M26: 163664.57 | N26: 166468.32 | O26: 165004.14 | V26: Jun | W26: 1305278.4 | X26: 1187044.5 | Y26: 2492322.8 | AA26: Jun | AB26: 47 | AC26: 43 | AD26: 90 | AE26: Clothing | AF26: 8 | AG26: 8 | AH26: 115469.15 | AI26: 97928.024 | AJ26: 4 | AK26: 4 | AL26: 75589.667 | AM26: 42820.183 | AN26: 9 | AO26: 8 | AP26: 65406.664 | AQ26: 63947.143 | AR26: 5 | AS26: 9 | AT26: 109646 | AU26: 110384.25 | AV26: 11 | AW26: 9 | AX26: 100904.85 | AY26: 84757.166 | AZ26: 6 | BA26: 1 | BB26: 150438.86 | BC26: 128221.13 | BD26: 11 | BE26: 5 | BF26: 171360.68 | BG26: 184148.12 | BH26: 1 | BI26: 5 | BJ26: 135211.42 | BK26: 106541.36 | BL26: 10 | BM26: 3 | BN26: 121062.81 | BO26: 106943.16 | BP26: 8 | BQ26: 5 | BR26: 81444.029 | BS26: 108892.92 | BT26: 4 | BU26: 8 | BV26: 102255.71 | BW26: 93380.943 | BX26: 8 | BY26: 5 | BZ26: 190958.52 | CA26: 210095.71 | CB26: 155 | CC26: 113946.34
B27: Jul | C27: 6638609.2 | D27: 5242556.5 | E27: 11881166 | L27: Jul | M27: 165965.23 | N27: 145626.57 | O27: 156331.13 | V27: Jul | W27: 1084227.4 | X27: 839989.39 | Y27: 1924216.8 | AA27: Jul | AB27: 40 | AC27: 36 | AD27: 76 | AE27: Electronics | AF27: 11 | AG27: 7 | AH27: 72315.763 | AI27: 84007.367 | AJ27: 7 | AK27: 4 | AL27: 60647.299 | AM27: 78687.152 | AN27: 4 | AO27: 10 | AP27: 61569.58 | AQ27: 65375.515 | AR27: 4 | AS27: 6 | AT27: 115434.62 | AU27: 97912.687 | AV27: 5 | AW27: 4 | AX27: 127419.89 | AY27: 136289.64 | AZ27: 7 | BA27: 8 | BB27: 141676.95 | BC27: 178279.6 | BD27: 3 | BE27: 5 | BF27: 145461.8 | BG27: 153067.07 | BH27: 1 | BI27: 4 | BJ27: 95966.17 | BK27: 78238.012 | BL27: 6 | BM27: 2 | BN27: 77519.912 | BO27: 123539.97 | BP27: 8 | BQ27: 5 | BR27: 119296.13 | BS27: 121334.24 | BT27: 5 | BU27: 7 | BV27: 78546.752 | BW27: 125092.66 | BX27: 7 | BY27: 4 | BZ27: 136763.78 | CA27: 175045.98 | CB27: 134 | CC27: 108075.21
B28: Aug | C28: 3437450.1 | D28: 4714525.2 | E28: 8151975.3 | L28: Aug | M28: 110885.49 | N28: 104767.23 | O28: 107262.83 | V28: Aug | W28: 580316.12 | X28: 768976.36 | Y28: 1349292.5 | AA28: Aug | AB28: 31 | AC28: 45 | AD28: 76 | AE28: Games | AF28: 6 | AG28: 9 | AH28: 121640.22 | AI28: 108595.65 | AJ28: 8 | AK28: 1 | AL28: 62735.369 | AM28: 61374.06 | AN28: 7 | AO28: 2 | AP28: 44769.331 | AQ28: 60683.66 | AR28: 10 | AS28: 3 | AT28: 118033.41 | AU28: 105187.08 | AV28: 3 | AW28: 13 | AX28: 62095.323 | AY28: 92771.99 | AZ28: 7 | BA28: 7 | BB28: 164179.56 | BC28: 131738.21 | BD28: 4 | BE28: 5 | BF28: 170397.46 | BG28: 188381.41 | BH28: 9 | BI28: 5 | BJ28: 129878.24 | BK28: 114048.95 | BL28: 6 | BM28: 5 | BN28: 71867.012 | BO28: 101369.37 | BP28: 6 | BQ28: 6 | BR28: 101941.6 | BS28: 102306.3 | BT28: 5 | BU28: 7 | BV28: 92824.324 | BW28: 108971.55 | BX28: 3 | BY28: 2 | BZ28: 235222.88 | CA28: 98998.45 | CB28: 139 | CC28: 110227.51
B29: Sep | C29: 4870060.5 | D29: 3778141.4 | E29: 8648201.9 | L29: Sep | M29: 99388.991 | N29: 111121.81 | O29: 104195.2 | V29: Sep | W29: 788191.58 | X29: 663167.65 | Y29: 1451359.2 | AA29: Sep | AB29: 49 | AC29: 34 | AD29: 83 | AE29: Other | AF29: 1 | AG29: 2 | AH29: 45256.74 | AI29: 119030.48 | AJ29: 1 | AK29: 1 | AL29: 24787.65 | AM29: 18897.97 | AO29: 4 | AQ29: 79785.75 | AV29: 2 | AW29: 3 | AX29: 50553.785 | AY29: 90071.207 | AZ29: 2 | BA29: 2 | BB29: 178267.98 | BC29: 179596.14 | BD29: 1 | BE29: 1 | BF29: 177802.7 | BG29: 45725.53 | BI29: 1 | BK29: 144530.35 | BL29: 2 | BM29: 1 | BN29: 55811.585 | BO29: 70657.26 | BQ29: 1 | BS29: 57333.85 | BU29: 2 | BW29: 123783.05 | BX29: 1 | BY29: 1 | BZ29: 383996.76 | CA29: 290551.74 | CB29: 29 | CC29: 112516.66
B30: Oct | C30: 4372149.5 | D30: 4869726.8 | E30: 9241876.4 | L30: Oct | M30: 101677.9 | N30: 97394.537 | O30: 99375.015 | V30: Oct | W30: 744434.48 | X30: 839700.96 | Y30: 1584135.4 | AA30: Oct | AB30: 43 | AC30: 50 | AD30: 93 | AE30: Outdoors | AF30: 1 | AG30: 3 | AH30: 103874.1 | AI30: 143616.59 | AJ30: 2 | AK30: 3 | AL30: 85145.885 | AM30: 61360.657 | AN30: 1 | AO30: 5 | AP30: 83141.47 | AQ30: 75357.568 | AS30: 1 | AU30: 152522.94 | AV30: 2 | AW30: 2 | AX30: 154369.25 | AY30: 118694.04 | AZ30: 2 | BA30: 4 | BB30: 110386.6 | BC30: 200705.4 | BD30: 1 | BE30: 1 | BF30: 77522.57 | BG30: 152676.77 | BH30: 3 | BI30: 1 | BJ30: 79821.24 | BK30: 87085.71 | BL30: 4 | BM30: 2 | BN30: 96617.792 | BO30: 117848.9 | BP30: 3 | BQ30: 2 | BR30: 117076.09 | BS30: 90997.21 | BU30: 3 | BW30: 70603.933 | BX30: 2 | BY30: 2 | BZ30: 180423.05 | CA30: 291502.93 | CB30: 50 | CC30: 118781.51
B31: Nov | C31: 2961318.6 | D31: 4734730.1 | E31: 7696048.7 | L31: Nov | M31: 89736.926 | N31: 105216.22 | O31: 98667.29 | V31: Nov | W31: 482287.62 | X31: 787670.37 | Y31: 1269958 | AA31: Nov | AB31: 33 | AC31: 45 | AD31: 78 | AE31: Smartphones | AF31: 5 | AG31: 4 | AH31: 127779.58 | AI31: 94415.525 | AJ31: 6 | AK31: 3 | AL31: 65515.082 | AM31: 70967.957 | AN31: 5 | AO31: 7 | AP31: 65425.678 | AQ31: 63900.306 | AR31: 3 | AS31: 1 | AT31: 112028.06 | AU31: 51416.24 | AV31: 5 | AW31: 2 | AX31: 103364.88 | AY31: 133276.58 | AZ31: 7 | BA31: 3 | BB31: 189537.14 | BC31: 111736.73 | BD31: 1 | BE31: 2 | BF31: 256603.66 | BG31: 44574.515 | BH31: 4 | BI31: 5 | BJ31: 98752.03 | BK31: 128746.58 | BM31: 2 | BO31: 92441.875 | BP31: 4 | BQ31: 9 | BR31: 103747.34 | BS31: 124754.67 | BT31: 2 | BU31: 5 | BV31: 122945.93 | BW31: 117360.34 | BX31: 5 | BY31: 5 | BZ31: 221901.28 | CA31: 164492.55 | CB31: 95 | CC31: 116859.52
B32: Dec | C32: 8713776 | D32: 5884298.3 | E32: 14598074 | L32: Dec | M32: 198040.36 | N32: 178312.07 | O32: 189585.38 | V32: Dec | W32: 1514673.6 | X32: 970796.22 | Y32: 2485469.8 | AA32: Dec | AB32: 44 | AC32: 33 | AD32: 77 | AE32: Grand Total | AF32: 44 | AG32: 51 | AH32: 102650.34 | AI32: 102268.62 | AJ32: 44 | AK32: 28 | AL32: 65808.27 | AM32: 69979.036 | AN32: 41 | AO32: 52 | AP32: 61508 | AQ32: 68845.074 | AR32: 36 | AS32: 38 | AT32: 115895.47 | AU32: 107081.52 | AV32: 38 | AW32: 55 | AX32: 100675.84 | AY32: 100689.89 | AZ32: 47 | BA32: 43 | BB32: 163664.57 | BC32: 166468.32 | BD32: 40 | BE32: 36 | BF32: 165965.23 | BG32: 145626.57 | BH32: 31 | BI32: 45 | BJ32: 110885.49 | BK32: 104767.23 | BL32: 49 | BM32: 34 | BN32: 99388.991 | BO32: 111121.81 | BP32: 43 | BQ32: 50 | BR32: 101677.9 | BS32: 97394.537 | BT32: 33 | BU32: 45 | BV32: 89736.926 | BW32: 105216.22 | BX32: 44 | BY32: 33 | BZ32: 198040.36 | CA32: 178312.07 | CB32: 1000 | CC32: 113361.74
B33: Grand Total | C33: 56617524 | D33: 56744214 | E33: 1.1336174e+08 | L33: Grand Total | M33: 115545.97 | N33: 111263.17 | O33: 113361.74 | V33: Grand Total | W33: 9487277.9 | X33: 9505149.8 | Y33: 18992428 | AA33: Grand Total | AB33: 490 | AC33: 510 | AD33: 1000
B36: Avg Profit per Sale | C36: Customer Analysis | G36: Difference in share of profits and sales | H36: Column Labels
B37: Customer | C37: 2019 | D37: 2020 | E37: Grand Total | G37: Row Labels | H37: 2019 | I37: 2020 | J37: Grand Total | P37: Profit Margin by Month | Q37: Column Labels
B38: Jan | C38: 16459.803 | D38: 18130.177 | E38: 17356.53 | G38: Jan | H38: -0.0058673652 | I38: -0.0023153856 | J38: -0.0081827508 | P38: Row Labels | Q38: 2019 | R38: 2020 | S38: Grand Total | AB38: Accessories
B39: Feb | C39: 11209.202 | D39: 11276.804 | E39: 11235.492 | G39: Feb | H39: -0.018031498 | I39: -0.011374926 | J39: -0.029406424 | P39: Jan | Q39: 0.16034826 | R39: 0.17727995 | S39: 0.16942222 | AB39: Appliances
B40: Mar | C40: 10473.674 | D40: 11468.149 | E40: 11029.725 | G40: Mar | H40: -0.018389904 | I40: -0.020600972 | J40: -0.038990876 | P40: Feb | Q40: 0.17033121 | R40: 0.16114546 | S40: 0.16662395 | AB40: Beauty
B41: Apr | C41: 19243.156 | D41: 18321.565 | E41: 18769.906 | G41: Apr | H41: 0.00047525373 | I41: -0.0013422609 | J41: -0.00086700718 | P41: Mar | Q41: 0.17028149 | R41: 0.16657909 | S41: 0.16810927 | AB41: Books
B42: May | C42: 17059.429 | D42: 16633.666 | E42: 16807.634 | G42: May | H42: -0.0038675389 | I42: -0.0068307157 | J42: -0.010698255 | P42: Apr | Q42: 0.1660389 | R42: 0.17109922 | S42: 0.1685374 | AB42: Clothing
B43: Jun | C43: 27771.88 | D43: 27605.685 | E43: 27692.476 | G43: Jun | H43: 0.021726252 | I43: 0.019500934 | J43: 0.041227186 | P43: May | Q43: 0.16944908 | R43: 0.16519699 | S43: 0.16693426 | AB43: Electronics
B44: Jul | C44: 27105.685 | D44: 23333.039 | E44: 25318.642 | G44: Jul | H44: 0.017087352 | I44: 0.0082275944 | J44: 0.025314947 | P44: Jun | Q44: 0.16968779 | R44: 0.16583146 | S44: 0.16782898 | AB44: Games
B45: Aug | C45: 18719.875 | D45: 17088.364 | E45: 17753.848 | G45: Aug | H45: -0.00044486884 | I45: -0.0045114236 | J45: -0.0049562925 | P45: Jul | Q45: 0.16332147 | R45: 0.16022515 | S45: 0.16195522 | AB45: Other
B46: Sep | C46: 16085.542 | D46: 19504.931 | E46: 17486.256 | G46: Sep | H46: -0.0074996931 | I46: 0.00091747657 | J46: -0.0065822165 | P46: Aug | Q46: 0.16882168 | R46: 0.16310791 | S46: 0.16551724 | AB46: Outdoors
B47: Oct | C47: 17312.43 | D47: 16794.019 | E47: 17033.714 | G47: Oct | H47: -0.0038036165 | I47: -0.0057875922 | J47: -0.0095912087 | P47: Sep | Q47: 0.16184431 | R47: 0.17552748 | S47: 0.16782208 | AB47: Smartphones
B48: Nov | C48: 14614.776 | D48: 17503.786 | E48: 16281.513 | G48: Nov | H48: -0.0076063206 | I48: -0.0035271361 | J48: -0.011133457 | P48: Oct | Q48: 0.17026739 | R48: 0.17243287 | S48: 0.17140842
B49: Dec | C49: 34424.399 | D49: 29418.067 | E49: 32278.828 | G49: Dec | H49: 0.035751445 | I49: 0.018114909 | J49: 0.053866355 | P49: Nov | Q49: 0.16286246 | R49: 0.16636014 | S49: 0.16501429
B50: Grand Total | C50: 19361.792 | D50: 18637.549 | E50: 18992.428 | G50: Grand Total | H50: 0.0095294983 | I50: -0.0095294983 | J50: 0 | P50: Dec | Q50: 0.17382517 | R50: 0.1649808 | S50: 0.17026011
P51: Grand Total | Q51: 0.16756787 | R51: 0.1675087 | S51: 0.16753825
AJ52: =CORREL(AH57:AH131,AG57:AG131) -> 0.018987969 | AK52: Orders and avg profit | AL52: overall
B53: Row Labels | C53: Average Order Value | D53: Average Profit | AJ53: =CORREL(AH57:AH131,AF57:AF131) -> 0.95783385 | AK53: Order val and avg profit
B54: 2019 | AI54: Appliances | AJ54: =CORREL(AF57:AF131,AG57:AG131) -> 0.034433589 | AK54: Orders and order val
B55: Jan | C55: 102650.34 | D55: 16459.803 | AC55: =_xlfn.STDEV.P(AF54:AF128) -> 22916.097 | AO55: Orders and avg order val > 20 orders | AP55: Orders and avg profit > 20 orders | AQ55: Avg Order Val and Avg Profit
B56: Feb | C56: 65808.27 | D56: 11209.202 | AC56: =MAX(AF54:AF128)-MIN(AF54:AF128) -> 135828.94 | AE56: Customers average order val in each cat | AF56: Average Order Value | AG56: Orders | AH56: Average of Profit | AJ56: Customer | AK56: Avg Order Val | AL56: Orders | AM56: Avg Profit | AO56: =CORREL(AK57:AK83,AL57:AL83) -> 0.36633918 | AP56: =CORREL(AL57:AL66,AM57:AM66) -> 0.45947906 | AQ56: =CORREL(AK57:AK66,AM57:AM66) -> 0.9369719
B57: Mar | C57: 61508 | D57: 10473.674 | AE57: Abbott, Roberts and Torp | AF57: 95588.925 | AG57: 2 | AH57: 13607.12 | AJ57: {=_xlfn._xlws.FILTER(AE57:AH131,AG57:AG131>20)} -> Dickinson, Hyatt and Berge | AK57: 112780.43 | AL57: 24 | AM57: 18969.824
B58: Apr | C58: 115895.47 | D58: 19243.156 | AE58: Altenwerth-Konopelski | AF58: 126210.42 | AG58: 20 | AH58: 20596.088 | AJ58: Hessel-Stiedemann | AK58: 118401.16 | AL58: 55 | AM58: 19196.303
B59: May | C59: 100675.84 | D59: 17059.429 | AE59: Armstrong-Little | AF59: 108330.92 | AG59: 19 | AH59: 18170.767 | AJ59: Johns and Sons | AK59: 115213.08 | AL59: 142 | AM59: 19860.203
B60: Jun | C60: 163664.57 | D60: 27771.88 | AE60: Bashirian, Okuneva and Bechtelar | AF60: 104150.05 | AG60: 13 | AH60: 17593.625 | AJ60: Kihn Inc | AK60: 91057.222 | AL60: 22 | AM60: 14477
B61: Jul | C61: 165965.23 | D61: 27105.685 | AE61: Baumbach Group | AF61: 85769.965 | AG61: 2 | AH61: 14734.2 | AJ61: Larkin-Collier | AK61: 122216.66 | AL61: 21 | AM61: 19083.672
B62: Aug | C62: 110885.49 | D62: 18719.875 | AE62: Christiansen, Donnelly and Bechtelar | AF62: 129885.28 | AG62: 15 | AH62: 22228.51 | AJ62: Murray, Reichel and Nolan | AK62: 84271.484 | AL62: 23 | AM62: 14458.847
B63: Sep | C63: 99388.991 | D63: 16085.542 | AE63: Connelly-Mohr | AF63: 126190.88 | AG63: 5 | AH63: 21623.364 | AJ63: Rowe, Hermiston and Kessler | AK63: 105114.77 | AL63: 22 | AM63: 18338.41
B64: Oct | C64: 101677.9 | D64: 17312.43 | AE64: Considine-Fisher | AF64: 120611.02 | AG64: 11 | AH64: 19912.483 | AJ64: Swaniawski, Runolfsson and Green | AK64: 100245.38 | AL64: 25 | AM64: 16364.248
B65: Nov | C65: 89736.926 | D65: 14614.776 | AE65: Corwin and Sons | AF65: 123737.89 | AG65: 15 | AH65: 21043.157 | AJ65: Tillman and Sons | AK65: 99014.511 | AL65: 21 | AM65: 16196.407
B66: Dec | C66: 198040.36 | D66: 34424.399 | AE66: Dibbert Inc | AF66: 104188.68 | AG66: 18 | AH66: 16254.1 | AJ66: Wisoky Inc | AK66: 108462.59 | AL66: 21 | AM66: 18932.587
B67: 2020 | AE67: Dickinson, Hyatt and Berge | AF67: 112780.43 | AG67: 24 | AH67: 18969.824
B68: Jan | C68: 102268.62 | D68: 18130.177 | AE68: Farrell, Swaniawski and Crist | AF68: 94214.645 | AG68: 17 | AH68: 16201.327
B69: Feb | C69: 69979.036 | D69: 11276.804 | AE69: Fisher, Morar and Skiles | AF69: 96254.501 | AG69: 9 | AH69: 16060.798
B70: Mar | C70: 68845.074 | D70: 11468.149 | AE70: Franecki-White | AF70: 125235.22 | AG70: 7 | AH70: 22616.336
B71: Apr | C71: 107081.52 | D71: 18321.565 | AE71: Friesen and Sons | AF71: 105464.75 | AG71: 6 | AH71: 16678.005
B72: May | C72: 100689.89 | D72: 16633.666 | AE72: Friesen-Rath | AF72: 110306.75 | AG72: 19 | AH72: 19132.837
B73: Jun | C73: 166468.32 | D73: 27605.685 | AE73: Gislason-Stanton | AF73: 118254.4 | AG73: 17 | AH73: 19516.626
B74: Jul | C74: 145626.57 | D74: 23333.039 | AE74: Gleichner-Green | AF74: 154762.58 | AG74: 3 | AH74: 26234.603
B75: Aug | C75: 104767.23 | D75: 17088.364 | AE75: Goldner-Dibbert | AF75: 100941.25 | AG75: 9 | AH75: 15782.092
B76: Sep | C76: 111121.81 | D76: 19504.931 | AE76: Gorczany-Lehner | AF76: 33724.53 | AG76: 1 | AH76: 6954
B77: Oct | C77: 97394.537 | D77: 16794.019 | AE77: Hamill, Kulas and Roob | AF77: 110790.79 | AG77: 13 | AH77: 18364.645
B78: Nov | C78: 105216.22 | D78: 17503.786 | AE78: Hane Inc | AF78: 115277.35 | AG78: 4 | AH78: 20294.27
B79: Dec | C79: 178312.07 | D79: 29418.067 | AE79: Hartmann, Hane and Pfannerstill | AF79: 111761.35 | AG79: 9 | AH79: 20009.624
B80: Grand Total | C80: 113361.74 | D80: 18992.428 | AE80: Heaney, Gulgowski and Kshlerin | AF80: 110552.55 | AG80: 4 | AH80: 17634.238
AE81: Hegmann Group | AF81: 124595.81 | AG81: 15 | AH81: 20745.871
AE82: Hermiston, Simonis and Wisoky | AF82: 107191.42 | AG82: 10 | AH82: 17858.762
AE83: Hessel-Stiedemann | AF83: 118401.16 | AG83: 55 | AH83: 19196.303
AE84: Hilll-Vandervort | AF84: 114416.18 | AG84: 16 | AH84: 17648.25
AE85: Homenick-Marvin | AF85: 85186.813 | AG85: 6 | AH85: 13242
AE86: Jacobson, Marvin and Brown | AF86: 155424 | AG86: 7 | AH86: 26353.47
AE87: Johns and Sons | AF87: 115213.08 | AG87: 142 | AH87: 19860.203
AE88: Keeling, Monahan and Pollich | AF88: 126333.61 | AG88: 11 | AH88: 20617.315
AE89: Kihn Inc | AF89: 91057.222 | AG89: 22 | AH89: 14477
AE90: Kirlin and Sons | AF90: 123571.41 | AG90: 12 | AH90: 19625.865
AE91: Konopelski LLC | AF91: 106182.7 | AG91: 5 | AH91: 21213.614
AE92: Labadie and Sons | AF92: 113961.31 | AG92: 19 | AH92: 18453.858
... AE132: Grand Total | AF132: 113361.74 | AG132: 1000 | AH132: 18992.428

Sheet MOMP
I1: More Orders = More Profit?
D2: This dashboard aims to look assess whether more orders drives profits or if there is something else in play. Orders placed between the start of 2019 and end of 2020 are included

Sheet Sales Rep Tables
B2: Total Profit | C2: Year | J2: Total Sales | K2: Year | P2: Year | Q2: 2019 | R2: 2020 | S2: Total | X2: Sum of order_value_GBP | Y2: Column Labels | AC2: Sales | AD2: Avg Profit Per Sale | AE2: Outlier removed
B3: Sales Rep Performance | C3: 2019 | D3: 2020 | E3: Grand Total | J3: Sales Rep | K3: 2019 | L3: 2020 | M3: Grand Total | P3: Avg Revenue per Sales Rep | Q3: =AVERAGE(Y4:Y38) -> 1665221.3 | R3: =AVERAGE(Z4:Z38) -> 1621263.3 | S3: =AVERAGE(AA4:AA38) -> 3238906.8 | X3: Row Labels | Y3: 2019 | Z3: 2020 | AA3: Grand Total | AC3: 40 | AD3: 18553.632
B4: Alyosha Meah | C4: 488522.9 | D4: 253622.37 | E4: 742145.27 | J4: Alyosha Meah | K4: 26 | L4: 14 | M4: 40 | P4: Avg Profit per Sales Rep | Q4: =AVERAGE(C4:C38) -> 279037.59 | R4: =AVERAGE(D4:D38) -> 271575.71 | S4: =AVERAGE($E$4:$E$38) -> 542640.79 | X4: Alyosha Meah | Y4: 3030652 | Z4: 1513936.9 | AA4: 4544588.9 | AC4: 56 | AD4: 19614.378
B5: Amelina Piscopiello | C5: 670413.28 | D5: 427991.86 | E5: 1098405.1 | J5: Amelina Piscopiello | K5: 32 | L5: 24 | M5: 56 | P5: STD of revenue per sales rep | Q5: =_xlfn.STDEV.P(Y4:Y38) -> 991635.71 | R5: =_xlfn.STDEV.P(Z4:Z38) -> 1000274.8 | S5: =_xlfn.STDEV.P(AA4:AA38) -> 1872464.1 | X5: Amelina Piscopiello | Y5: 4062022 | Z5: 2593138.1 | AA5: 6655160.2 | AC5: 36 | AD5: 17251.023
B6: Anita Woakes | C6: 309538.55 | D6: 311498.26 | E6: 621036.81 | J6: Anita Woakes | K6: 18 | L6: 18 | M6: 36 | P6: STD of profit per sales rep | Q6: =_xlfn.STDEV.P(C4:C38) -> 164910.74 | R6: =_xlfn.STDEV.P(D4:D38) -> 171210.7 | S6: =_xlfn.STDEV.P(E4:E38) -> 315823.32 | X6: Anita Woakes | Y6: 1793567.5 | Z6: 1823275.9 | AA6: 3616843.4 | AC6: 52 | AD6: 18242.499
B7: Aurelie Wren | C7: 372518.26 | D7: 576091.69 | E7: 948609.95 | J7: Aurelie Wren | K7: 23 | L7: 29 | M7: 52 | P7: Avg Profit per Sales Rep per sale | Q7: =AVERAGE(E125:E159) -> 18999.228 | R7: =AVERAGE(F125:F159) -> 17789.375 | S7: =AVERAGE(G125:G159) -> 18364.654 | X7: Aurelie Wren | Y7: 2185327.9 | Z7: 3303225.3 | AA7: 5488553.1 | AC7: 43 | AD7: 18656.655
B8: Avrit Chanders | C8: 355420.74 | D8: 446815.42 | E8: 802236.16 | J8: Avrit Chanders | K8: 18 | L8: 25 | M8: 43 | X8: Avrit Chanders | Y8: 2039486 | Z8: 2673265.4 | AA8: 4712751.4 | AC8: 2 | AD8: 17859.19
B9: Bank Coumbe | D9: 35718.38 | E9: 35718.38 | J9: Bank Coumbe | L9: 2 | M9: 2 | X9: Bank Coumbe | Z9: 190166.35 | AA9: 190166.35 | AC9: 15 | AD9: 22229.617
B10: Bernadine Fullagar | C10: 188754.79 | D10: 144689.47 | E10: 333444.26 | J10: Bernadine Fullagar | K10: 7 | L10: 8 | M10: 15 | X10: Bernadine Fullagar | Y10: 1068607 | Z10: 814589.38 | AA10: 1883196.4 | AC10: 9 | AD10: 19239.037
B11: Bertha Walbrook | C11: 123282.47 | D11: 49868.86 | E11: 173151.33 | J11: Bertha Walbrook | K11: 6 | L11: 3 | M11: 9 | X11: Bertha Walbrook | Y11: 745852.74 | Z11: 319711.14 | AA11: 1065563.9 | AC11: 41 | AD11: 19592.632
B12: Brynn Dempster | C12: 219609.35 | D12: 583688.57 | E12: 803297.92 | J12: Brynn Dempster | K12: 13 | L12: 28 | M12: 41 | X12: Brynn Dempster | Y12: 1305050.1 | Z12: 3453981.5 | AA12: 4759031.6 | AC12: 23 | AD12: 20529.511
B13: Bunnie Tonbridge | C13: 234503.02 | D13: 237675.73 | E13: 472178.75 | J13: Bunnie Tonbridge | K13: 8 | L13: 15 | M13: 23 | X13: Bunnie Tonbridge | Y13: 1272857.8 | Z13: 1445013.9 | AA13: 2717871.7 | AC13: 29 | AD13: 16436.134
B14: Caro Morfield | C14: 210665.29 | D14: 265982.59 | E14: 476647.88 | J14: Caro Morfield | K14: 13 | L14: 16 | M14: 29 | X14: Caro Morfield | Y14: 1328012.7 | Z14: 1630841.5 | AA14: 2958854.3 | AC14: 6 | AD14: 13931.777
B15: Case Desorts | C15: 49906.69 | D15: 33683.97 | E15: 83590.66 | J15: Case Desorts | K15: 3 | L15: 3 | M15: 6 | X15: Case Desorts | Y15: 297172.76 | Z15: 193787.99 | AA15: 490960.75 | AC15: 24 | AD15: 19414.931
B16: Casie MacBain | C16: 232393.73 | D16: 233564.62 | E16: 465958.35 | J16: Casie MacBain | K16: 11 | L16: 13 | M16: 24 | X16: Casie MacBain | Y16: 1409637.3 | Z16: 1384411.2 | AA16: 2794048.5 | AC16: 6 | AD16: 15738.88
B17: Cobby Andersen | C17: 7578.52 | D17: 42183.52 | E17: 49762.04 | J17: Cobby Andersen | K17: 1 | L17: 4 | M17: 5 | X17: Cobby Andersen | Y17: 39287.29 | Z17: 232955.47 | AA17: 272242.76 | AC17: 53 | AD17: 22405.31
B18: Collin Mackness | C18: 38458.04 | D18: 55975.24 | E18: 94433.28 | J18: Collin Mackness | K18: 2 | L18: 4 | M18: 6 | X18: Collin Mackness | Y18: 228554.31 | Z18: 380415.65 | AA18: 608969.96 | AC18: 47 | AD18: 17871.528
B19: Corene Shirer | C19: 522584.97 | D19: 664896.46 | E19: 1187481.4 | J19: Corene Shirer | K19: 23 | L19: 30 | M19: 53 | X19: Corene Shirer | Y19: 2987701.2 | Z19: 3909351.9 | AA19: 6897053 | AC19: 37 | AD19: 19501.181
B20: Crysta Halls | C20: 459517.15 | D20: 380444.65 | E20: 839961.8 | J20: Crysta Halls | K20: 27 | L20: 20 | M20: 47 | X20: Crysta Halls | Y20: 2878091.5 | Z20: 2276511.2 | AA20: 5154602.7 | AC20: 52 | AD20: 19603.876
B21: Genevra Charrisson | C21: 420564.16 | D21: 300979.55 | E21: 721543.71 | J21: Genevra Charrisson | K21: 21 | L21: 16 | M21: 37 | X21: Genevra Charrisson | Y21: 2436958.6 | Z21: 1896682.9 | AA21: 4333641.5 | AC21: 26 | AD21: 19592.159
... B36: Tarrah Castelletti | C36: 456904.67 | D36: 332742.3 | E36: 789646.97 | J36: Tarrah Castelletti | K36: 21 | L36: 17 | M36: 38 | X36: Tarrah Castelletti | Y36: 2587900.9 | Z36: 1979274.6 | AA36: 4567175.5 | AC36: 38 | AD36: 21608.279
B37: Wat Bowkley | C37: 210956.79 | D37: 244950.15 | E37: 455906.94 | J37: Wat Bowkley | K37: 12 | L37: 11 | M37: 23 | X37: Wat Bowkley | Y37: 1217596.7 | Z37: 1620122.6 | AA37: 2837719.3
B38: Winny Agnolo | C38: 359330.26 | D38: 461784.36 | E38: 821114.62 | J38: Winny Agnolo | K38: 16 | L38: 22 | M38: 38 | X38: Winny Agnolo | Y38: 2025308.2 | Z38: 2650229.6 | AA38: 4675537.8
B39: Grand Total | C39: 9487277.9 | D39: 9505149.8 | E39: 18992428 | J39: Grand Total | K39: 490 | L39: 510 | M39: 1000 | X39: Grand Total | Y39: 56617524 | Z39: 56744214 | AA39: 1.1336174e+08
F40: Sales | G40: Avg Profit per Sale
B41: Sales Rep | C41: Avg Profit per Sale | D41: Number of Sales | F41: 40 | G41: 18553.632
B42: Alyosha Meah | C42: 18553.632 | D42: 40 | F42: 56 | G42: 19614.378 | K42: 40
B43: Amelina Piscopiello | C43: 19614.378 | D43: 56 | F43: 36 | G43: 17251.023 | K43: 56
B44: Anita Woakes | C44: 17251.023 | D44: 36 | F44: 52 | G44: 18242.499 | K44: 36
B45: Aurelie Wren | C45: 18242.499 | D45: 52 | F45: 43 | G45: 18656.655 | I45: Category | J45: Avg Profit per Sale | K45: 52 | L45: Sales per Category | M45: Category
B46: Avrit Chanders | C46: 18656.655 | D46: 43 | F46: 2 | G46: 17859.19 | I46: Accessories | J46: 22397.038 | K46: 43 | L46: Sales Rep | M46: Accessories | N46: Appliances | O46: Beauty | P46: Books | Q46: Clothing | R46: Electronics | S46: Games | T46: Other | U46: Outdoors | V46: Smartphones | W46: Grand Total | Y46: Sales Rep | Z46: Accessories | AA46: Appliances | AB46: Beauty | AC46: Books | AD46: Clothing | AE46: Electronics | AF46: Games | AG46: Other | AH46: Outdoors | AI46: Smartphones
B47: Bank Coumbe | C47: 17859.19 | D47: 2 | F47: 15 | G47: 22229.617 | I47: Appliances | J47: 19350.224 | K47: 2 | L47: Alyosha Meah | M47: 1 | N47: 4 | O47: 4 | P47: 4 | Q47: 9 | R47: 4 | S47: 6 | T47: 3 | U47: 1 | V47: 4 | W47: 40 | Y47: Alyosha Meah | Z47: =SUMIFS(Sales_Export_2019_2020__2[[profit]:[profit]],Sales_Export_2019_2020__2[[sales_rep]:[sales_rep]],$Y47,Sales_Export_2019_2020__2[[category]:[category]],Z$46) -> 15023.86 | AA47: =SUMIFS(Sales_Export_2019_2020__2[[profit]:[profit]],Sales_Export_2019_2020__2[[sales_rep]:[sales_rep]],$Y47,Sales_Export_2019_2020__2[[category]:[category]],AA$46) -> 45219.24 | AB47: =SUMIFS(Sales_Export_2019_2020__2[[profit]:[profit]],Sales_Export_2019_2020__2[[sales_rep]:[sales_rep]],$Y47,Sales_Export_2019_2020__2[[category]:[category]],AB$46) -> 116128.08 | AC47: =SUMIFS(Sales_Export_2019_2020__2[[profit]:[profit]],Sales_Export_2019_2020__2[[sales_rep]:[sales_rep]],$Y47,Sales_Export_2019_2020__2[[category]:[category]],AC$46) -> 60245.33 | AD47: =SUMIFS(Sales_Export_2019_2020__2[[profit]:[profit]],Sales_Export_2019_2020__2[[sales_rep]:[sales_rep]],$Y47,Sales_Export_2019_2020__2[[category]:[category]],AD$46) -> 139845.32 | AE47: =SUMIFS(Sales_Export_2019_2020__2[[profit]:[profit]],Sales_Export_2019_2020__2[[sales_rep]:[sales_rep]],$Y47,Sales_Export_2019_2020__2[[category]:[category]],AE$46) -> 83679.84 | AF47: =SUMIFS(Sales_Export_2019_2020__2[[profit]:[profit]],Sales_Export_2019_2020__2[[sales_rep]:[sales_rep]],$Y47,Sales_Export_2019_2020__2[[category]:[category]],AF$46) -> 75415.64 | AG47: =SUMIFS(Sales_Export_2019_2020__2[[profit]:[profit]],Sales_Export_2019_2020__2[[sales_rep]:[sales_rep]],$Y47,Sales_Export_2019_2020__2[[category]:[category]],AG$46) -> 40785.12 | ... AI47: =SUMIFS(Sales_Export_2019_2020__2[[profit]:[profit]],Sales_Export_2019_2020__2[[sales_rep]:[sales_rep]],$Y47,Sales_Export_2019_2020__2[[category]:[category]],AI$46) -> 132838.37
B48: Bernadine Fullagar | C48: 22229.617 | D48: 15 | F48: 9 | G48: 19239.037 | I48: Beauty | J48: 18421.108 | K48: 15 | L48: Amelina Piscopiello | N48: 10 | O48: 3 | P48: 4 | Q48: 9 | R48: 10 | S48: 7 | T48: 4 | U48: 2 | V48: 7 | W48: 56 | Y48: Amelina Piscopiello | Z48: =SUMIFS(Sales_Export_2019_2020__2[[profit]:[profit]],Sales_Export_2019_2020__2[[sales_rep]:[sales_rep]],$Y48,Sales_Export_2019_2020__2[[category]:[category]],Z$46) -> 0 | AA48: =SUMIFS(Sales_Export_2019_2020__2[[profit]:[profit]],Sales_Export_2019_2020__2[[sales_rep]:[sales_rep]],$Y48,Sales_Export_2019_2020__2[[category]:[category]],AA$46) -> 199939.76 | AB48: =SUMIFS(Sales_Export_2019_2020__2[[profit]:[profit]],Sales_Export_2019_2020__2[[sales_rep]:[sales_rep]],$Y48,Sales_Export_2019_2020__2[[category]:[category]],AB$46) -> 53188.3 | AC48: =SUMIFS(Sales_Export_2019_2020__2[[profit]:[profit]],Sales_Export_2019_2020__2[[sales_rep]:[sales_rep]],$Y48,Sales_Export_2019_2020__2[[category]:[category]],AC$46) -> 87797.88 | AD48: =SUMIFS(Sales_Export_2019_2020__2[[profit]:[profit]],Sales_Export_2019_2020__2[[sales_rep]:[sales_rep]],$Y48,Sales_Export_2019_2020__2[[category]:[category]],AD$46) -> 211021.77 | AE48: =SUMIFS(Sales_Export_2019_2020__2[[profit]:[profit]],Sales_Export_2019_2020__2[[sales_rep]:[sales_rep]],$Y48,Sales_Export_2019_2020__2[[category]:[category]],AE$46) -> 161744 | AF48: =SUMIFS(Sales_Export_2019_2020__2[[profit]:[profit]],Sales_Export_2019_2020__2[[sales_rep]:[sales_rep]],$Y48,Sales_Export_2019_2020__2[[category]:[category]],AF$46) -> 149716.76 | AG48: =SUMIFS(Sales_Export_2019_2020__2[[profit]:[profit]],Sales_Export_2019_2020__2[[sales_rep]:[sales_rep]],$Y48,Sales_Export_2019_2020__2[[category]:[category]],AG$46) -> 59098.05 | ... AI48: =SUMIFS(Sales_Export_2019_2020__2[[profit]:[profit]],Sales_Export_2019_2020__2[[sales_rep]:[sales_rep]],$Y48,Sales_Export_2019_2020__2[[category]:[category]],AI$46) -> 122154.78
B49: Bertha Walbrook | C49: 19239.037 | D49: 9 | F49: 41 | G49: 19592.632 | I49: Books | J49: 19024.905 | K49: 9 | L49: Anita Woakes | M49: 2 | N49: 3 | O49: 8 | P49: 5 | Q49: 5 | R49: 5 | S49: 3 | T49: 1 | V49: 4 | W49: 36 | Y49: Anita Woakes | Z49: =SUMIFS(Sales_Export_2019_2020__2[[profit]:[profit]],Sales_Export_2019_2020__2[[sales_rep]:[sales_rep]],$Y49,Sales_Export_2019_2020__2[[category]:[category]],Z$46) -> 68584.93 | AA49: =SUMIFS(Sales_Export_2019_2020__2[[profit]:[profit]],Sales_Export_2019_2020__2[[sales_rep]:[sales_rep]],$Y49,Sales_Export_2019_2020__2[[category]:[category]],AA$46) -> 42710.1 | AB49: =SUMIFS(Sales_Export_2019_2020__2[[profit]:[profit]],Sales_Export_2019_2020__2[[sales_rep]:[sales_rep]],$Y49,Sales_Export_2019_2020__2[[category]:[category]],AB$46) -> 91139.61 | AC49: =SUMIFS(Sales_Export_2019_2020__2[[profit]:[profit]],Sales_Export_2019_2020__2[[sales_rep]:[sales_rep]],$Y49,Sales_Export_2019_2020__2[[category]:[category]],AC$46) -> 71814.32 | AD49: =SUMIFS(Sales_Export_2019_2020__2[[profit]:[profit]],Sales_Export_2019_2020__2[[sales_rep]:[sales_rep]],$Y49,Sales_Export_2019_2020__2[[category]:[category]],AD$46) -> 74218.47 | AE49: =SUMIFS(Sales_Export_2019_2020__2[[profit]:[profit]],Sales_Export_2019_2020__2[[sales_rep]:[sales_rep]],$Y49,Sales_Export_2019_2020__2[[category]:[category]],AE$46) -> 90548.3 | AF49: =SUMIFS(Sales_Export_2019_2020__2[[profit]:[profit]],Sales_Export_2019_2020__2[[sales_rep]:[sales_rep]],$Y49,Sales_Export_2019_2020__2[[category]:[category]],AF$46) -> 81520.33 | AG49: =SUMIFS(Sales_Export_2019_2020__2[[profit]:[profit]],Sales_Export_2019_2020__2[[sales_rep]:[sales_rep]],$Y49,Sales_Export_2019_2020__2[[category]:[category]],AG$46) -> 17295.59 | ... AI49: =SUMIFS(Sales_Export_2019_2020__2[[profit]:[profit]],Sales_Export_2019_2020__2[[sales_rep]:[sales_rep]],$Y49,Sales_Export_2019_2020__2[[category]:[category]],AI$46) -> 83205.16
B50: Brynn Dempster | C50: 19592.632 | D50: 41 | F50: 23 | G50: 20529.511 | I50: Clothing | J50: 18980.246 | K50: 41 | L50: Aurelie Wren | M50: 2 | N50: 6 | O50: 3 | P50: 8 | Q50: 8 | R50: 7 | S50: 7 | T50: 2 | U50: 4 | V50: 5 | W50: 52 | Y50: Aurelie Wren | Z50: =SUMIFS(Sales_Export_2019_2020__2[[profit]:[profit]],Sales_Export_2019_2020__2[[sales_rep]:[sales_rep]],$Y50,Sales_Export_2019_2020__2[[category]:[category]],Z$46) -> 32228.31 | AA50: =SUMIFS(Sales_Export_2019_2020__2[[profit]:[profit]],Sales_Export_2019_2020__2[[sales_rep]:[sales_rep]],$Y50,Sales_Export_2019_2020__2[[category]:[category]],AA$46) -> 120014.26 | AB50: =SUMIFS(Sales_Export_2019_2020__2[[profit]:[profit]],Sales_Export_2019_2020__2[[sales_rep]:[sales_rep]],$Y50,Sales_Export_2019_2020__2[[category]:[category]],AB$46) -> 64195.8 | AC50: =SUMIFS(Sales_Export_2019_2020__2[[profit]:[profit]],Sales_Export_2019_2020__2[[sales_rep]:[sales_rep]],$Y50,Sales_Export_2019_2020__2[[category]:[category]],AC$46) -> 165263.09 | AD50: =SUMIFS(Sales_Export_2019_2020__2[[profit]:[profit]],Sales_Export_2019_2020__2[[sales_rep]:[sales_rep]],$Y50,Sales_Export_2019_2020__2[[category]:[category]],AD$46) -> 124442.32 | AE50: =SUMIFS(Sales_Export_2019_2020__2[[profit]:[profit]],Sales_Export_2019_2020__2[[sales_rep]:[sales_rep]],$Y50,Sales_Export_2019_2020__2[[category]:[category]],AE$46) -> 147587.39 | AF50: =SUMIFS(Sales_Export_2019_2020__2[[profit]:[profit]],Sales_Export_2019_2020__2[[sales_rep]:[sales_rep]],$Y50,Sales_Export_2019_2020__2[[category]:[category]],AF$46) -> 115837.1 | AG50: =SUMIFS(Sales_Export_2019_2020__2[[profit]:[profit]],Sales_Export_2019_2020__2[[sales_rep]:[sales_rep]],$Y50,Sales_Export_2019_2020__2[[category]:[category]],AG$46) -> 20347.4 | ... AI50: =SUMIFS(Sales_Export_2019_2020__2[[profit]:[profit]],Sales_Export_2019_2020__2[[sales_rep]:[sales_rep]],$Y50,Sales_Export_2019_2020__2[[category]:[category]],AI$46) -> 69878.02
B51: Bunnie Tonbridge | C51: 20529.511 | D51: 23 | F51: 29 | G51: 16436.134 | I51: Electronics | J51: 17918.903 | K51: 23 | L51: Avrit Chanders | M51: 1 | N51: 8 | O51: 1 | P51: 8 | Q51: 5 | R51: 6 | S51: 7 | U51: 2 | V51: 5 | W51: 43 | Y51: Avrit Chanders | Z51: =SUMIFS(Sales_Export_2019_2020__2[[profit]:[profit]],Sales_Export_2019_2020__2[[sales_rep]:[sales_rep]],$Y51,Sales_Export_2019_2020__2[[category]:[category]],Z$46) -> 17352.29 | AA51: =SUMIFS(Sales_Export_2019_2020__2[[profit]:[profit]],Sales_Export_2019_2020__2[[sales_rep]:[sales_rep]],$Y51,Sales_Export_2019_2020__2[[category]:[category]],AA$46) -> 135338.81 | AB51: =SUMIFS(Sales_Export_2019_2020__2[[profit]:[profit]],Sales_Export_2019_2020__2[[sales_rep]:[sales_rep]],$Y51,Sales_Export_2019_2020__2[[category]:[category]],AB$46) -> 16819.8 | AC51: =SUMIFS(Sales_Export_2019_2020__2[[profit]:[profit]],Sales_Export_2019_2020__2[[sales_rep]:[sales_rep]],$Y51,Sales_Export_2019_2020__2[[category]:[category]],AC$46) -> 154729.61 | AD51: =SUMIFS(Sales_Export_2019_2020__2[[profit]:[profit]],Sales_Export_2019_2020__2[[sales_rep]:[sales_rep]],$Y51,Sales_Export_2019_2020__2[[category]:[category]],AD$46) -> 116876.79 | AE51: =SUMIFS(Sales_Export_2019_2020__2[[profit]:[profit]],Sales_Export_2019_2020__2[[sales_rep]:[sales_rep]],$Y51,Sales_Export_2019_2020__2[[category]:[category]],AE$46) -> 106586.81 | AF51: =SUMIFS(Sales_Export_2019_2020__2[[profit]:[profit]],Sales_Export_2019_2020__2[[sales_rep]:[sales_rep]],$Y51,Sales_Export_2019_2020__2[[category]:[category]],AF$46) -> 78345.16 | AG51: =SUMIFS(Sales_Export_2019_2020__2[[profit]:[profit]],Sales_Export_2019_2020__2[[sales_rep]:[sales_rep]],$Y51,Sales_Export_2019_2020__2[[category]:[category]],AG$46) -> 0 | ... AI51: =SUMIFS(Sales_Export_2019_2020__2[[profit]:[profit]],Sales_Export_2019_2020__2[[sales_rep]:[sales_rep]],$Y51,Sales_Export_2019_2020__2[[category]:[category]],AI$46) -> 145055.86
B52: Caro Morfield | C52: 16436.134 | D52: 29 | F52: 6 | G52: 13931.777 | I52: Games | J52: 18415.797 | K52: 29 | L52: Bank Coumbe | R52: 1 | S52: 1 | W52: 2 | Y52: Bank Coumbe | Z52: =SUMIFS(Sales_Export_2019_2020__2[[profit]:[profit]],Sales_Export_2019_2020__2[[sales_rep]:[sales_rep]],$Y52,Sales_Export_2019_2020__2[[category]:[category]],Z$46) -> 0 | AA52: =SUMIFS(Sales_Export_2019_2020__2[[profit]:[profit]],Sales_Export_2019_2020__2[[sales_rep]:[sales_rep]],$Y52,Sales_Export_2019_2020__2[[category]:[category]],AA$46) -> 0 | AB52: =SUMIFS(Sales_Export_2019_2020__2[[profit]:[profit]],Sales_Export_2019_2020__2[[sales_rep]:[sales_rep]],$Y52,Sales_Export_2019_2020__2[[category]:[category]],AB$46) -> 0 | AC52: =SUMIFS(Sales_Export_2019_2020__2[[profit]:[profit]],Sales_Export_2019_2020__2[[sales_rep]:[sales_rep]],$Y52,Sales_Export_2019_2020__2[[category]:[category]],AC$46) -> 0 | AD52: =SUMIFS(Sales_Export_2019_2020__2[[profit]:[profit]],Sales_Export_2019_2020__2[[sales_rep]:[sales_rep]],$Y52,Sales_Export_2019_2020__2[[category]:[category]],AD$46) -> 0 | AE52: =SUMIFS(Sales_Export_2019_2020__2[[profit]:[profit]],Sales_Export_2019_2020__2[[sales_rep]:[sales_rep]],$Y52,Sales_Export_2019_2020__2[[category]:[category]],AE$46) -> 10350.99 | AF52: =SUMIFS(Sales_Export_2019_2020__2[[profit]:[profit]],Sales_Export_2019_2020__2[[sales_rep]:[sales_rep]],$Y52,Sales_Export_2019_2020__2[[category]:[category]],AF$46) -> 25367.39 | AG52: =SUMIFS(Sales_Export_2019_2020__2[[profit]:[profit]],Sales_Export_2019_2020__2[[sales_rep]:[sales_rep]],$Y52,Sales_Export_2019_2020__2[[category]:[category]],AG$46) -> 0 | ... AI52: =SUMIFS(Sales_Export_2019_2020__2[[profit]:[profit]],Sales_Export_2019_2020__2[[sales_rep]:[sales_rep]],$Y52,Sales_Export_2019_2020__2[[category]:[category]],AI$46) -> 0
B53: Case Desorts | C53: 13931.777 | D53: 6 | F53: 24 | G53: 19414.931 | I53: Other | J53: 18932.197 | K53: 6 | L53: Bernadine Fullagar | M53: 1 | N53: 2 | O53: 2 | P53: 4 | R53: 1 | S53: 4 | V53: 1 | W53: 15 | Y53: Bernadine Fullagar | Z53: =SUMIFS(Sales_Export_2019_2020__2[[profit]:[profit]],Sales_Export_2019_2020__2[[sales_rep]:[sales_rep]],$Y53,Sales_Export_2019_2020__2[[category]:[category]],Z$46) -> 18595.15 | AA53: =SUMIFS(Sales_Export_2019_2020__2[[profit]:[profit]],Sales_Export_2019_2020__2[[sales_rep]:[sales_rep]],$Y53,Sales_Export_2019_2020__2[[category]:[category]],AA$46) -> 69197.31 | AB53: =SUMIFS(Sales_Export_2019_2020__2[[profit]:[profit]],Sales_Export_2019_2020__2[[sales_rep]:[sales_rep]],$Y53,Sales_Export_2019_2020__2[[category]:[category]],AB$46) -> 43519.24 | AC53: =SUMIFS(Sales_Export_2019_2020__2[[profit]:[profit]],Sales_Export_2019_2020__2[[sales_rep]:[sales_rep]],$Y53,Sales_Export_2019_2020__2[[category]:[category]],AC$46) -> 78690.81 | AD53: =SUMIFS(Sales_Export_2019_2020__2[[profit]:[profit]],Sales_Export_2019_2020__2[[sales_rep]:[sales_rep]],$Y53,Sales_Export_2019_2020__2[[category]:[category]],AD$46) -> 0 | AE53: =SUMIFS(Sales_Export_2019_2020__2[[profit]:[profit]],Sales_Export_2019_2020__2[[sales_rep]:[sales_rep]],$Y53,Sales_Export_2019_2020__2[[category]:[category]],AE$46) -> 18562.48 | AF53: =SUMIFS(Sales_Export_2019_2020__2[[profit]:[profit]],Sales_Export_2019_2020__2[[sales_rep]:[sales_rep]],$Y53,Sales_Export_2019_2020__2[[category]:[category]],AF$46) -> 83150.59 | AG53: =SUMIFS(Sales_Export_2019_2020__2[[profit]:[profit]],Sales_Export_2019_2020__2[[sales_rep]:[sales_rep]],$Y53,Sales_Export_2019_2020__2[[category]:[category]],AG$46) -> 0 | ... AI53: =SUMIFS(Sales_Export_2019_2020__2[[profit]:[profit]],Sales_Export_2019_2020__2[[sales_rep]:[sales_rep]],$Y53,Sales_Export_2019_2020__2[[category]:[category]],AI$46) -> 21728.68
B54: Casie MacBain | C54: 19414.931 | D54: 24 | F54: 5 | G54: 9952.408 | I54: Outdoors | J54: 21135.25 | K54: 24 | L54: Bertha Walbrook | N54: 1 | O54: 1 | R54: 4 | S54: 2 | U54: 1 | W54: 9 | Y54: Bertha Walbrook | Z54: =SUMIFS(Sales_Export_2019_2020__2[[profit]:[profit]],Sales_Export_2019_2020__2[[sales_rep]:[sales_rep]],$Y54,Sales_Export_2019_2020__2[[category]:[category]],Z$46) -> 0 | AA54: =SUMIFS(Sales_Export_2019_2020__2[[profit]:[profit]],Sales_Export_2019_2020__2[[sales_rep]:[sales_rep]],$Y54,Sales_Export_2019_2020__2[[category]:[category]],AA$46) -> 30977.78 | AB54: =SUMIFS(Sales_Export_2019_2020__2[[profit]:[profit]],Sales_Export_2019_2020__2[[sales_rep]:[sales_rep]],$Y54,Sales_Export_2019_2020__2[[category]:[category]],AB$46) -> 11533.96 | AC54: =SUMIFS(Sales_Export_2019_2020__2[[profit]:[profit]],Sales_Export_2019_2020__2[[sales_rep]:[sales_rep]],$Y54,Sales_Export_2019_2020__2[[category]:[category]],AC$46) -> 0 | AD54: =SUMIFS(Sales_Export_2019_2020__2[[profit]:[profit]],Sales_Export_2019_2020__2[[sales_rep]:[sales_rep]],$Y54,Sales_Export_2019_2020__2[[category]:[category]],AD$46) -> 0 | AE54: =SUMIFS(Sales_Export_2019_2020__2[[profit]:[profit]],Sales_Export_2019_2020__2[[sales_rep]:[sales_rep]],$Y54,Sales_Export_2019_2020__2[[category]:[category]],AE$46) -> 61937.76 | AF54: =SUMIFS(Sales_Export_2019_2020__2[[profit]:[profit]],Sales_Export_2019_2020__2[[sales_rep]:[sales_rep]],$Y54,Sales_Export_2019_2020__2[[category]:[category]],AF$46) -> 54391.99 | AG54: =SUMIFS(Sales_Export_2019_2020__2[[profit]:[profit]],Sales_Export_2019_2020__2[[sales_rep]:[sales_rep]],$Y54,Sales_Export_2019_2020__2[[category]:[category]],AG$46) -> 0 | ... AI54: =SUMIFS(Sales_Export_2019_2020__2[[profit]:[profit]],Sales_Export_2019_2020__2[[sales_rep]:[sales_rep]],$Y54,Sales_Export_2019_2020__2[[category]:[category]],AI$46) -> 0
B55: Cobby Andersen | C55: 9952.408 | D55: 5 | F55: 6 | G55: 15738.88 | I55: Smartphones | J55: 19164.712 | K55: 5 | L55: Brynn Dempster | M55: 2 | N55: 5 | O55: 5 | P55: 3 | Q55: 6 | R55: 6 | S55: 8 | T55: 1 | U55: 2 | V55: 3 | W55: 41 | Y55: Brynn Dempster | Z55: =SUMIFS(Sales_Export_2019_2020__2[[profit]:[profit]],Sales_Export_2019_2020__2[[sales_rep]:[sales_rep]],$Y55,Sales_Export_2019_2020__2[[category]:[category]],Z$46) -> 54416.84 | AA55: =SUMIFS(Sales_Export_2019_2020__2[[profit]:[profit]],Sales_Export_2019_2020__2[[sales_rep]:[sales_rep]],$Y55,Sales_Export_2019_2020__2[[category]:[category]],AA$46) -> 101376.35 | AB55: =SUMIFS(Sales_Export_2019_2020__2[[profit]:[profit]],Sales_Export_2019_2020__2[[sales_rep]:[sales_rep]],$Y55,Sales_Export_2019_2020__2[[category]:[category]],AB$46) -> 86783.85 | AC55: =SUMIFS(Sales_Export_2019_2020__2[[profit]:[profit]],Sales_Export_2019_2020__2[[sales_rep]:[sales_rep]],$Y55,Sales_Export_2019_2020__2[[category]:[category]],AC$46) -> 53960.66 | AD55: =SUMIFS(Sales_Export_2019_2020__2[[profit]:[profit]],Sales_Export_2019_2020__2[[sales_rep]:[sales_rep]],$Y55,Sales_Export_2019_2020__2[[category]:[category]],AD$46) -> 110373.04 | AE55: =SUMIFS(Sales_Export_2019_2020__2[[profit]:[profit]],Sales_Export_2019_2020__2[[sales_rep]:[sales_rep]],$Y55,Sales_Export_2019_2020__2[[category]:[category]],AE$46) -> 79746.7 | AF55: =SUMIFS(Sales_Export_2019_2020__2[[profit]:[profit]],Sales_Export_2019_2020__2[[sales_rep]:[sales_rep]],$Y55,Sales_Export_2019_2020__2[[category]:[category]],AF$46) -> 168458.82 | AG55: =SUMIFS(Sales_Export_2019_2020__2[[profit]:[profit]],Sales_Export_2019_2020__2[[sales_rep]:[sales_rep]],$Y55,Sales_Export_2019_2020__2[[category]:[category]],AG$46) -> 51020.88 | ... AI55: =SUMIFS(Sales_Export_2019_2020__2[[profit]:[profit]],Sales_Export_2019_2020__2[[sales_rep]:[sales_rep]],$Y55,Sales_Export_2019_2020__2[[category]:[category]],AI$46) -> 55658.14
B56: Collin Mackness | C56: 15738.88 | D56: 6 | F56: 53 | G56: 22405.31 | I56: Grand Total | J56: 18992.428 | K56: 6 | L56: Bunnie Tonbridge | N56: 1 | O56: 4 | P56: 2 | Q56: 4 | R56: 3 | S56: 3 | T56: 1 | U56: 3 | V56: 2 | W56: 23 | Y56: Bunnie Tonbridge | Z56: =SUMIFS(Sales_Export_2019_2020__2[[profit]:[profit]],Sales_Export_2019_2020__2[[sales_rep]:[sales_rep]],$Y56,Sales_Export_2019_2020__2[[category]:[category]],Z$46) -> 0 | AA56: =SUMIFS(Sales_Export_2019_2020__2[[profit]:[profit]],Sales_Export_2019_2020__2[[sales_rep]:[sales_rep]],$Y56,Sales_Export_2019_2020__2[[category]:[category]],AA$46) -> 16297.25 | AB56: =SUMIFS(Sales_Export_2019_2020__2[[profit]:[profit]],Sales_Export_2019_2020__2[[sales_rep]:[sales_rep]],$Y56,Sales_Export_2019_2020__2[[category]:[category]],AB$46) -> 71708.55 | AC56: =SUMIFS(Sales_Export_2019_2020__2[[profit]:[profit]],Sales_Export_2019_2020__2[[sales_rep]:[sales_rep]],$Y56,Sales_Export_2019_2020__2[[category]:[category]],AC$46) -> 105648.99 | AD56: =SUMIFS(Sales_Export_2019_2020__2[[profit]:[profit]],Sales_Export_2019_2020__2[[sales_rep]:[sales_rep]],$Y56,Sales_Export_2019_2020__2[[category]:[category]],AD$46) -> 56489.87 | AE56: =SUMIFS(Sales_Export_2019_2020__2[[profit]:[profit]],Sales_Export_2019_2020__2[[sales_rep]:[sales_rep]],$Y56,Sales_Export_2019_2020__2[[category]:[category]],AE$46) -> 85771.86 | AF56: =SUMIFS(Sales_Export_2019_2020__2[[profit]:[profit]],Sales_Export_2019_2020__2[[sales_rep]:[sales_rep]],$Y56,Sales_Export_2019_2020__2[[category]:[category]],AF$46) -> 39628.74 | AG56: =SUMIFS(Sales_Export_2019_2020__2[[profit]:[profit]],Sales_Export_2019_2020__2[[sales_rep]:[sales_rep]],$Y56,Sales_Export_2019_2020__2[[category]:[category]],AG$46) -> 6730.8 | ... AI56: =SUMIFS(Sales_Export_2019_2020__2[[profit]:[profit]],Sales_Export_2019_2020__2[[sales_rep]:[sales_rep]],$Y56,Sales_Export_2019_2020__2[[category]:[category]],AI$46) -> 49324.25
B57: Corene Shirer | C57: 22405.31 | D57: 53 | F57: 47 | G57: 17871.528 | K57: 53 | L57: Caro Morfield | N57: 1 | O57: 6 | P57: 1 | Q57: 6 | R57: 5 | S57: 3 | T57: 1 | U57: 1 | V57: 5 | W57: 29 | Y57: Caro Morfield | Z57: =SUMIFS(Sales_Export_2019_2020__2[[profit]:[profit]],Sales_Export_2019_2020__2[[sales_rep]:[sales_rep]],$Y57,Sales_Export_2019_2020__2[[category]:[category]],Z$46) -> 0 | AA57: =SUMIFS(Sales_Export_2019_2020__2[[profit]:[profit]],Sales_Export_2019_2020__2[[sales_rep]:[sales_rep]],$Y57,Sales_Export_2019_2020__2[[category]:[category]],AA$46) -> 17741.81 | AB57: =SUMIFS(Sales_Export_2019_2020__2[[profit]:[profit]],Sales_Export_2019_2020__2[[sales_rep]:[sales_rep]],$Y57,Sales_Export_2019_2020__2[[category]:[category]],AB$46) -> 83212.01 | AC57: =SUMIFS(Sales_Export_2019_2020__2[[profit]:[profit]],Sales_Export_2019_2020__2[[sales_rep]:[sales_rep]],$Y57,Sales_Export_2019_2020__2[[category]:[category]],AC$46) -> 15352.29 | AD57: =SUMIFS(Sales_Export_2019_2020__2[[profit]:[profit]],Sales_Export_2019_2020__2[[sales_rep]:[sales_rep]],$Y57,Sales_Export_2019_2020__2[[category]:[category]],AD$46) -> 97191.1 | AE57: =SUMIFS(Sales_Export_2019_2020__2[[profit]:[profit]],Sales_Export_2019_2020__2[[sales_rep]:[sales_rep]],$Y57,Sales_Export_2019_2020__2[[category]:[category]],AE$46) -> 76769.08 | AF57: =SUMIFS(Sales_Export_2019_2020__2[[profit]:[profit]],Sales_Export_2019_2020__2[[sales_rep]:[sales_rep]],$Y57,Sales_Export_2019_2020__2[[category]:[category]],AF$46) -> 98448.04 | AG57: =SUMIFS(Sales_Export_2019_2020__2[[profit]:[profit]],Sales_Export_2019_2020__2[[sales_rep]:[sales_rep]],$Y57,Sales_Export_2019_2020__2[[category]:[category]],AG$46) -> 4332.88 | ... AI57: =SUMIFS(Sales_Export_2019_2020__2[[profit]:[profit]],Sales_Export_2019_2020__2[[sales_rep]:[sales_rep]],$Y57,Sales_Export_2019_2020__2[[category]:[category]],AI$46) -> 62321.72
B58: Crysta Halls | C58: 17871.528 | D58: 47 | F58: 37 | G58: 19501.181 | I58: Category | J58: Total Sales | K58: 47 | L58: Case Desorts | N58: 1 | P58: 1 | Q58: 2 | R58: 1 | V58: 1 | W58: 6 | Y58: Case Desorts | Z58: =SUMIFS(Sales_Export_2019_2020__2[[profit]:[profit]],Sales_Export_2019_2020__2[[sales_rep]:[sales_rep]],$Y58,Sales_Export_2019_2020__2[[category]:[category]],Z$46) -> 0 | AA58: =SUMIFS(Sales_Export_2019_2020__2[[profit]:[profit]],Sales_Export_2019_2020__2[[sales_rep]:[sales_rep]],$Y58,Sales_Export_2019_2020__2[[category]:[category]],AA$46) -> 4145.62 | AB58: =SUMIFS(Sales_Export_2019_2020__2[[profit]:[profit]],Sales_Export_2019_2020__2[[sales_rep]:[sales_rep]],$Y58,Sales_Export_2019_2020__2[[category]:[category]],AB$46) -> 0 | AC58: =SUMIFS(Sales_Export_2019_2020__2[[profit]:[profit]],Sales_Export_2019_2020__2[[sales_rep]:[sales_rep]],$Y58,Sales_Export_2019_2020__2[[category]:[category]],AC$46) -> 4226.86 | AD58: =SUMIFS(Sales_Export_2019_2020__2[[profit]:[profit]],Sales_Export_2019_2020__2[[sales_rep]:[sales_rep]],$Y58,Sales_Export_2019_2020__2[[category]:[category]],AD$46) -> 20563.76 | AE58: =SUMIFS(Sales_Export_2019_2020__2[[profit]:[profit]],Sales_Export_2019_2020__2[[sales_rep]:[sales_rep]],$Y58,Sales_Export_2019_2020__2[[category]:[category]],AE$46) -> 13120.21 | AF58: =SUMIFS(Sales_Export_2019_2020__2[[profit]:[profit]],Sales_Export_2019_2020__2[[sales_rep]:[sales_rep]],$Y58,Sales_Export_2019_2020__2[[category]:[category]],AF$46) -> 0 | AG58: =SUMIFS(Sales_Export_2019_2020__2[[profit]:[profit]],Sales_Export_2019_2020__2[[sales_rep]:[sales_rep]],$Y58,Sales_Export_2019_2020__2[[category]:[category]],AG$46) -> 0 | ... AI58: =SUMIFS(Sales_Export_2019_2020__2[[profit]:[profit]],Sales_Export_2019_2020__2[[sales_rep]:[sales_rep]],$Y58,Sales_Export_2019_2020__2[[category]:[category]],AI$46) -> 41534.21
B59: Genevra Charrisson | C59: 19501.181 | D59: 37 | F59: 52 | G59: 19603.876 | I59: Accessories | J59: 35 | K59: 37 | L59: Casie MacBain | M59: 4 | N59: 5 | O59: 1 | P59: 1 | Q59: 3 | R59: 6 | S59: 2 | U59: 1 | V59: 1 | W59: 24 | Y59: Casie MacBain | Z59: =SUMIFS(Sales_Export_2019_2020__2[[profit]:[profit]],Sales_Export_2019_2020__2[[sales_rep]:[sales_rep]],$Y59,Sales_Export_2019_2020__2[[category]:[category]],Z$46) -> 56722.2 | AA59: =SUMIFS(Sales_Export_2019_2020__2[[profit]:[profit]],Sales_Export_2019_2020__2[[sales_rep]:[sales_rep]],$Y59,Sales_Export_2019_2020__2[[category]:[category]],AA$46) -> 130631.58 | AB59: =SUMIFS(Sales_Export_2019_2020__2[[profit]:[profit]],Sales_Export_2019_2020__2[[sales_rep]:[sales_rep]],$Y59,Sales_Export_2019_2020__2[[category]:[category]],AB$46) -> 35330.22 | AC59: =SUMIFS(Sales_Export_2019_2020__2[[profit]:[profit]],Sales_Export_2019_2020__2[[sales_rep]:[sales_rep]],$Y59,Sales_Export_2019_2020__2[[category]:[category]],AC$46) -> 11323.55 | AD59: =SUMIFS(Sales_Export_2019_2020__2[[profit]:[profit]],Sales_Export_2019_2020__2[[sales_rep]:[sales_rep]],$Y59,Sales_Export_2019_2020__2[[category]:[category]],AD$46) -> 50115.47 | AE59: =SUMIFS(Sales_Export_2019_2020__2[[profit]:[profit]],Sales_Export_2019_2020__2[[sales_rep]:[sales_rep]],$Y59,Sales_Export_2019_2020__2[[category]:[category]],AE$46) -> 96790.46 | AF59: =SUMIFS(Sales_Export_2019_2020__2[[profit]:[profit]],Sales_Export_2019_2020__2[[sales_rep]:[sales_rep]],$Y59,Sales_Export_2019_2020__2[[category]:[category]],AF$46) -> 60072.18 | AG59: =SUMIFS(Sales_Export_2019_2020__2[[profit]:[profit]],Sales_Export_2019_2020__2[[sales_rep]:[sales_rep]],$Y59,Sales_Export_2019_2020__2[[category]:[category]],AG$46) -> 0 | ... AI59: =SUMIFS(Sales_Export_2019_2020__2[[profit]:[profit]],Sales_Export_2019_2020__2[[sales_rep]:[sales_rep]],$Y59,Sales_Export_2019_2020__2[[category]:[category]],AI$46) -> 15437.71
B60: Hortense Gerring | C60: 19603.876 | D60: 52 | F60: 26 | G60: 19592.159 | I60: Appliances | J60: 131 | K60: 52 | L60: Cobby Andersen | N60: 1 | P60: 3 | S60: 1 | W60: 5 | Y60: Cobby Andersen | Z60: =SUMIFS(Sales_Export_2019_2020__2[[profit]:[profit]],Sales_Export_2019_2020__2[[sales_rep]:[sales_rep]],$Y60,Sales_Export_2019_2020__2[[category]:[category]],Z$46) -> 0 | AA60: =SUMIFS(Sales_Export_2019_2020__2[[profit]:[profit]],Sales_Export_2019_2020__2[[sales_rep]:[sales_rep]],$Y60,Sales_Export_2019_2020__2[[category]:[category]],AA$46) -> 8974.85 | AB60: =SUMIFS(Sales_Export_2019_2020__2[[profit]:[profit]],Sales_Export_2019_2020__2[[sales_rep]:[sales_rep]],$Y60,Sales_Export_2019_2020__2[[category]:[category]],AB$46) -> 0 | AC60: =SUMIFS(Sales_Export_2019_2020__2[[profit]:[profit]],Sales_Export_2019_2020__2[[sales_rep]:[sales_rep]],$Y60,Sales_Export_2019_2020__2[[category]:[category]],AC$46) -> 33208.67 | AD60: =SUMIFS(Sales_Export_2019_2020__2[[profit]:[profit]],Sales_Export_2019_2020__2[[sales_rep]:[sales_rep]],$Y60,Sales_Export_2019_2020__2[[category]:[category]],AD$46) -> 0 | AE60: =SUMIFS(Sales_Export_2019_2020__2[[profit]:[profit]],Sales_Export_2019_2020__2[[sales_rep]:[sales_rep]],$Y60,Sales_Export_2019_2020__2[[category]:[category]],AE$46) -> 0 | AF60: =SUMIFS(Sales_Export_2019_2020__2[[profit]:[profit]],Sales_Export_2019_2020__2[[sales_rep]:[sales_rep]],$Y60,Sales_Export_2019_2020__2[[category]:[category]],AF$46) -> 7578.52 | AG60: =SUMIFS(Sales_Export_2019_2020__2[[profit]:[profit]],Sales_Export_2019_2020__2[[sales_rep]:[sales_rep]],$Y60,Sales_Export_2019_2020__2[[category]:[category]],AG$46) -> 0 | ... AI60: =SUMIFS(Sales_Export_2019_2020__2[[profit]:[profit]],Sales_Export_2019_2020__2[[sales_rep]:[sales_rep]],$Y60,Sales_Export_2019_2020__2[[category]:[category]],AI$46) -> 0
B61: Jay Morefield | C61: 19592.159 | D61: 26 | F61: 22 | G61: 21934.839 | I61: Beauty | J61: 115 | K61: 26 | L61: Collin Mackness | M61: 1 | N61: 2 | Q61: 1 | S61: 1 | V61: 1 | W61: 6 | Y61: Collin Mackness | Z61: =SUMIFS(Sales_Export_2019_2020__2[[profit]:[profit]],Sales_Export_2019_2020__2[[sales_rep]:[sales_rep]],$Y61,Sales_Export_2019_2020__2[[category]:[category]],Z$46) -> 5747.24 | AA61: =SUMIFS(Sales_Export_2019_2020__2[[profit]:[profit]],Sales_Export_2019_2020__2[[sales_rep]:[sales_rep]],$Y61,Sales_Export_2019_2020__2[[category]:[category]],AA$46) -> 30381.38 | AB61: =SUMIFS(Sales_Export_2019_2020__2[[profit]:[profit]],Sales_Export_2019_2020__2[[sales_rep]:[sales_rep]],$Y61,Sales_Export_2019_2020__2[[category]:[category]],AB$46) -> 0 | AC61: =SUMIFS(Sales_Export_2019_2020__2[[profit]:[profit]],Sales_Export_2019_2020__2[[sales_rep]:[sales_rep]],$Y61,Sales_Export_2019_2020__2[[category]:[category]],AC$46) -> 0 | AD61: =SUMIFS(Sales_Export_2019_2020__2[[profit]:[profit]],Sales_Export_2019_2020__2[[sales_rep]:[sales_rep]],$Y61,Sales_Export_2019_2020__2[[category]:[category]],AD$46) -> 14566.33 | AE61: =SUMIFS(Sales_Export_2019_2020__2[[profit]:[profit]],Sales_Export_2019_2020__2[[sales_rep]:[sales_rep]],$Y61,Sales_Export_2019_2020__2[[category]:[category]],AE$46) -> 0 | AF61: =SUMIFS(Sales_Export_2019_2020__2[[profit]:[profit]],Sales_Export_2019_2020__2[[sales_rep]:[sales_rep]],$Y61,Sales_Export_2019_2020__2[[category]:[category]],AF$46) -> 23891.71 | AG61: =SUMIFS(Sales_Export_2019_2020__2[[profit]:[profit]],Sales_Export_2019_2020__2[[sales_rep]:[sales_rep]],$Y61,Sales_Export_2019_2020__2[[category]:[category]],AG$46) -> 0 | ... AI61: =SUMIFS(Sales_Export_2019_2020__2[[profit]:[profit]],Sales_Export_2019_2020__2[[sales_rep]:[sales_rep]],$Y61,Sales_Export_2019_2020__2[[category]:[category]],AI$46) -> 19846.62
B62: Jocelyn Laurentino | C62: 21934.839 | D62: 22 | F62: 10 | G62: 15545.863 | I62: Books | J62: 117 | K62: 22 | L62: Corene Shirer | N62: 7 | O62: 7 | P62: 7 | Q62: 8 | R62: 5 | S62: 9 | T62: 1 | U62: 2 | V62: 7 | W62: 53 | Y62: Corene Shirer | Z62: =SUMIFS(Sales_Export_2019_2020__2[[profit]:[profit]],Sales_Export_2019_2020__2[[sales_rep]:[sales_rep]],$Y62,Sales_Export_2019_2020__2[[category]:[category]],Z$46) -> 0 | AA62: =SUMIFS(Sales_Export_2019_2020__2[[profit]:[profit]],Sales_Export_2019_2020__2[[sales_rep]:[sales_rep]],$Y62,Sales_Export_2019_2020__2[[category]:[category]],AA$46) -> 165552.47 | AB62: =SUMIFS(Sales_Export_2019_2020__2[[profit]:[profit]],Sales_Export_2019_2020__2[[sales_rep]:[sales_rep]],$Y62,Sales_Export_2019_2020__2[[category]:[category]],AB$46) -> 133554.56 | AC62: =SUMIFS(Sales_Export_2019_2020__2[[profit]:[profit]],Sales_Export_2019_2020__2[[sales_rep]:[sales_rep]],$Y62,Sales_Export_2019_2020__2[[category]:[category]],AC$46) -> 114760.35 | AD62: =SUMIFS(Sales_Export_2019_2020__2[[profit]:[profit]],Sales_Export_2019_2020__2[[sales_rep]:[sales_rep]],$Y62,Sales_Export_2019_2020__2[[category]:[category]],AD$46) -> 195333.76 | AE62: =SUMIFS(Sales_Export_2019_2020__2[[profit]:[profit]],Sales_Export_2019_2020__2[[sales_rep]:[sales_rep]],$Y62,Sales_Export_2019_2020__2[[category]:[category]],AE$46) -> 116359.6 | AF62: =SUMIFS(Sales_Export_2019_2020__2[[profit]:[profit]],Sales_Export_2019_2020__2[[sales_rep]:[sales_rep]],$Y62,Sales_Export_2019_2020__2[[category]:[category]],AF$46) -> 257174.33 | AG62: =SUMIFS(Sales_Export_2019_2020__2[[profit]:[profit]],Sales_Export_2019_2020__2[[sales_rep]:[sales_rep]],$Y62,Sales_Export_2019_2020__2[[category]:[category]],AG$46) -> 33404.24 | ... AI62: =SUMIFS(Sales_Export_2019_2020__2[[profit]:[profit]],Sales_Export_2019_2020__2[[sales_rep]:[sales_rep]],$Y62,Sales_Export_2019_2020__2[[category]:[category]],AI$46) -> 131103.14
B63: Joshua Prevost | C63: 15545.863 | D63: 10 | F63: 39 | G63: 17026.67 | I63: Clothing | J63: 155 | K63: 10 | L63: Crysta Halls | M63: 2 | N63: 9 | O63: 8 | P63: 4 | Q63: 5 | R63: 5 | S63: 4 | T63: 1 | U63: 2 | V63: 7 | W63: 47 | Y63: Crysta Halls | Z63: =SUMIFS(Sales_Export_2019_2020__2[[profit]:[profit]],Sales_Export_2019_2020__2[[sales_rep]:[sales_rep]],$Y63,Sales_Export_2019_2020__2[[category]:[category]],Z$46) -> 31394.67 | AA63: =SUMIFS(Sales_Export_2019_2020__2[[profit]:[profit]],Sales_Export_2019_2020__2[[sales_rep]:[sales_rep]],$Y63,Sales_Export_2019_2020__2[[category]:[category]],AA$46) -> 195396.99 | AB63: =SUMIFS(Sales_Export_2019_2020__2[[profit]:[profit]],Sales_Export_2019_2020__2[[sales_rep]:[sales_rep]],$Y63,Sales_Export_2019_2020__2[[category]:[category]],AB$46) -> 114121.39 | AC63: =SUMIFS(Sales_Export_2019_2020__2[[profit]:[profit]],Sales_Export_2019_2020__2[[sales_rep]:[sales_rep]],$Y63,Sales_Export_2019_2020__2[[category]:[category]],AC$46) -> 106468.64 | AD63: =SUMIFS(Sales_Export_2019_2020__2[[profit]:[profit]],Sales_Export_2019_2020__2[[sales_rep]:[sales_rep]],$Y63,Sales_Export_2019_2020__2[[category]:[category]],AD$46) -> 82385.35 | AE63: =SUMIFS(Sales_Export_2019_2020__2[[profit]:[profit]],Sales_Export_2019_2020__2[[sales_rep]:[sales_rep]],$Y63,Sales_Export_2019_2020__2[[category]:[category]],AE$46) -> 55911.37 | AF63: =SUMIFS(Sales_Export_2019_2020__2[[profit]:[profit]],Sales_Export_2019_2020__2[[sales_rep]:[sales_rep]],$Y63,Sales_Export_2019_2020__2[[category]:[category]],AF$46) -> 89935.81 | AG63: =SUMIFS(Sales_Export_2019_2020__2[[profit]:[profit]],Sales_Export_2019_2020__2[[sales_rep]:[sales_rep]],$Y63,Sales_Export_2019_2020__2[[category]:[category]],AG$46) -> 12380.16 | ... AI63: =SUMIFS(Sales_Export_2019_2020__2[[profit]:[profit]],Sales_Export_2019_2020__2[[sales_rep]:[sales_rep]],$Y63,Sales_Export_2019_2020__2[[category]:[category]],AI$46) -> 107692.29
B64: Madelon Bront | C64: 17026.67 | D64: 39 | F64: 36 | G64: 19774.34 | I64: Electronics | J64: 134 | K64: 39 | L64: Genevra Charrisson | M64: 1 | N64: 5 | O64: 2 | P64: 1 | Q64: 5 | R64: 5 | S64: 8 | U64: 6 | V64: 4 | W64: 37 | Y64: Genevra Charrisson | Z64: =SUMIFS(Sales_Export_2019_2020__2[[profit]:[profit]],Sales_Export_2019_2020__2[[sales_rep]:[sales_rep]],$Y64,Sales_Export_2019_2020__2[[category]:[category]],Z$46) -> 12979.84 | AA64: =SUMIFS(Sales_Export_2019_2020__2[[profit]:[profit]],Sales_Export_2019_2020__2[[sales_rep]:[sales_rep]],$Y64,Sales_Export_2019_2020__2[[category]:[category]],AA$46) -> 128007 | AB64: =SUMIFS(Sales_Export_2019_2020__2[[profit]:[profit]],Sales_Export_2019_2020__2[[sales_rep]:[sales_rep]],$Y64,Sales_Export_2019_2020__2[[category]:[category]],AB$46) -> 39360.88 | AC64: =SUMIFS(Sales_Export_2019_2020__2[[profit]:[profit]],Sales_Export_2019_2020__2[[sales_rep]:[sales_rep]],$Y64,Sales_Export_2019_2020__2[[category]:[category]],AC$46) -> 16625.66 | AD64: =SUMIFS(Sales_Export_2019_2020__2[[profit]:[profit]],Sales_Export_2019_2020__2[[sales_rep]:[sales_rep]],$Y64,Sales_Export_2019_2020__2[[category]:[category]],AD$46) -> 120441.88 | AE64: =SUMIFS(Sales_Export_2019_2020__2[[profit]:[profit]],Sales_Export_2019_2020__2[[sales_rep]:[sales_rep]],$Y64,Sales_Export_2019_2020__2[[category]:[category]],AE$46) -> 105835.81 | AF64: =SUMIFS(Sales_Export_2019_2020__2[[profit]:[profit]],Sales_Export_2019_2020__2[[sales_rep]:[sales_rep]],$Y64,Sales_Export_2019_2020__2[[category]:[category]],AF$46) -> 107971.98 | AG64: =SUMIFS(Sales_Export_2019_2020__2[[profit]:[profit]],Sales_Export_2019_2020__2[[sales_rep]:[sales_rep]],$Y64,Sales_Export_2019_2020__2[[category]:[category]],AG$46) -> 0 | ... AI64: =SUMIFS(Sales_Export_2019_2020__2[[profit]:[profit]],Sales_Export_2019_2020__2[[sales_rep]:[sales_rep]],$Y64,Sales_Export_2019_2020__2[[category]:[category]],AI$46) -> 93337.98
B65: Maighdiln Upcraft | C65: 19774.34 | D65: 36 | F65: 5 | G65: 15524.046 | I65: Games | J65: 139 | K65: 36 | L65: Hortense Gerring | M65: 2 | N65: 4 | O65: 8 | P65: 5 | Q65: 13 | R65: 6 | S65: 7 | T65: 1 | U65: 1 | V65: 5 | W65: 52 | Y65: Hortense Gerring | Z65: =SUMIFS(Sales_Export_2019_2020__2[[profit]:[profit]],Sales_Export_2019_2020__2[[sales_rep]:[sales_rep]],$Y65,Sales_Export_2019_2020__2[[category]:[category]],Z$46) -> 45662.77 | AA65: =SUMIFS(Sales_Export_2019_2020__2[[profit]:[profit]],Sales_Export_2019_2020__2[[sales_rep]:[sales_rep]],$Y65,Sales_Export_2019_2020__2[[category]:[category]],AA$46) -> 125233.72 | AB65: =SUMIFS(Sales_Export_2019_2020__2[[profit]:[profit]],Sales_Export_2019_2020__2[[sales_rep]:[sales_rep]],$Y65,Sales_Export_2019_2020__2[[category]:[category]],AB$46) -> 156067.55 | AC65: =SUMIFS(Sales_Export_2019_2020__2[[profit]:[profit]],Sales_Export_2019_2020__2[[sales_rep]:[sales_rep]],$Y65,Sales_Export_2019_2020__2[[category]:[category]],AC$46) -> 82692.81 | AD65: =SUMIFS(Sales_Export_2019_2020__2[[profit]:[profit]],Sales_Export_2019_2020__2[[sales_rep]:[sales_rep]],$Y65,Sales_Export_2019_2020__2[[category]:[category]],AD$46) -> 272867.27 | AE65: =SUMIFS(Sales_Export_2019_2020__2[[profit]:[profit]],Sales_Export_2019_2020__2[[sales_rep]:[sales_rep]],$Y65,Sales_Export_2019_2020__2[[category]:[category]],AE$46) -> 104586.57 | AF65: =SUMIFS(Sales_Export_2019_2020__2[[profit]:[profit]],Sales_Export_2019_2020__2[[sales_rep]:[sales_rep]],$Y65,Sales_Export_2019_2020__2[[category]:[category]],AF$46) -> 106852.42 | AG65: =SUMIFS(Sales_Export_2019_2020__2[[profit]:[profit]],Sales_Export_2019_2020__2[[sales_rep]:[sales_rep]],$Y65,Sales_Export_2019_2020__2[[category]:[category]],AG$46) -> 10452.02 | ... AI65: =SUMIFS(Sales_Export_2019_2020__2[[profit]:[profit]],Sales_Export_2019_2020__2[[sales_rep]:[sales_rep]],$Y65,Sales_Export_2019_2020__2[[category]:[category]],AI$46) -> 93877.99
B66: Manuel Goudie | C66: 15524.046 | D66: 5 | F66: 21 | G66: 21113.244 | I66: Other | J66: 29 | K66: 5 | L66: Jay Morefield | M66: 2 | N66: 4 | O66: 4 | P66: 4 | Q66: 5 | R66: 1 | S66: 3 | U66: 1 | V66: 2 | W66: 26 | Y66: Jay Morefield | Z66: =SUMIFS(Sales_Export_2019_2020__2[[profit]:[profit]],Sales_Export_2019_2020__2[[sales_rep]:[sales_rep]],$Y66,Sales_Export_2019_2020__2[[category]:[category]],Z$46) -> 46448.65 | AA66: =SUMIFS(Sales_Export_2019_2020__2[[profit]:[profit]],Sales_Export_2019_2020__2[[sales_rep]:[sales_rep]],$Y66,Sales_Export_2019_2020__2[[category]:[category]],AA$46) -> 113896.98 | AB66: =SUMIFS(Sales_Export_2019_2020__2[[profit]:[profit]],Sales_Export_2019_2020__2[[sales_rep]:[sales_rep]],$Y66,Sales_Export_2019_2020__2[[category]:[category]],AB$46) -> 82931.13 | AC66: =SUMIFS(Sales_Export_2019_2020__2[[profit]:[profit]],Sales_Export_2019_2020__2[[sales_rep]:[sales_rep]],$Y66,Sales_Export_2019_2020__2[[category]:[category]],AC$46) -> 79753.51 | AD66: =SUMIFS(Sales_Export_2019_2020__2[[profit]:[profit]],Sales_Export_2019_2020__2[[sales_rep]:[sales_rep]],$Y66,Sales_Export_2019_2020__2[[category]:[category]],AD$46) -> 61072.87 | AE66: =SUMIFS(Sales_Export_2019_2020__2[[profit]:[profit]],Sales_Export_2019_2020__2[[sales_rep]:[sales_rep]],$Y66,Sales_Export_2019_2020__2[[category]:[category]],AE$46) -> 28846.65 | AF66: =SUMIFS(Sales_Export_2019_2020__2[[profit]:[profit]],Sales_Export_2019_2020__2[[sales_rep]:[sales_rep]],$Y66,Sales_Export_2019_2020__2[[category]:[category]],AF$46) -> 37883.18 | AG66: =SUMIFS(Sales_Export_2019_2020__2[[profit]:[profit]],Sales_Export_2019_2020__2[[sales_rep]:[sales_rep]],$Y66,Sales_Export_2019_2020__2[[category]:[category]],AG$46) -> 0 | ... AI66: =SUMIFS(Sales_Export_2019_2020__2[[profit]:[profit]],Sales_Export_2019_2020__2[[sales_rep]:[sales_rep]],$Y66,Sales_Export_2019_2020__2[[category]:[category]],AI$46) -> 24281.03
B67: Mellicent Mattys | C67: 21113.244 | D67: 21 | F67: 28 | G67: 18770.217 | I67: Outdoors | J67: 50 | K67: 21 | L67: Jocelyn Laurentino | M67: 2 | N67: 2 | O67: 3 | P67: 3 | Q67: 3 | R67: 2 | S67: 3 | U67: 2 | V67: 2 | W67: 22 | Y67: Jocelyn Laurentino | Z67: =SUMIFS(Sales_Export_2019_2020__2[[profit]:[profit]],Sales_Export_2019_2020__2[[sales_rep]:[sales_rep]],$Y67,Sales_Export_2019_2020__2[[category]:[category]],Z$46) -> 60030.92 | AA67: =SUMIFS(Sales_Export_2019_2020__2[[profit]:[profit]],Sales_Export_2019_2020__2[[sales_rep]:[sales_rep]],$Y67,Sales_Export_2019_2020__2[[category]:[category]],AA$46) -> 20327.21 | AB67: =SUMIFS(Sales_Export_2019_2020__2[[profit]:[profit]],Sales_Export_2019_2020__2[[sales_rep]:[sales_rep]],$Y67,Sales_Export_2019_2020__2[[category]:[category]],AB$46) -> 62584.73 | AC67: =SUMIFS(Sales_Export_2019_2020__2[[profit]:[profit]],Sales_Export_2019_2020__2[[sales_rep]:[sales_rep]],$Y67,Sales_Export_2019_2020__2[[category]:[category]],AC$46) -> 74790.09 | AD67: =SUMIFS(Sales_Export_2019_2020__2[[profit]:[profit]],Sales_Export_2019_2020__2[[sales_rep]:[sales_rep]],$Y67,Sales_Export_2019_2020__2[[category]:[category]],AD$46) -> 56799.57 | AE67: =SUMIFS(Sales_Export_2019_2020__2[[profit]:[profit]],Sales_Export_2019_2020__2[[sales_rep]:[sales_rep]],$Y67,Sales_Export_2019_2020__2[[category]:[category]],AE$46) -> 33072.22 | AF67: =SUMIFS(Sales_Export_2019_2020__2[[profit]:[profit]],Sales_Export_2019_2020__2[[sales_rep]:[sales_rep]],$Y67,Sales_Export_2019_2020__2[[category]:[category]],AF$46) -> 59055.54 | AG67: =SUMIFS(Sales_Export_2019_2020__2[[profit]:[profit]],Sales_Export_2019_2020__2[[sales_rep]:[sales_rep]],$Y67,Sales_Export_2019_2020__2[[category]:[category]],AG$46) -> 0 | ... AI67: =SUMIFS(Sales_Export_2019_2020__2[[profit]:[profit]],Sales_Export_2019_2020__2[[sales_rep]:[sales_rep]],$Y67,Sales_Export_2019_2020__2[[category]:[category]],AI$46) -> 53410.05
B68: Nero Harbisher | C68: 18770.217 | D68: 28 | F68: 50 | G68: 17650.505 | I68: Smartphones | J68: 95 | K68: 28 | L68: Joshua Prevost | N68: 1 | P68: 3 | Q68: 1 | S68: 3 | T68: 1 | V68: 1 | W68: 10 | Y68: Joshua Prevost | Z68: =SUMIFS(Sales_Export_2019_2020__2[[profit]:[profit]],Sales_Export_2019_2020__2[[sales_rep]:[sales_rep]],$Y68,Sales_Export_2019_2020__2[[category]:[category]],Z$46) -> 0 | AA68: =SUMIFS(Sales_Export_2019_2020__2[[profit]:[profit]],Sales_Export_2019_2020__2[[sales_rep]:[sales_rep]],$Y68,Sales_Export_2019_2020__2[[category]:[category]],AA$46) -> 6789.7 | AB68: =SUMIFS(Sales_Export_2019_2020__2[[profit]:[profit]],Sales_Export_2019_2020__2[[sales_rep]:[sales_rep]],$Y68,Sales_Export_2019_2020__2[[category]:[category]],AB$46) -> 0 | AC68: =SUMIFS(Sales_Export_2019_2020__2[[profit]:[profit]],Sales_Export_2019_2020__2[[sales_rep]:[sales_rep]],$Y68,Sales_Export_2019_2020__2[[category]:[category]],AC$46) -> 38194.88 | AD68: =SUMIFS(Sales_Export_2019_2020__2[[profit]:[profit]],Sales_Export_2019_2020__2[[sales_rep]:[sales_rep]],$Y68,Sales_Export_2019_2020__2[[category]:[category]],AD$46) -> 16151.28 | AE68: =SUMIFS(Sales_Export_2019_2020__2[[profit]:[profit]],Sales_Export_2019_2020__2[[sales_rep]:[sales_rep]],$Y68,Sales_Export_2019_2020__2[[category]:[category]],AE$46) -> 0 | AF68: =SUMIFS(Sales_Export_2019_2020__2[[profit]:[profit]],Sales_Export_2019_2020__2[[sales_rep]:[sales_rep]],$Y68,Sales_Export_2019_2020__2[[category]:[category]],AF$46) -> 50036.26 | AG68: =SUMIFS(Sales_Export_2019_2020__2[[profit]:[profit]],Sales_Export_2019_2020__2[[sales_rep]:[sales_rep]],$Y68,Sales_Export_2019_2020__2[[category]:[category]],AG$46) -> 21976.57 | ... AI68: =SUMIFS(Sales_Export_2019_2020__2[[profit]:[profit]],Sales_Export_2019_2020__2[[sales_rep]:[sales_rep]],$Y68,Sales_Export_2019_2020__2[[category]:[category]],AI$46) -> 22309.94
B69: Ora Grennan | C69: 17650.505 | D69: 50 | F69: 20 | G69: 17856.662 | I69: Grand Total | J69: 1000 | K69: 50 | L69: Madelon Bront | M69: 1 | N69: 8 | O69: 4 | P69: 6 | Q69: 5 | R69: 6 | S69: 3 | T69: 1 | U69: 4 | V69: 1 | W69: 39 | Y69: Madelon Bront | Z69: =SUMIFS(Sales_Export_2019_2020__2[[profit]:[profit]],Sales_Export_2019_2020__2[[sales_rep]:[sales_rep]],$Y69,Sales_Export_2019_2020__2[[category]:[category]],Z$46) -> 22611.75 | AA69: =SUMIFS(Sales_Export_2019_2020__2[[profit]:[profit]],Sales_Export_2019_2020__2[[sales_rep]:[sales_rep]],$Y69,Sales_Export_2019_2020__2[[category]:[category]],AA$46) -> 116182.54 | AB69: =SUMIFS(Sales_Export_2019_2020__2[[profit]:[profit]],Sales_Export_2019_2020__2[[sales_rep]:[sales_rep]],$Y69,Sales_Export_2019_2020__2[[category]:[category]],AB$46) -> 49412.82 | AC69: =SUMIFS(Sales_Export_2019_2020__2[[profit]:[profit]],Sales_Export_2019_2020__2[[sales_rep]:[sales_rep]],$Y69,Sales_Export_2019_2020__2[[category]:[category]],AC$46) -> 99901.78 | AD69: =SUMIFS(Sales_Export_2019_2020__2[[profit]:[profit]],Sales_Export_2019_2020__2[[sales_rep]:[sales_rep]],$Y69,Sales_Export_2019_2020__2[[category]:[category]],AD$46) -> 79908.24 | AE69: =SUMIFS(Sales_Export_2019_2020__2[[profit]:[profit]],Sales_Export_2019_2020__2[[sales_rep]:[sales_rep]],$Y69,Sales_Export_2019_2020__2[[category]:[category]],AE$46) -> 128051.3 | AF69: =SUMIFS(Sales_Export_2019_2020__2[[profit]:[profit]],Sales_Export_2019_2020__2[[sales_rep]:[sales_rep]],$Y69,Sales_Export_2019_2020__2[[category]:[category]],AF$46) -> 55368.16 | AG69: =SUMIFS(Sales_Export_2019_2020__2[[profit]:[profit]],Sales_Export_2019_2020__2[[sales_rep]:[sales_rep]],$Y69,Sales_Export_2019_2020__2[[category]:[category]],AG$46) -> 20699.91 | ... AI69: =SUMIFS(Sales_Export_2019_2020__2[[profit]:[profit]],Sales_Export_2019_2020__2[[sales_rep]:[sales_rep]],$Y69,Sales_Export_2019_2020__2[[category]:[category]],AI$46) -> 20167.9
B70: Palm Wetherald | C70: 17856.662 | D70: 20 | F70: 12 | G70: 13659.872 | K70: 20 | L70: Maighdiln Upcraft | M70: 2 | N70: 4 | O70: 10 | P70: 5 | Q70: 3 | R70: 5 | S70: 2 | T70: 2 | U70: 1 | V70: 2 | W70: 36 | Y70: Maighdiln Upcraft | Z70: =SUMIFS(Sales_Export_2019_2020__2[[profit]:[profit]],Sales_Export_2019_2020__2[[sales_rep]:[sales_rep]],$Y70,Sales_Export_2019_2020__2[[category]:[category]],Z$46) -> 54760.59 | AA70: =SUMIFS(Sales_Export_2019_2020__2[[profit]:[profit]],Sales_Export_2019_2020__2[[sales_rep]:[sales_rep]],$Y70,Sales_Export_2019_2020__2[[category]:[category]],AA$46) -> 72684.99 | AB70: =SUMIFS(Sales_Export_2019_2020__2[[profit]:[profit]],Sales_Export_2019_2020__2[[sales_rep]:[sales_rep]],$Y70,Sales_Export_2019_2020__2[[category]:[category]],AB$46) -> 193105.54 | AC70: =SUMIFS(Sales_Export_2019_2020__2[[profit]:[profit]],Sales_Export_2019_2020__2[[sales_rep]:[sales_rep]],$Y70,Sales_Export_2019_2020__2[[category]:[category]],AC$46) -> 147390.07 | AD70: =SUMIFS(Sales_Export_2019_2020__2[[profit]:[profit]],Sales_Export_2019_2020__2[[sales_rep]:[sales_rep]],$Y70,Sales_Export_2019_2020__2[[category]:[category]],AD$46) -> 69079.86 | AE70: =SUMIFS(Sales_Export_2019_2020__2[[profit]:[profit]],Sales_Export_2019_2020__2[[sales_rep]:[sales_rep]],$Y70,Sales_Export_2019_2020__2[[category]:[category]],AE$46) -> 88734.87 | AF70: =SUMIFS(Sales_Export_2019_2020__2[[profit]:[profit]],Sales_Export_2019_2020__2[[sales_rep]:[sales_rep]],$Y70,Sales_Export_2019_2020__2[[category]:[category]],AF$46) -> 25995.53 | AG70: =SUMIFS(Sales_Export_2019_2020__2[[profit]:[profit]],Sales_Export_2019_2020__2[[sales_rep]:[sales_rep]],$Y70,Sales_Export_2019_2020__2[[category]:[category]],AG$46) -> 21251.5 | ... AI70: =SUMIFS(Sales_Export_2019_2020__2[[profit]:[profit]],Sales_Export_2019_2020__2[[sales_rep]:[sales_rep]],$Y70,Sales_Export_2019_2020__2[[category]:[category]],AI$46) -> 12127.56
B71: Perri Aldersley | C71: 13659.872 | D71: 12 | F71: 15 | G71: 18130.591 | K71: 12 | L71: Manuel Goudie | O71: 1 | R71: 2 | S71: 1 | T71: 1 | W71: 5 | Y71: Manuel Goudie | Z71: =SUMIFS(Sales_Export_2019_2020__2[[profit]:[profit]],Sales_Export_2019_2020__2[[sales_rep]:[sales_rep]],$Y71,Sales_Export_2019_2020__2[[category]:[category]],Z$46) -> 0 | AA71: =SUMIFS(Sales_Export_2019_2020__2[[profit]:[profit]],Sales_Export_2019_2020__2[[sales_rep]:[sales_rep]],$Y71,Sales_Export_2019_2020__2[[category]:[category]],AA$46) -> 0 | AB71: =SUMIFS(Sales_Export_2019_2020__2[[profit]:[profit]],Sales_Export_2019_2020__2[[sales_rep]:[sales_rep]],$Y71,Sales_Export_2019_2020__2[[category]:[category]],AB$46) -> 11946.16 | AC71: =SUMIFS(Sales_Export_2019_2020__2[[profit]:[profit]],Sales_Export_2019_2020__2[[sales_rep]:[sales_rep]],$Y71,Sales_Export_2019_2020__2[[category]:[category]],AC$46) -> 0 | AD71: =SUMIFS(Sales_Export_2019_2020__2[[profit]:[profit]],Sales_Export_2019_2020__2[[sales_rep]:[sales_rep]],$Y71,Sales_Export_2019_2020__2[[category]:[category]],AD$46) -> 0 | AE71: =SUMIFS(Sales_Export_2019_2020__2[[profit]:[profit]],Sales_Export_2019_2020__2[[sales_rep]:[sales_rep]],$Y71,Sales_Export_2019_2020__2[[category]:[category]],AE$46) -> 18517.2 | AF71: =SUMIFS(Sales_Export_2019_2020__2[[profit]:[profit]],Sales_Export_2019_2020__2[[sales_rep]:[sales_rep]],$Y71,Sales_Export_2019_2020__2[[category]:[category]],AF$46) -> 18034 | AG71: =SUMIFS(Sales_Export_2019_2020__2[[profit]:[profit]],Sales_Export_2019_2020__2[[sales_rep]:[sales_rep]],$Y71,Sales_Export_2019_2020__2[[category]:[category]],AG$46) -> 29122.87 | ... AI71: =SUMIFS(Sales_Export_2019_2020__2[[profit]:[profit]],Sales_Export_2019_2020__2[[sales_rep]:[sales_rep]],$Y71,Sales_Export_2019_2020__2[[category]:[category]],AI$46) -> 0
B72: Shermy McGready | C72: 18130.591 | D72: 15 | F72: 41 | G72: 17349.188 | K72: 15 | L72: Mellicent Mattys | M72: 1 | N72: 4 | O72: 3 | P72: 1 | Q72: 3 | R72: 3 | S72: 5 | U72: 1 | W72: 21 | Y72: Mellicent Mattys | Z72: =SUMIFS(Sales_Export_2019_2020__2[[profit]:[profit]],Sales_Export_2019_2020__2[[sales_rep]:[sales_rep]],$Y72,Sales_Export_2019_2020__2[[category]:[category]],Z$46) -> 10180.92 | AA72: =SUMIFS(Sales_Export_2019_2020__2[[profit]:[profit]],Sales_Export_2019_2020__2[[sales_rep]:[sales_rep]],$Y72,Sales_Export_2019_2020__2[[category]:[category]],AA$46) -> 111570.79 | AB72: =SUMIFS(Sales_Export_2019_2020__2[[profit]:[profit]],Sales_Export_2019_2020__2[[sales_rep]:[sales_rep]],$Y72,Sales_Export_2019_2020__2[[category]:[category]],AB$46) -> 67062.41 | AC72: =SUMIFS(Sales_Export_2019_2020__2[[profit]:[profit]],Sales_Export_2019_2020__2[[sales_rep]:[sales_rep]],$Y72,Sales_Export_2019_2020__2[[category]:[category]],AC$46) -> 22194.31 | AD72: =SUMIFS(Sales_Export_2019_2020__2[[profit]:[profit]],Sales_Export_2019_2020__2[[sales_rep]:[sales_rep]],$Y72,Sales_Export_2019_2020__2[[category]:[category]],AD$46) -> 47248.91 | AE72: =SUMIFS(Sales_Export_2019_2020__2[[profit]:[profit]],Sales_Export_2019_2020__2[[sales_rep]:[sales_rep]],$Y72,Sales_Export_2019_2020__2[[category]:[category]],AE$46) -> 52695.56 | AF72: =SUMIFS(Sales_Export_2019_2020__2[[profit]:[profit]],Sales_Export_2019_2020__2[[sales_rep]:[sales_rep]],$Y72,Sales_Export_2019_2020__2[[category]:[category]],AF$46) -> 97677.61 | AG72: =SUMIFS(Sales_Export_2019_2020__2[[profit]:[profit]],Sales_Export_2019_2020__2[[sales_rep]:[sales_rep]],$Y72,Sales_Export_2019_2020__2[[category]:[category]],AG$46) -> 0 | ... AI72: =SUMIFS(Sales_Export_2019_2020__2[[profit]:[profit]],Sales_Export_2019_2020__2[[sales_rep]:[sales_rep]],$Y72,Sales_Export_2019_2020__2[[category]:[category]],AI$46) -> 0
B73: Smitty Culverhouse | C73: 17349.188 | D73: 41 | F73: 38 | G73: 20780.183 | K73: 41 | L73: Nero Harbisher | N73: 2 | O73: 1 | P73: 4 | Q73: 6 | R73: 4 | S73: 4 | U73: 2 | V73: 5 | W73: 28 | Y73: Nero Harbisher | Z73: =SUMIFS(Sales_Export_2019_2020__2[[profit]:[profit]],Sales_Export_2019_2020__2[[sales_rep]:[sales_rep]],$Y73,Sales_Export_2019_2020__2[[category]:[category]],Z$46) -> 0 | AA73: =SUMIFS(Sales_Export_2019_2020__2[[profit]:[profit]],Sales_Export_2019_2020__2[[sales_rep]:[sales_rep]],$Y73,Sales_Export_2019_2020__2[[category]:[category]],AA$46) -> 26702.59 | AB73: =SUMIFS(Sales_Export_2019_2020__2[[profit]:[profit]],Sales_Export_2019_2020__2[[sales_rep]:[sales_rep]],$Y73,Sales_Export_2019_2020__2[[category]:[category]],AB$46) -> 34569.29 | AC73: =SUMIFS(Sales_Export_2019_2020__2[[profit]:[profit]],Sales_Export_2019_2020__2[[sales_rep]:[sales_rep]],$Y73,Sales_Export_2019_2020__2[[category]:[category]],AC$46) -> 100836.58 | AD73: =SUMIFS(Sales_Export_2019_2020__2[[profit]:[profit]],Sales_Export_2019_2020__2[[sales_rep]:[sales_rep]],$Y73,Sales_Export_2019_2020__2[[category]:[category]],AD$46) -> 127524.98 | AE73: =SUMIFS(Sales_Export_2019_2020__2[[profit]:[profit]],Sales_Export_2019_2020__2[[sales_rep]:[sales_rep]],$Y73,Sales_Export_2019_2020__2[[category]:[category]],AE$46) -> 69294.93 | AF73: =SUMIFS(Sales_Export_2019_2020__2[[profit]:[profit]],Sales_Export_2019_2020__2[[sales_rep]:[sales_rep]],$Y73,Sales_Export_2019_2020__2[[category]:[category]],AF$46) -> 57976.22 | AG73: =SUMIFS(Sales_Export_2019_2020__2[[profit]:[profit]],Sales_Export_2019_2020__2[[sales_rep]:[sales_rep]],$Y73,Sales_Export_2019_2020__2[[category]:[category]],AG$46) -> 0 | ... AI73: =SUMIFS(Sales_Export_2019_2020__2[[profit]:[profit]],Sales_Export_2019_2020__2[[sales_rep]:[sales_rep]],$Y73,Sales_Export_2019_2020__2[[category]:[category]],AI$46) -> 61594.45
B74: Tarrah Castelletti | C74: 20780.183 | D74: 38 | F74: 23 | G74: 19822.041 | K74: 38 | L74: Ora Grennan | M74: 1 | N74: 8 | O74: 8 | P74: 9 | Q74: 7 | R74: 7 | S74: 4 | T74: 1 | V74: 5 | W74: 50 | Y74: Ora Grennan | Z74: =SUMIFS(Sales_Export_2019_2020__2[[profit]:[profit]],Sales_Export_2019_2020__2[[sales_rep]:[sales_rep]],$Y74,Sales_Export_2019_2020__2[[category]:[category]],Z$46) -> 10723.72 | AA74: =SUMIFS(Sales_Export_2019_2020__2[[profit]:[profit]],Sales_Export_2019_2020__2[[sales_rep]:[sales_rep]],$Y74,Sales_Export_2019_2020__2[[category]:[category]],AA$46) -> 114716.2 | AB74: =SUMIFS(Sales_Export_2019_2020__2[[profit]:[profit]],Sales_Export_2019_2020__2[[sales_rep]:[sales_rep]],$Y74,Sales_Export_2019_2020__2[[category]:[category]],AB$46) -> 149437.08 | AC74: =SUMIFS(Sales_Export_2019_2020__2[[profit]:[profit]],Sales_Export_2019_2020__2[[sales_rep]:[sales_rep]],$Y74,Sales_Export_2019_2020__2[[category]:[category]],AC$46) -> 152809.88 | AD74: =SUMIFS(Sales_Export_2019_2020__2[[profit]:[profit]],Sales_Export_2019_2020__2[[sales_rep]:[sales_rep]],$Y74,Sales_Export_2019_2020__2[[category]:[category]],AD$46) -> 96252.38 | AE74: =SUMIFS(Sales_Export_2019_2020__2[[profit]:[profit]],Sales_Export_2019_2020__2[[sales_rep]:[sales_rep]],$Y74,Sales_Export_2019_2020__2[[category]:[category]],AE$46) -> 175281.11 | AF74: =SUMIFS(Sales_Export_2019_2020__2[[profit]:[profit]],Sales_Export_2019_2020__2[[sales_rep]:[sales_rep]],$Y74,Sales_Export_2019_2020__2[[category]:[category]],AF$46) -> 47083.34 | AG74: =SUMIFS(Sales_Export_2019_2020__2[[profit]:[profit]],Sales_Export_2019_2020__2[[sales_rep]:[sales_rep]],$Y74,Sales_Export_2019_2020__2[[category]:[category]],AG$46) -> 21431.02 | ... AI74: =SUMIFS(Sales_Export_2019_2020__2[[profit]:[profit]],Sales_Export_2019_2020__2[[sales_rep]:[sales_rep]],$Y74,Sales_Export_2019_2020__2[[category]:[category]],AI$46) -> 114790.5
B75: Wat Bowkley | C75: 19822.041 | D75: 23 | F75: 38 | G75: 21608.279 | K75: 23 | L75: Palm Wetherald | M75: 1 | N75: 2 | O75: 2 | P75: 1 | Q75: 2 | R75: 4 | S75: 3 | T75: 1 | V75: 4 | W75: 20 | Y75: Palm Wetherald | Z75: =SUMIFS(Sales_Export_2019_2020__2[[profit]:[profit]],Sales_Export_2019_2020__2[[sales_rep]:[sales_rep]],$Y75,Sales_Export_2019_2020__2[[category]:[category]],Z$46) -> 45565.87 | AA75: =SUMIFS(Sales_Export_2019_2020__2[[profit]:[profit]],Sales_Export_2019_2020__2[[sales_rep]:[sales_rep]],$Y75,Sales_Export_2019_2020__2[[category]:[category]],AA$46) -> 33012.46 | AB75: =SUMIFS(Sales_Export_2019_2020__2[[profit]:[profit]],Sales_Export_2019_2020__2[[sales_rep]:[sales_rep]],$Y75,Sales_Export_2019_2020__2[[category]:[category]],AB$46) -> 65199.54 | AC75: =SUMIFS(Sales_Export_2019_2020__2[[profit]:[profit]],Sales_Export_2019_2020__2[[sales_rep]:[sales_rep]],$Y75,Sales_Export_2019_2020__2[[category]:[category]],AC$46) -> 12439.73 | AD75: =SUMIFS(Sales_Export_2019_2020__2[[profit]:[profit]],Sales_Export_2019_2020__2[[sales_rep]:[sales_rep]],$Y75,Sales_Export_2019_2020__2[[category]:[category]],AD$46) -> 37435.42 | AE75: =SUMIFS(Sales_Export_2019_2020__2[[profit]:[profit]],Sales_Export_2019_2020__2[[sales_rep]:[sales_rep]],$Y75,Sales_Export_2019_2020__2[[category]:[category]],AE$46) -> 50294.03 | AF75: =SUMIFS(Sales_Export_2019_2020__2[[profit]:[profit]],Sales_Export_2019_2020__2[[sales_rep]:[sales_rep]],$Y75,Sales_Export_2019_2020__2[[category]:[category]],AF$46) -> 44195.71 | AG75: =SUMIFS(Sales_Export_2019_2020__2[[profit]:[profit]],Sales_Export_2019_2020__2[[sales_rep]:[sales_rep]],$Y75,Sales_Export_2019_2020__2[[category]:[category]],AG$46) -> 13347.05 | ... AI75: =SUMIFS(Sales_Export_2019_2020__2[[profit]:[profit]],Sales_Export_2019_2020__2[[sales_rep]:[sales_rep]],$Y75,Sales_Export_2019_2020__2[[category]:[category]],AI$46) -> 55643.43
B76: Winny Agnolo | C76: 21608.279 | D76: 38 | K76: 38 | L76: Perri Aldersley | O76: 2 | P76: 1 | Q76: 4 | R76: 1 | S76: 1 | T76: 1 | V76: 2 | W76: 12 | Y76: Perri Aldersley | Z76: =SUMIFS(Sales_Export_2019_2020__2[[profit]:[profit]],Sales_Export_2019_2020__2[[sales_rep]:[sales_rep]],$Y76,Sales_Export_2019_2020__2[[category]:[category]],Z$46) -> 0 | AA76: =SUMIFS(Sales_Export_2019_2020__2[[profit]:[profit]],Sales_Export_2019_2020__2[[sales_rep]:[sales_rep]],$Y76,Sales_Export_2019_2020__2[[category]:[category]],AA$46) -> 0 | AB76: =SUMIFS(Sales_Export_2019_2020__2[[profit]:[profit]],Sales_Export_2019_2020__2[[sales_rep]:[sales_rep]],$Y76,Sales_Export_2019_2020__2[[category]:[category]],AB$46) -> 29472.47 | AC76: =SUMIFS(Sales_Export_2019_2020__2[[profit]:[profit]],Sales_Export_2019_2020__2[[sales_rep]:[sales_rep]],$Y76,Sales_Export_2019_2020__2[[category]:[category]],AC$46) -> 6672.92 | AD76: =SUMIFS(Sales_Export_2019_2020__2[[profit]:[profit]],Sales_Export_2019_2020__2[[sales_rep]:[sales_rep]],$Y76,Sales_Export_2019_2020__2[[category]:[category]],AD$46) -> 47949.81 | AE76: =SUMIFS(Sales_Export_2019_2020__2[[profit]:[profit]],Sales_Export_2019_2020__2[[sales_rep]:[sales_rep]],$Y76,Sales_Export_2019_2020__2[[category]:[category]],AE$46) -> 16490.34 | AF76: =SUMIFS(Sales_Export_2019_2020__2[[profit]:[profit]],Sales_Export_2019_2020__2[[sales_rep]:[sales_rep]],$Y76,Sales_Export_2019_2020__2[[category]:[category]],AF$46) -> 30983.8 | AG76: =SUMIFS(Sales_Export_2019_2020__2[[profit]:[profit]],Sales_Export_2019_2020__2[[sales_rep]:[sales_rep]],$Y76,Sales_Export_2019_2020__2[[category]:[category]],AG$46) -> 5728.48 | ... AI76: =SUMIFS(Sales_Export_2019_2020__2[[profit]:[profit]],Sales_Export_2019_2020__2[[sales_rep]:[sales_rep]],$Y76,Sales_Export_2019_2020__2[[category]:[category]],AI$46) -> 26620.64
B77: Grand Total | C77: 18992.428 | D77: 1000 | L77: Shermy McGready | N77: 2 | P77: 2 | Q77: 3 | R77: 3 | S77: 1 | U77: 2 | V77: 2 | W77: 15 | Y77: Shermy McGready | Z77: =SUMIFS(Sales_Export_2019_2020__2[[profit]:[profit]],Sales_Export_2019_2020__2[[sales_rep]:[sales_rep]],$Y77,Sales_Export_2019_2020__2[[category]:[category]],Z$46) -> 0 | AA77: =SUMIFS(Sales_Export_2019_2020__2[[profit]:[profit]],Sales_Export_2019_2020__2[[sales_rep]:[sales_rep]],$Y77,Sales_Export_2019_2020__2[[category]:[category]],AA$46) -> 31192.4 | AB77: =SUMIFS(Sales_Export_2019_2020__2[[profit]:[profit]],Sales_Export_2019_2020__2[[sales_rep]:[sales_rep]],$Y77,Sales_Export_2019_2020__2[[category]:[category]],AB$46) -> 0 | AC77: =SUMIFS(Sales_Export_2019_2020__2[[profit]:[profit]],Sales_Export_2019_2020__2[[sales_rep]:[sales_rep]],$Y77,Sales_Export_2019_2020__2[[category]:[category]],AC$46) -> 39728.86 | AD77: =SUMIFS(Sales_Export_2019_2020__2[[profit]:[profit]],Sales_Export_2019_2020__2[[sales_rep]:[sales_rep]],$Y77,Sales_Export_2019_2020__2[[category]:[category]],AD$46) -> 72969.44 | AE77: =SUMIFS(Sales_Export_2019_2020__2[[profit]:[profit]],Sales_Export_2019_2020__2[[sales_rep]:[sales_rep]],$Y77,Sales_Export_2019_2020__2[[category]:[category]],AE$46) -> 52357.18 | AF77: =SUMIFS(Sales_Export_2019_2020__2[[profit]:[profit]],Sales_Export_2019_2020__2[[sales_rep]:[sales_rep]],$Y77,Sales_Export_2019_2020__2[[category]:[category]],AF$46) -> 7679.92 | AG77: =SUMIFS(Sales_Export_2019_2020__2[[profit]:[profit]],Sales_Export_2019_2020__2[[sales_rep]:[sales_rep]],$Y77,Sales_Export_2019_2020__2[[category]:[category]],AG$46) -> 0 | ... AI77: =SUMIFS(Sales_Export_2019_2020__2[[profit]:[profit]],Sales_Export_2019_2020__2[[sales_rep]:[sales_rep]],$Y77,Sales_Export_2019_2020__2[[category]:[category]],AI$46) -> 35128.48
I78: Row Labels | J78: Total Profit | L78: Smitty Culverhouse | M78: 2 | N78: 7 | O78: 3 | P78: 3 | Q78: 4 | R78: 4 | S78: 10 | T78: 1 | U78: 4 | V78: 3 | W78: 41 | Y78: Smitty Culverhouse | Z78: =SUMIFS(Sales_Export_2019_2020__2[[profit]:[profit]],Sales_Export_2019_2020__2[[sales_rep]:[sales_rep]],$Y78,Sales_Export_2019_2020__2[[category]:[category]],Z$46) -> 44608.65 | AA78: =SUMIFS(Sales_Export_2019_2020__2[[profit]:[profit]],Sales_Export_2019_2020__2[[sales_rep]:[sales_rep]],$Y78,Sales_Export_2019_2020__2[[category]:[category]],AA$46) -> 102453.53 | AB78: =SUMIFS(Sales_Export_2019_2020__2[[profit]:[profit]],Sales_Export_2019_2020__2[[sales_rep]:[sales_rep]],$Y78,Sales_Export_2019_2020__2[[category]:[category]],AB$46) -> 67856.85 | AC78: =SUMIFS(Sales_Export_2019_2020__2[[profit]:[profit]],Sales_Export_2019_2020__2[[sales_rep]:[sales_rep]],$Y78,Sales_Export_2019_2020__2[[category]:[category]],AC$46) -> 23692.46 | AD78: =SUMIFS(Sales_Export_2019_2020__2[[profit]:[profit]],Sales_Export_2019_2020__2[[sales_rep]:[sales_rep]],$Y78,Sales_Export_2019_2020__2[[category]:[category]],AD$46) -> 93666.45 | AE78: =SUMIFS(Sales_Export_2019_2020__2[[profit]:[profit]],Sales_Export_2019_2020__2[[sales_rep]:[sales_rep]],$Y78,Sales_Export_2019_2020__2[[category]:[category]],AE$46) -> 46106.8 | AF78: =SUMIFS(Sales_Export_2019_2020__2[[profit]:[profit]],Sales_Export_2019_2020__2[[sales_rep]:[sales_rep]],$Y78,Sales_Export_2019_2020__2[[category]:[category]],AF$46) -> 183770.2 | AG78: =SUMIFS(Sales_Export_2019_2020__2[[profit]:[profit]],Sales_Export_2019_2020__2[[sales_rep]:[sales_rep]],$Y78,Sales_Export_2019_2020__2[[category]:[category]],AG$46) -> 6281.64 | ... AI78: =SUMIFS(Sales_Export_2019_2020__2[[profit]:[profit]],Sales_Export_2019_2020__2[[sales_rep]:[sales_rep]],$Y78,Sales_Export_2019_2020__2[[category]:[category]],AI$46) -> 67685.46
B79: Row Labels | C79: Avg Profit per Sale | I79: Accessories | J79: 783896.33 | L79: Tarrah Castelletti | M79: 1 | N79: 6 | O79: 4 | P79: 4 | Q79: 7 | R79: 8 | S79: 4 | T79: 1 | U79: 1 | V79: 2 | W79: 38 | Y79: Tarrah Castelletti | Z79: =SUMIFS(Sales_Export_2019_2020__2[[profit]:[profit]],Sales_Export_2019_2020__2[[sales_rep]:[sales_rep]],$Y79,Sales_Export_2019_2020__2[[category]:[category]],Z$46) -> 45802.88 | AA79: =SUMIFS(Sales_Export_2019_2020__2[[profit]:[profit]],Sales_Export_2019_2020__2[[sales_rep]:[sales_rep]],$Y79,Sales_Export_2019_2020__2[[category]:[category]],AA$46) -> 125629.82 | AB79: =SUMIFS(Sales_Export_2019_2020__2[[profit]:[profit]],Sales_Export_2019_2020__2[[sales_rep]:[sales_rep]],$Y79,Sales_Export_2019_2020__2[[category]:[category]],AB$46) -> 58254.61 | AC79: =SUMIFS(Sales_Export_2019_2020__2[[profit]:[profit]],Sales_Export_2019_2020__2[[sales_rep]:[sales_rep]],$Y79,Sales_Export_2019_2020__2[[category]:[category]],AC$46) -> 74822.49 | AD79: =SUMIFS(Sales_Export_2019_2020__2[[profit]:[profit]],Sales_Export_2019_2020__2[[sales_rep]:[sales_rep]],$Y79,Sales_Export_2019_2020__2[[category]:[category]],AD$46) -> 139521.18 | AE79: =SUMIFS(Sales_Export_2019_2020__2[[profit]:[profit]],Sales_Export_2019_2020__2[[sales_rep]:[sales_rep]],$Y79,Sales_Export_2019_2020__2[[category]:[category]],AE$46) -> 180788.93 | AF79: =SUMIFS(Sales_Export_2019_2020__2[[profit]:[profit]],Sales_Export_2019_2020__2[[sales_rep]:[sales_rep]],$Y79,Sales_Export_2019_2020__2[[category]:[category]],AF$46) -> 54980.24 | AG79: =SUMIFS(Sales_Export_2019_2020__2[[profit]:[profit]],Sales_Export_2019_2020__2[[sales_rep]:[sales_rep]],$Y79,Sales_Export_2019_2020__2[[category]:[category]],AG$46) -> 51918.06 | ... AI79: =SUMIFS(Sales_Export_2019_2020__2[[profit]:[profit]],Sales_Export_2019_2020__2[[sales_rep]:[sales_rep]],$Y79,Sales_Export_2019_2020__2[[category]:[category]],AI$46) -> 35983.92
B80: Alyosha Meah | C80: 18553.632 | E80: Corr between total sales and prof per sale | F80: =CORREL(C42:C76,D42:D76) -> 0.43963324 | I80: Appliances | J80: 2534879.3 | L80: Wat Bowkley | N80: 4 | O80: 3 | P80: 1 | Q80: 5 | R80: 2 | S80: 6 | T80: 1 | U80: 1 | W80: 23 | Y80: Wat Bowkley | Z80: =SUMIFS(Sales_Export_2019_2020__2[[profit]:[profit]],Sales_Export_2019_2020__2[[sales_rep]:[sales_rep]],$Y80,Sales_Export_2019_2020__2[[category]:[category]],Z$46) -> 0 | AA80: =SUMIFS(Sales_Export_2019_2020__2[[profit]:[profit]],Sales_Export_2019_2020__2[[sales_rep]:[sales_rep]],$Y80,Sales_Export_2019_2020__2[[category]:[category]],AA$46) -> 66993.41 | AB80: =SUMIFS(Sales_Export_2019_2020__2[[profit]:[profit]],Sales_Export_2019_2020__2[[sales_rep]:[sales_rep]],$Y80,Sales_Export_2019_2020__2[[category]:[category]],AB$46) -> 72652.46 | AC80: =SUMIFS(Sales_Export_2019_2020__2[[profit]:[profit]],Sales_Export_2019_2020__2[[sales_rep]:[sales_rep]],$Y80,Sales_Export_2019_2020__2[[category]:[category]],AC$46) -> 22742.02 | AD80: =SUMIFS(Sales_Export_2019_2020__2[[profit]:[profit]],Sales_Export_2019_2020__2[[sales_rep]:[sales_rep]],$Y80,Sales_Export_2019_2020__2[[category]:[category]],AD$46) -> 124359.1 | AE80: =SUMIFS(Sales_Export_2019_2020__2[[profit]:[profit]],Sales_Export_2019_2020__2[[sales_rep]:[sales_rep]],$Y80,Sales_Export_2019_2020__2[[category]:[category]],AE$46) -> 12219.26 | AF80: =SUMIFS(Sales_Export_2019_2020__2[[profit]:[profit]],Sales_Export_2019_2020__2[[sales_rep]:[sales_rep]],$Y80,Sales_Export_2019_2020__2[[category]:[category]],AF$46) -> 126064.77 | AG80: =SUMIFS(Sales_Export_2019_2020__2[[profit]:[profit]],Sales_Export_2019_2020__2[[sales_rep]:[sales_rep]],$Y80,Sales_Export_2019_2020__2[[category]:[category]],AG$46) -> 19705.75 | ... AI80: =SUMIFS(Sales_Export_2019_2020__2[[profit]:[profit]],Sales_Export_2019_2020__2[[sales_rep]:[sales_rep]],$Y80,Sales_Export_2019_2020__2[[category]:[category]],AI$46) -> 0
B81: Amelina Piscopiello | C81: 19614.378 | F81: =AVERAGE(D42:D76) -> 28.571429 | I81: Beauty | J81: 2118427.4 | L81: Winny Agnolo | M81: 3 | N81: 2 | O81: 4 | P81: 9 | Q81: 8 | R81: 2 | S81: 3 | T81: 2 | U81: 3 | V81: 2 | W81: 38 | Y81: Winny Agnolo | Z81: =SUMIFS(Sales_Export_2019_2020__2[[profit]:[profit]],Sales_Export_2019_2020__2[[sales_rep]:[sales_rep]],$Y81,Sales_Export_2019_2020__2[[category]:[category]],Z$46) -> 84454.28 | AA81: =SUMIFS(Sales_Export_2019_2020__2[[profit]:[profit]],Sales_Export_2019_2020__2[[sales_rep]:[sales_rep]],$Y81,Sales_Export_2019_2020__2[[category]:[category]],AA$46) -> 25590.44 | AB81: =SUMIFS(Sales_Export_2019_2020__2[[profit]:[profit]],Sales_Export_2019_2020__2[[sales_rep]:[sales_rep]],$Y81,Sales_Export_2019_2020__2[[category]:[category]],AB$46) -> 57278.54 | AC81: =SUMIFS(Sales_Export_2019_2020__2[[profit]:[profit]],Sales_Export_2019_2020__2[[sales_rep]:[sales_rep]],$Y81,Sales_Export_2019_2020__2[[category]:[category]],AC$46) -> 167134.78 | AD81: =SUMIFS(Sales_Export_2019_2020__2[[profit]:[profit]],Sales_Export_2019_2020__2[[sales_rep]:[sales_rep]],$Y81,Sales_Export_2019_2020__2[[category]:[category]],AD$46) -> 185266.1 | AE81: =SUMIFS(Sales_Export_2019_2020__2[[profit]:[profit]],Sales_Export_2019_2020__2[[sales_rep]:[sales_rep]],$Y81,Sales_Export_2019_2020__2[[category]:[category]],AE$46) -> 32493.39 | AF81: =SUMIFS(Sales_Export_2019_2020__2[[profit]:[profit]],Sales_Export_2019_2020__2[[sales_rep]:[sales_rep]],$Y81,Sales_Export_2019_2020__2[[category]:[category]],AF$46) -> 39253.78 | AG81: =SUMIFS(Sales_Export_2019_2020__2[[profit]:[profit]],Sales_Export_2019_2020__2[[sales_rep]:[sales_rep]],$Y81,Sales_Export_2019_2020__2[[category]:[category]],AG$46) -> 81723.72 | ... AI81: =SUMIFS(Sales_Export_2019_2020__2[[profit]:[profit]],Sales_Export_2019_2020__2[[sales_rep]:[sales_rep]],$Y81,Sales_Export_2019_2020__2[[category]:[category]],AI$46) -> 45909.38
B82: Anita Woakes | C82: 17251.023 | I82: Books | J82: 2225913.9 | L82: Grand Total | M82: 35 | N82: 131 | O82: 115 | P82: 117 | Q82: 155 | R82: 134 | S82: 139 | T82: 29 | U82: 50 | V82: 95 | W82: 1000 | Y82: Average | Z82: =AVERAGEIF(Z47:Z81,"<>0",Z47:Z81) -> 37328.397 | AA82: =AVERAGEIF(AA47:AA81,"<>0",AA47:AA81) -> 79214.979 | AB82: =AVERAGEIF(AB47:AB81,"<>0",AB47:AB81) -> 73049.222 | AC82: =AVERAGEIF(AC47:AC81,"<>0",AC47:AC81) -> 71803.674 | AD82: =AVERAGEIF(AD47:AD81,"<>0",AD47:AD81) -> 98064.603 | AE82: =AVERAGEIF(AE47:AE81,"<>0",AE47:AE81) -> 75035.406 | AF82: =AVERAGEIF(AF47:AF81,"<>0",AF47:AF81) -> 75288.111 | AG82: =AVERAGEIF(AG47:AG81,"<>0",AG47:AG81) -> 26144.462 | ... AI82: =AVERAGEIF(AI47:AI81,"<>0",AI47:AI81) -> 62780.954
B83: Aurelie Wren | C83: 18242.499 | I83: Clothing | J83: 2941938.1 | Y83: % of Profits | Z83: Accessories | AA83: Appliances | AB83: Beauty | AC83: Books | AD83: Clothing | AE83: Electronics | AF83: Games | AG83: Other | AH83: Outdoors | AI83: Smartphones | AK83: % of Sales | AL83: Accessories | AM83: Appliances | AN83: Beauty | AO83: Books | AP83: Clothing | AQ83: Electronics | AR83: Games | AS83: Other | AT83: Outdoors | AU83: Smartphones
B84: Avrit Chanders | C84: 18656.655 | I84: Electronics | J84: 2401133 | Y84: Alyosha Meah | Z84: =Z47/SUM($Z47:$AI47) -> 0.020243826 | AA84: =AA47/SUM($Z47:$AI47) -> 0.060930443 | AB84: =AB47/SUM($Z47:$AI47) -> 0.15647621 | AC84: =AC47/SUM($Z47:$AI47) -> 0.081177274 | AD84: =AD47/SUM($Z47:$AI47) -> 0.18843389 | AE84: =AE47/SUM($Z47:$AI47) -> 0.11275399 | AF84: =AF47/SUM($Z47:$AI47) -> 0.10161843 | AG84: =AG47/SUM($Z47:$AI47) -> 0.05495571 | ... AI84: =AI47/SUM($Z47:$AI47) -> 0.17899241 | AK84: Alyosha Meah | AL84: =M85/$W85 -> 0.025 | AM84: =N85/$W85 -> 0.1 | AN84: =O$85/$W85 -> 0.1 | AO84: =P$85/$W85 -> 0.1 | AP84: =Q$85/$W85 -> 0.225 | AQ84: =R$85/$W85 -> 0.1 | AR84: =S$85/$W85 -> 0.15 | AS84: =T$85/$W85 -> 0.075 | AT84: =U$85/$W85 -> 0.025 | AU84: =V$85/$W85 -> 0.1
B85: Bank Coumbe | C85: 17859.19 | I85: Games | J85: 2559795.8 | L85: Alyosha Meah | M85: 1 | N85: 4 | O85: 4 | P85: 4 | Q85: 9 | R85: 4 | S85: 6 | T85: 3 | U85: 1 | V85: 4 | W85: 40 | Y85: Amelina Piscopiello | Z85: =Z48/SUM($Z48:$AI48) -> 0 | AA85: =AA48/SUM($Z48:$AI48) -> 0.18202733 | AB85: =AB48/SUM($Z48:$AI48) -> 0.048423207 | AC85: =AC48/SUM($Z48:$AI48) -> 0.079932146 | AD85: =AD48/SUM($Z48:$AI48) -> 0.19211652 | AE85: =AE48/SUM($Z48:$AI48) -> 0.1472535 | AF85: =AF48/SUM($Z48:$AI48) -> 0.13630377 | AG85: =AG48/SUM($Z48:$AI48) -> 0.053803508 | ... AI85: =AI48/SUM($Z48:$AI48) -> 0.11121104 | AK85: Amelina Piscopiello | AL85: =M86/$W86 -> 0 | AM85: =N86/$W86 -> 0.17857143 | AN85: =O86/$W86 -> 0.053571429 | AO85: =P86/$W86 -> 0.071428571 | AP85: =Q86/$W86 -> 0.16071429 | AQ85: =R86/$W86 -> 0.17857143 | AR85: =S86/$W86 -> 0.125 | AS85: =T86/$W86 -> 0.071428571 | ... AU85: =V86/$W86 -> 0.125
B86: Bernadine Fullagar | C86: 22229.617 | I86: Other | J86: 549033.71 | L86: Amelina Piscopiello | N86: 10 | O86: 3 | P86: 4 | Q86: 9 | R86: 10 | S86: 7 | T86: 4 | U86: 2 | V86: 7 | W86: 56 | Y86: Anita Woakes | Z86: =Z49/SUM($Z49:$AI49) -> 0.11043618 | AA86: =AA49/SUM($Z49:$AI49) -> 0.068772252 | AB86: =AB49/SUM($Z49:$AI49) -> 0.14675396 | AC86: =AC49/SUM($Z49:$AI49) -> 0.11563617 | AD86: =AD49/SUM($Z49:$AI49) -> 0.11950736 | AE86: =AE49/SUM($Z49:$AI49) -> 0.14580182 | AF86: =AF49/SUM($Z49:$AI49) -> 0.13126489 | AG86: =AG49/SUM($Z49:$AI49) -> 0.027849541 | ... AI86: =AI49/SUM($Z49:$AI49) -> 0.13397782 | AK86: Anita Woakes | AL86: =M87/$W87 -> 0.055555556 | AM86: =N87/$W87 -> 0.083333333 | AN86: =O87/$W87 -> 0.22222222 | AO86: =P87/$W87 -> 0.13888889 | AP86: =Q87/$W87 -> 0.13888889 | AQ86: =R87/$W87 -> 0.13888889 | AR86: =S87/$W87 -> 0.083333333 | AS86: =T87/$W87 -> 0.027777778 | ... AU86: =V87/$W87 -> 0.11111111
B87: Bertha Walbrook | C87: 19239.037 | I87: Outdoors | J87: 1056762.5 | L87: Anita Woakes | M87: 2 | N87: 3 | O87: 8 | P87: 5 | Q87: 5 | R87: 5 | S87: 3 | T87: 1 | V87: 4 | W87: 36 | Y87: Aurelie Wren | Z87: =Z50/SUM($Z50:$AI50) -> 0.033974248 | AA87: =AA50/SUM($Z50:$AI50) -> 0.12651592 | AB87: =AB50/SUM($Z50:$AI50) -> 0.067673547 | AC87: =AC50/SUM($Z50:$AI50) -> 0.17421606 | AD87: =AD50/SUM($Z50:$AI50) -> 0.13118387 | AE87: =AE50/SUM($Z50:$AI50) -> 0.1555828 | AF87: =AF50/SUM($Z50:$AI50) -> 0.12211247 | AG87: =AG50/SUM($Z50:$AI50) -> 0.021449701 | ... AI87: =AI50/SUM($Z50:$AI50) -> 0.073663596 | AK87: Aurelie Wren | AL87: =M88/$W88 -> 0.038461538 | AM87: =N88/$W88 -> 0.11538462 | AN87: =O88/$W88 -> 0.057692308 | AO87: =P88/$W88 -> 0.15384615 | AP87: =Q88/$W88 -> 0.15384615 | AQ87: =R88/$W88 -> 0.13461538 | AR87: =S88/$W88 -> 0.13461538 | AS87: =T88/$W88 -> 0.038461538 | ... AU87: =V88/$W88 -> 0.096153846
B88: Brynn Dempster | C88: 19592.632 | I88: Smartphones | J88: 1820647.7 | L88: Aurelie Wren | M88: 2 | N88: 6 | O88: 3 | P88: 8 | Q88: 8 | R88: 7 | S88: 7 | T88: 2 | U88: 4 | V88: 5 | W88: 52 | Y88: Avrit Chanders | Z88: =Z51/SUM($Z51:$AI51) -> 0.021629903 | AA88: =AA51/SUM($Z51:$AI51) -> 0.16870196 | AB88: =AB51/SUM($Z51:$AI51) -> 0.020966145 | AC88: =AC51/SUM($Z51:$AI51) -> 0.19287289 | AD88: =AD51/SUM($Z51:$AI51) -> 0.14568876 | AE88: =AE51/SUM($Z51:$AI51) -> 0.13286214 | AF88: =AF51/SUM($Z51:$AI51) -> 0.097658475 | AG88: =AG51/SUM($Z51:$AI51) -> 0 | ... AI88: =AI51/SUM($Z51:$AI51) -> 0.18081441 | AK88: Avrit Chanders | AL88: =M89/$W89 -> 0.023255814 | AM88: =N89/$W89 -> 0.18604651 | AN88: =O89/$W89 -> 0.023255814 | AO88: =P89/$W89 -> 0.18604651 | AP88: =Q89/$W89 -> 0.11627907 | AQ88: =R89/$W89 -> 0.13953488 | AR88: =S89/$W89 -> 0.1627907 | AS88: =T89/$W89 -> 0 | ... AU88: =V89/$W89 -> 0.11627907
B89: Bunnie Tonbridge | C89: 20529.511 | I89: Grand Total | J89: 18992428 | L89: Avrit Chanders | M89: 1 | N89: 8 | O89: 1 | P89: 8 | Q89: 5 | R89: 6 | S89: 7 | U89: 2 | V89: 5 | W89: 43 | Y89: Bank Coumbe | Z89: =Z52/SUM($Z52:$AI52) -> 0 | AA89: =AA52/SUM($Z52:$AI52) -> 0 | AB89: =AB52/SUM($Z52:$AI52) -> 0 | AC89: =AC52/SUM($Z52:$AI52) -> 0 | AD89: =AD52/SUM($Z52:$AI52) -> 0 | AE89: =AE52/SUM($Z52:$AI52) -> 0.2897945 | AF89: =AF52/SUM($Z52:$AI52) -> 0.7102055 | AG89: =AG52/SUM($Z52:$AI52) -> 0 | ... AI89: =AI52/SUM($Z52:$AI52) -> 0 | AK89: Bank Coumbe | AL89: =M90/$W90 -> 0 | AM89: =N90/$W90 -> 0 | AN89: =O90/$W90 -> 0 | AO89: =P90/$W90 -> 0 | AP89: =Q90/$W90 -> 0 | AQ89: =R90/$W90 -> 0.5 | AR89: =S90/$W90 -> 0.5 | AS89: =T90/$W90 -> 0 | ... AU89: =V90/$W90 -> 0
B90: Caro Morfield | C90: 16436.134 | L90: Bank Coumbe | R90: 1 | S90: 1 | W90: 2 | Y90: Bernadine Fullagar | Z90: =Z53/SUM($Z53:$AI53) -> 0.055766892 | AA90: =AA53/SUM($Z53:$AI53) -> 0.20752287 | AB90: =AB53/SUM($Z53:$AI53) -> 0.13051429 | AC90: =AC53/SUM($Z53:$AI53) -> 0.2359939 | AD90: =AD53/SUM($Z53:$AI53) -> 0 | AE90: =AE53/SUM($Z53:$AI53) -> 0.055668914 | AF90: =AF53/SUM($Z53:$AI53) -> 0.24936879 | AG90: =AG53/SUM($Z53:$AI53) -> 0 | ... AI90: =AI53/SUM($Z53:$AI53) -> 0.065164355 | AK90: Bernadine Fullagar | AL90: =M91/$W91 -> 0.066666667 | AM90: =N91/$W91 -> 0.13333333 | AN90: =O91/$W91 -> 0.13333333 | AO90: =P91/$W91 -> 0.26666667 | AP90: =Q91/$W91 -> 0 | AQ90: =R91/$W91 -> 0.066666667 | AR90: =S91/$W91 -> 0.26666667 | AS90: =T91/$W91 -> 0 | ... AU90: =V91/$W91 -> 0.066666667
B91: Case Desorts | C91: 13931.777 | L91: Bernadine Fullagar | M91: 1 | N91: 2 | O91: 2 | P91: 4 | R91: 1 | S91: 4 | V91: 1 | W91: 15 | Y91: Bertha Walbrook | Z91: =Z54/SUM($Z54:$AI54) -> 0 | AA91: =AA54/SUM($Z54:$AI54) -> 0.17890582 | AB91: =AB54/SUM($Z54:$AI54) -> 0.066612021 | AC91: =AC54/SUM($Z54:$AI54) -> 0 | AD91: =AD54/SUM($Z54:$AI54) -> 0 | AE91: =AE54/SUM($Z54:$AI54) -> 0.35770883 | AF91: =AF54/SUM($Z54:$AI54) -> 0.31412978 | AG91: =AG54/SUM($Z54:$AI54) -> 0 | ... AI91: =AI54/SUM($Z54:$AI54) -> 0 | AK91: Bertha Walbrook | AL91: =M92/$W92 -> 0 | AM91: =N92/$W92 -> 0.11111111 | AN91: =O92/$W92 -> 0.11111111 | AO91: =P92/$W92 -> 0 | AP91: =Q92/$W92 -> 0 | AQ91: =R92/$W92 -> 0.44444444 | AR91: =S92/$W92 -> 0.22222222 | AS91: =T92/$W92 -> 0 | ... AU91: =V92/$W92 -> 0
B92: Casie MacBain | C92: 19414.931 | L92: Bertha Walbrook | N92: 1 | O92: 1 | R92: 4 | S92: 2 | U92: 1 | W92: 9 | Y92: Brynn Dempster | Z92: =Z55/SUM($Z55:$AI55) -> 0.067741791 | AA92: =AA55/SUM($Z55:$AI55) -> 0.12620019 | AB92: =AB55/SUM($Z55:$AI55) -> 0.10803445 | AC92: =AC55/SUM($Z55:$AI55) -> 0.067173907 | AD92: =AD55/SUM($Z55:$AI55) -> 0.13739988 | AE92: =AE55/SUM($Z55:$AI55) -> 0.099274127 | AF92: =AF55/SUM($Z55:$AI55) -> 0.20970902 | AG92: =AG55/SUM($Z55:$AI55) -> 0.063514269 | ... AI92: =AI55/SUM($Z55:$AI55) -> 0.069287046 | AK92: Brynn Dempster | AL92: =M93/$W93 -> 0.048780488 | AM92: =N93/$W93 -> 0.12195122 | AN92: =O93/$W93 -> 0.12195122 | AO92: =P93/$W93 -> 0.073170732 | AP92: =Q93/$W93 -> 0.14634146 | AQ92: =R93/$W93 -> 0.14634146 | AR92: =S93/$W93 -> 0.19512195 | AS92: =T93/$W93 -> 0.024390244 | ... AU92: =V93/$W93 -> 0.073170732
B93: Cobby Andersen | C93: 9952.408 | L93: Brynn Dempster | M93: 2 | N93: 5 | O93: 5 | P93: 3 | Q93: 6 | R93: 6 | S93: 8 | T93: 1 | U93: 2 | V93: 3 | W93: 41 | Y93: Bunnie Tonbridge | Z93: =Z56/SUM($Z56:$AI56) -> 0 | AA93: =AA56/SUM($Z56:$AI56) -> 0.034515001 | AB93: =AB56/SUM($Z56:$AI56) -> 0.15186738 | AC93: =AC56/SUM($Z56:$AI56) -> 0.22374787 | AD93: =AD56/SUM($Z56:$AI56) -> 0.11963662 | AE93: =AE56/SUM($Z56:$AI56) -> 0.18165125 | AF93: =AF56/SUM($Z56:$AI56) -> 0.083927411 | AG93: =AG56/SUM($Z56:$AI56) -> 0.014254771 | ... AI93: =AI56/SUM($Z56:$AI56) -> 0.10446097 | AK93: Bunnie Tonbridge | AL93: =M94/$W94 -> 0 | AM93: =N94/$W94 -> 0.043478261 | AN93: =O94/$W94 -> 0.17391304 | AO93: =P94/$W94 -> 0.086956522 | AP93: =Q94/$W94 -> 0.17391304 | AQ93: =R94/$W94 -> 0.13043478 | AR93: =S94/$W94 -> 0.13043478 | AS93: =T94/$W94 -> 0.043478261 | ... AU93: =V94/$W94 -> 0.086956522
B94: Collin Mackness | C94: 15738.88 | L94: Bunnie Tonbridge | N94: 1 | O94: 4 | P94: 2 | Q94: 4 | R94: 3 | S94: 3 | T94: 1 | U94: 3 | V94: 2 | W94: 23 | Y94: Caro Morfield | Z94: =Z57/SUM($Z57:$AI57) -> 0 | AA94: =AA57/SUM($Z57:$AI57) -> 0.037222047 | AB94: =AB57/SUM($Z57:$AI57) -> 0.17457753 | AC94: =AC57/SUM($Z57:$AI57) -> 0.032208871 | AD94: =AD57/SUM($Z57:$AI57) -> 0.20390545 | AE94: =AE57/SUM($Z57:$AI57) -> 0.16106036 | AF94: =AF57/SUM($Z57:$AI57) -> 0.20654249 | AG94: =AG57/SUM($Z57:$AI57) -> 0.0090903163 | ... AI94: =AI57/SUM($Z57:$AI57) -> 0.13075002 | AK94: Caro Morfield | AL94: =M95/$W95 -> 0 | AM94: =N95/$W95 -> 0.034482759 | AN94: =O95/$W95 -> 0.20689655 | AO94: =P95/$W95 -> 0.034482759 | AP94: =Q95/$W95 -> 0.20689655 | AQ94: =R95/$W95 -> 0.17241379 | AR94: =S95/$W95 -> 0.10344828 | AS94: =T95/$W95 -> 0.034482759 | ... AU94: =V95/$W95 -> 0.17241379
B95: Corene Shirer | C95: 22405.31 | L95: Caro Morfield | N95: 1 | O95: 6 | P95: 1 | Q95: 6 | R95: 5 | S95: 3 | T95: 1 | U95: 1 | V95: 5 | W95: 29 | Y95: Case Desorts | Z95: =Z58/SUM($Z58:$AI58) -> 0 | AA95: =AA58/SUM($Z58:$AI58) -> 0.049594297 | AB95: =AB58/SUM($Z58:$AI58) -> 0 | AC95: =AC58/SUM($Z58:$AI58) -> 0.050566176 | AD95: =AD58/SUM($Z58:$AI58) -> 0.24600547 | AE95: =AE58/SUM($Z58:$AI58) -> 0.15695785 | AF95: =AF58/SUM($Z58:$AI58) -> 0 | AG95: =AG58/SUM($Z58:$AI58) -> 0 | ... AI95: =AI58/SUM($Z58:$AI58) -> 0.49687621 | AK95: Case Desorts | AL95: =M96/$W96 -> 0 | AM95: =N96/$W96 -> 0.16666667 | AN95: =O96/$W96 -> 0 | AO95: =P96/$W96 -> 0.16666667 | AP95: =Q96/$W96 -> 0.33333333 | AQ95: =R96/$W96 -> 0.16666667 | AR95: =S96/$W96 -> 0 | AS95: =T96/$W96 -> 0 | ... AU95: =V96/$W96 -> 0.16666667
B96: Crysta Halls | C96: 17871.528 | L96: Case Desorts | N96: 1 | P96: 1 | Q96: 2 | R96: 1 | V96: 1 | W96: 6 | Y96: Casie MacBain | Z96: =Z59/SUM($Z59:$AI59) -> 0.12173234 | AA96: =AA59/SUM($Z59:$AI59) -> 0.28035034 | AB96: =AB59/SUM($Z59:$AI59) -> 0.0758227 | AC96: =AC59/SUM($Z59:$AI59) -> 0.024301636 | AD96: =AD59/SUM($Z59:$AI59) -> 0.10755354 | AE96: =AE59/SUM($Z59:$AI59) -> 0.20772342 | AF96: =AF59/SUM($Z59:$AI59) -> 0.12892178 | AG96: =AG59/SUM($Z59:$AI59) -> 0 | ... AI96: =AI59/SUM($Z59:$AI59) -> 0.033131094 | AK96: Casie MacBain | AL96: =M97/$W97 -> 0.16666667 | AM96: =N97/$W97 -> 0.20833333 | AN96: =O97/$W97 -> 0.041666667 | AO96: =P97/$W97 -> 0.041666667 | AP96: =Q97/$W97 -> 0.125 | AQ96: =R97/$W97 -> 0.25 | AR96: =S97/$W97 -> 0.083333333 | AS96: =T97/$W97 -> 0 | ... AU96: =V97/$W97 -> 0.041666667
B97: Genevra Charrisson | C97: 19501.181 | L97: Casie MacBain | M97: 4 | N97: 5 | O97: 1 | P97: 1 | Q97: 3 | R97: 6 | S97: 2 | U97: 1 | V97: 1 | W97: 24 | Y97: Cobby Andersen | Z97: =Z60/SUM($Z60:$AI60) -> 0 | AA97: =AA60/SUM($Z60:$AI60) -> 0.18035535 | AB97: =AB60/SUM($Z60:$AI60) -> 0 | AC97: =AC60/SUM($Z60:$AI60) -> 0.66734945 | AD97: =AD60/SUM($Z60:$AI60) -> 0 | AE97: =AE60/SUM($Z60:$AI60) -> 0 | AF97: =AF60/SUM($Z60:$AI60) -> 0.1522952 | AG97: =AG60/SUM($Z60:$AI60) -> 0 | ... AI97: =AI60/SUM($Z60:$AI60) -> 0 | AK97: Cobby Andersen | AL97: =M98/$W98 -> 0 | AM97: =N98/$W98 -> 0.2 | AN97: =O98/$W98 -> 0 | AO97: =P98/$W98 -> 0.6 | AP97: =Q98/$W98 -> 0 | AQ97: =R98/$W98 -> 0 | AR97: =S98/$W98 -> 0.2 | AS97: =T98/$W98 -> 0 | ... AU97: =V98/$W98 -> 0
B98: Hortense Gerring | C98: 19603.876 | L98: Cobby Andersen | N98: 1 | P98: 3 | S98: 1 | W98: 5 | Y98: Collin Mackness | Z98: =Z61/SUM($Z61:$AI61) -> 0.060860324 | AA98: =AA61/SUM($Z61:$AI61) -> 0.32172323 | AB98: =AB61/SUM($Z61:$AI61) -> 0 | AC98: =AC61/SUM($Z61:$AI61) -> 0 | AD98: =AD61/SUM($Z61:$AI61) -> 0.15424996 | AE98: =AE61/SUM($Z61:$AI61) -> 0 | AF98: =AF61/SUM($Z61:$AI61) -> 0.25300095 | AG98: =AG61/SUM($Z61:$AI61) -> 0 | ... AI98: =AI61/SUM($Z61:$AI61) -> 0.21016553 | AK98: Collin Mackness | AL98: =M99/$W99 -> 0.16666667 | AM98: =N99/$W99 -> 0.33333333 | AN98: =O99/$W99 -> 0 | AO98: =P99/$W99 -> 0 | AP98: =Q99/$W99 -> 0.16666667 | AQ98: =R99/$W99 -> 0 | AR98: =S99/$W99 -> 0.16666667 | AS98: =T99/$W99 -> 0 | ... AU98: =V99/$W99 -> 0.16666667
B99: Jay Morefield | C99: 19592.159 | L99: Collin Mackness | M99: 1 | N99: 2 | Q99: 1 | S99: 1 | V99: 1 | W99: 6 | Y99: Corene Shirer | Z99: =Z62/SUM($Z62:$AI62) -> 0 | AA99: =AA62/SUM($Z62:$AI62) -> 0.13941479 | AB99: =AB62/SUM($Z62:$AI62) -> 0.11246876 | AC99: =AC62/SUM($Z62:$AI62) -> 0.096641806 | AD99: =AD62/SUM($Z62:$AI62) -> 0.16449416 | AE99: =AE62/SUM($Z62:$AI62) -> 0.097988564 | AF99: =AF62/SUM($Z62:$AI62) -> 0.21657124 | AG99: =AG62/SUM($Z62:$AI62) -> 0.028130326 | ... AI99: =AI62/SUM($Z62:$AI62) -> 0.11040437 | AK99: Corene Shirer | AL99: =M100/$W100 -> 0 | AM99: =N100/$W100 -> 0.13207547 | AN99: =O100/$W100 -> 0.13207547 | AO99: =P100/$W100 -> 0.13207547 | AP99: =Q100/$W100 -> 0.1509434 | AQ99: =R100/$W100 -> 0.094339623 | AR99: =S100/$W100 -> 0.16981132 | AS99: =T100/$W100 -> 0.018867925 | ... AU99: =V100/$W100 -> 0.13207547
B100: Jocelyn Laurentino | C100: 21934.839 | L100: Corene Shirer | N100: 7 | O100: 7 | P100: 7 | Q100: 8 | R100: 5 | S100: 9 | T100: 1 | U100: 2 | V100: 7 | W100: 53 | Y100: Crysta Halls | Z100: =Z63/SUM($Z63:$AI63) -> 0.037376307 | AA100: =AA63/SUM($Z63:$AI63) -> 0.23262604 | AB100: =AB63/SUM($Z63:$AI63) -> 0.13586498 | AC100: =AC63/SUM($Z63:$AI63) -> 0.12675415 | AD100: =AD63/SUM($Z63:$AI63) -> 0.098082258 | AE100: =AE63/SUM($Z63:$AI63) -> 0.066564182 | AF100: =AF63/SUM($Z63:$AI63) -> 0.10707131 | AG100: =AG63/SUM($Z63:$AI63) -> 0.014738956 | ... AI100: =AI63/SUM($Z63:$AI63) -> 0.12821094 | AK100: Crysta Halls | AL100: =M101/$W101 -> 0.042553191 | AM100: =N101/$W101 -> 0.19148936 | AN100: =O101/$W101 -> 0.17021277 | AO100: =P101/$W101 -> 0.085106383 | AP100: =Q101/$W101 -> 0.10638298 | AQ100: =R101/$W101 -> 0.10638298 | AR100: =S101/$W101 -> 0.085106383 | AS100: =T101/$W101 -> 0.021276596 | ... AU100: =V101/$W101 -> 0.14893617
B101: Joshua Prevost | C101: 15545.863 | L101: Crysta Halls | M101: 2 | N101: 9 | O101: 8 | P101: 4 | Q101: 5 | R101: 5 | S101: 4 | T101: 1 | U101: 2 | V101: 7 | W101: 47 | Y101: Genevra Charrisson | Z101: =Z64/SUM($Z64:$AI64) -> 0.017988986 | AA101: =AA64/SUM($Z64:$AI64) -> 0.17740713 | AB101: =AB64/SUM($Z64:$AI64) -> 0.054550929 | AC101: =AC64/SUM($Z64:$AI64) -> 0.023041792 | AD101: =AD64/SUM($Z64:$AI64) -> 0.1669225 | AE101: =AE64/SUM($Z64:$AI64) -> 0.14667969 | AF101: =AF64/SUM($Z64:$AI64) -> 0.14964025 | AG101: =AG64/SUM($Z64:$AI64) -> 0 | ... AI101: =AI64/SUM($Z64:$AI64) -> 0.12935873 | AK101: Genevra Charrisson | AL101: =M102/$W102 -> 0.027027027 | AM101: =N102/$W102 -> 0.13513514 | AN101: =O102/$W102 -> 0.054054054 | AO101: =P102/$W102 -> 0.027027027 | AP101: =Q102/$W102 -> 0.13513514 | AQ101: =R102/$W102 -> 0.13513514 | AR101: =S102/$W102 -> 0.21621622 | AS101: =T102/$W102 -> 0 | ... AU101: =V102/$W102 -> 0.10810811
B102: Madelon Bront | C102: 17026.67 | L102: Genevra Charrisson | M102: 1 | N102: 5 | O102: 2 | P102: 1 | Q102: 5 | R102: 5 | S102: 8 | U102: 6 | V102: 4 | W102: 37 | Y102: Hortense Gerring | Z102: =Z65/SUM($Z65:$AI65) -> 0.044793702 | AA102: =AA65/SUM($Z65:$AI65) -> 0.12285023 | AB102: =AB65/SUM($Z65:$AI65) -> 0.15309723 | AC102: =AC65/SUM($Z65:$AI65) -> 0.081118975 | AD102: =AD65/SUM($Z65:$AI65) -> 0.26767398 | AE102: =AE65/SUM($Z65:$AI65) -> 0.10259605 | AF102: =AF65/SUM($Z65:$AI65) -> 0.10481877 | AG102: =AG65/SUM($Z65:$AI65) -> 0.010253094 | ... AI102: =AI65/SUM($Z65:$AI65) -> 0.092091276 | AK102: Hortense Gerring | AL102: =M103/$W103 -> 0.038461538 | AM102: =N103/$W103 -> 0.076923077 | AN102: =O103/$W103 -> 0.15384615 | AO102: =P103/$W103 -> 0.096153846 | AP102: =Q103/$W103 -> 0.25 | AQ102: =R103/$W103 -> 0.11538462 | AR102: =S103/$W103 -> 0.13461538 | AS102: =T103/$W103 -> 0.019230769 | ... AU102: =V103/$W103 -> 0.096153846
B103: Maighdiln Upcraft | C103: 19774.34 | L103: Hortense Gerring | M103: 2 | N103: 4 | O103: 8 | P103: 5 | Q103: 13 | R103: 6 | S103: 7 | T103: 1 | U103: 1 | V103: 5 | W103: 52 | Y103: Jay Morefield | Z103: =Z66/SUM($Z66:$AI66) -> 0.091183751 | AA103: =AA66/SUM($Z66:$AI66) -> 0.22359216 | AB103: =AB66/SUM($Z66:$AI66) -> 0.16280283 | AC103: =AC66/SUM($Z66:$AI66) -> 0.15656481 | AD103: =AD66/SUM($Z66:$AI66) -> 0.11989269 | AE103: =AE66/SUM($Z66:$AI66) -> 0.056629111 | AF103: =AF66/SUM($Z66:$AI66) -> 0.074368802 | AG103: =AG66/SUM($Z66:$AI66) -> 0 | ... AI103: =AI66/SUM($Z66:$AI66) -> 0.047666302 | AK103: Jay Morefield | AL103: =M104/$W104 -> 0.076923077 | AM103: =N104/$W104 -> 0.15384615 | AN103: =O104/$W104 -> 0.15384615 | AO103: =P104/$W104 -> 0.15384615 | AP103: =Q104/$W104 -> 0.19230769 | AQ103: =R104/$W104 -> 0.038461538 | AR103: =S104/$W104 -> 0.11538462 | AS103: =T104/$W104 -> 0 | ... AU103: =V104/$W104 -> 0.076923077
B104: Manuel Goudie | C104: 15524.046 | L104: Jay Morefield | M104: 2 | N104: 4 | O104: 4 | P104: 4 | Q104: 5 | R104: 1 | S104: 3 | U104: 1 | V104: 2 | W104: 26 | Y104: Jocelyn Laurentino | Z104: =Z67/SUM($Z67:$AI67) -> 0.12439928 | AA104: =AA67/SUM($Z67:$AI67) -> 0.042123131 | AB104: =AB67/SUM($Z67:$AI67) -> 0.12969142 | AC104: =AC67/SUM($Z67:$AI67) -> 0.15498402 | AD104: =AD67/SUM($Z67:$AI67) -> 0.1177031 | AE104: =AE67/SUM($Z67:$AI67) -> 0.068534021 | AF104: =AF67/SUM($Z67:$AI67) -> 0.12237805 | AG104: =AG67/SUM($Z67:$AI67) -> 0 | ... AI104: =AI67/SUM($Z67:$AI67) -> 0.11067916 | AK104: Jocelyn Laurentino | AL104: =M105/$W105 -> 0.090909091 | AM104: =N105/$W105 -> 0.090909091 | AN104: =O105/$W105 -> 0.13636364 | AO104: =P105/$W105 -> 0.13636364 | AP104: =Q105/$W105 -> 0.13636364 | AQ104: =R105/$W105 -> 0.090909091 | AR104: =S105/$W105 -> 0.13636364 | AS104: =T105/$W105 -> 0 | ... AU104: =V105/$W105 -> 0.090909091
B105: Mellicent Mattys | C105: 21113.244 | L105: Jocelyn Laurentino | M105: 2 | N105: 2 | O105: 3 | P105: 3 | Q105: 3 | R105: 2 | S105: 3 | U105: 2 | V105: 2 | W105: 22 | Y105: Joshua Prevost | Z105: =Z68/SUM($Z68:$AI68) -> 0 | AA105: =AA68/SUM($Z68:$AI68) -> 0.043675285 | AB105: =AB68/SUM($Z68:$AI68) -> 0 | AC105: =AC68/SUM($Z68:$AI68) -> 0.2456916 | AD105: =AD68/SUM($Z68:$AI68) -> 0.10389439 | AE105: =AE68/SUM($Z68:$AI68) -> 0 | AF105: =AF68/SUM($Z68:$AI68) -> 0.32186222 | AG105: =AG68/SUM($Z68:$AI68) -> 0.14136603 | ... AI105: =AI68/SUM($Z68:$AI68) -> 0.14351046 | AK105: Joshua Prevost | AL105: =M106/$W106 -> 0 | AM105: =N106/$W106 -> 0.1 | AN105: =O106/$W106 -> 0 | AO105: =P106/$W106 -> 0.3 | AP105: =Q106/$W106 -> 0.1 | AQ105: =R106/$W106 -> 0 | AR105: =S106/$W106 -> 0.3 | AS105: =T106/$W106 -> 0.1 | ... AU105: =V106/$W106 -> 0.1
B106: Nero Harbisher | C106: 18770.217 | L106: Joshua Prevost | N106: 1 | P106: 3 | Q106: 1 | S106: 3 | T106: 1 | V106: 1 | W106: 10 | Y106: Madelon Bront | Z106: =Z69/SUM($Z69:$AI69) -> 0.034051783 | AA106: =AA69/SUM($Z69:$AI69) -> 0.17496313 | AB106: =AB69/SUM($Z69:$AI69) -> 0.074412401 | AC106: =AC69/SUM($Z69:$AI69) -> 0.1504454 | AD106: =AD69/SUM($Z69:$AI69) -> 0.12033646 | AE106: =AE69/SUM($Z69:$AI69) -> 0.19283669 | AF106: =AF69/SUM($Z69:$AI69) -> 0.083380745 | AG106: =AG69/SUM($Z69:$AI69) -> 0.03117268 | ... AI106: =AI69/SUM($Z69:$AI69) -> 0.030371508 | AK106: Madelon Bront | AL106: =M107/$W107 -> 0.025641026 | AM106: =N107/$W107 -> 0.20512821 | AN106: =O107/$W107 -> 0.1025641 | AO106: =P107/$W107 -> 0.15384615 | AP106: =Q107/$W107 -> 0.12820513 | AQ106: =R107/$W107 -> 0.15384615 | AR106: =S107/$W107 -> 0.076923077 | AS106: =T107/$W107 -> 0.025641026 | ... AU106: =V107/$W107 -> 0.025641026
B107: Ora Grennan | C107: 17650.505 | L107: Madelon Bront | M107: 1 | N107: 8 | O107: 4 | P107: 6 | Q107: 5 | R107: 6 | S107: 3 | T107: 1 | U107: 4 | V107: 1 | W107: 39 | Y107: Maighdiln Upcraft | Z107: =Z70/SUM($Z70:$AI70) -> 0.076924312 | AA107: =AA70/SUM($Z70:$AI70) -> 0.10210341 | AB107: =AB70/SUM($Z70:$AI70) -> 0.2712628 | AC107: =AC70/SUM($Z70:$AI70) -> 0.20704451 | AD107: =AD70/SUM($Z70:$AI70) -> 0.097039143 | AE107: =AE70/SUM($Z70:$AI70) -> 0.12464929 | AF107: =AF70/SUM($Z70:$AI70) -> 0.036516923 | AG107: =AG70/SUM($Z70:$AI70) -> 0.029852801 | ... AI107: =AI70/SUM($Z70:$AI70) -> 0.017036051 | AK107: Maighdiln Upcraft | AL107: =M108/$W108 -> 0.055555556 | AM107: =N108/$W108 -> 0.11111111 | AN107: =O108/$W108 -> 0.27777778 | AO107: =P108/$W108 -> 0.13888889 | AP107: =Q108/$W108 -> 0.083333333 | AQ107: =R108/$W108 -> 0.13888889 | AR107: =S108/$W108 -> 0.055555556 | AS107: =T108/$W108 -> 0.055555556 | ... AU107: =V108/$W108 -> 0.055555556
B108: Palm Wetherald | C108: 17856.662 | L108: Maighdiln Upcraft | M108: 2 | N108: 4 | O108: 10 | P108: 5 | Q108: 3 | R108: 5 | S108: 2 | T108: 2 | U108: 1 | V108: 2 | W108: 36 | Y108: Manuel Goudie | Z108: =Z71/SUM($Z71:$AI71) -> 0 | AA108: =AA71/SUM($Z71:$AI71) -> 0 | AB108: =AB71/SUM($Z71:$AI71) -> 0.15390524 | AC108: =AC71/SUM($Z71:$AI71) -> 0 | AD108: =AD71/SUM($Z71:$AI71) -> 0 | AE108: =AE71/SUM($Z71:$AI71) -> 0.23856152 | AF108: =AF71/SUM($Z71:$AI71) -> 0.23233634 | AG108: =AG71/SUM($Z71:$AI71) -> 0.3751969 | ... AI108: =AI71/SUM($Z71:$AI71) -> 0 | AK108: Manuel Goudie | AL108: =M109/$W109 -> 0 | AM108: =N109/$W109 -> 0 | AN108: =O109/$W109 -> 0.2 | AO108: =P109/$W109 -> 0 | AP108: =Q109/$W109 -> 0 | AQ108: =R109/$W109 -> 0.4 | AR108: =S109/$W109 -> 0.2 | AS108: =T109/$W109 -> 0.2 | ... AU108: =V109/$W109 -> 0
B109: Perri Aldersley | C109: 13659.872 | L109: Manuel Goudie | O109: 1 | R109: 2 | S109: 1 | T109: 1 | W109: 5 | Y109: Mellicent Mattys | Z109: =Z72/SUM($Z72:$AI72) -> 0.022962162 | AA109: =AA72/SUM($Z72:$AI72) -> 0.25163801 | AB109: =AB72/SUM($Z72:$AI72) -> 0.15125331 | AC109: =AC72/SUM($Z72:$AI72) -> 0.050057296 | AD109: =AD72/SUM($Z72:$AI72) -> 0.10656572 | AE109: =AE72/SUM($Z72:$AI72) -> 0.11885016 | AF109: =AF72/SUM($Z72:$AI72) -> 0.22030318 | AG109: =AG72/SUM($Z72:$AI72) -> 0 | ... AI109: =AI72/SUM($Z72:$AI72) -> 0 | AK109: Mellicent Mattys | AL109: =M110/$W110 -> 0.047619048 | AM109: =N110/$W110 -> 0.19047619 | AN109: =O110/$W110 -> 0.14285714 | AO109: =P110/$W110 -> 0.047619048 | AP109: =Q110/$W110 -> 0.14285714 | AQ109: =R110/$W110 -> 0.14285714 | AR109: =S110/$W110 -> 0.23809524 | AS109: =T110/$W110 -> 0 | ... AU109: =V110/$W110 -> 0
B110: Shermy McGready | C110: 18130.591 | L110: Mellicent Mattys | M110: 1 | N110: 4 | O110: 3 | P110: 1 | Q110: 3 | R110: 3 | S110: 5 | U110: 1 | W110: 21 | Y110: Nero Harbisher | Z110: =Z73/SUM($Z73:$AI73) -> 0 | AA110: =AA73/SUM($Z73:$AI73) -> 0.050807292 | AB110: =AB73/SUM($Z73:$AI73) -> 0.065775343 | AC110: =AC73/SUM($Z73:$AI73) -> 0.1918628 | AD110: =AD73/SUM($Z73:$AI73) -> 0.24264309 | AE110: =AE73/SUM($Z73:$AI73) -> 0.13184818 | AF110: =AF73/SUM($Z73:$AI73) -> 0.11031195 | AG110: =AG73/SUM($Z73:$AI73) -> 0 | ... AI110: =AI73/SUM($Z73:$AI73) -> 0.11719639 | AK110: Nero Harbisher | AL110: =M111/$W111 -> 0 | AM110: =N111/$W111 -> 0.071428571 | AN110: =O111/$W111 -> 0.035714286 | AO110: =P111/$W111 -> 0.14285714 | AP110: =Q111/$W111 -> 0.21428571 | AQ110: =R111/$W111 -> 0.14285714 | AR110: =S111/$W111 -> 0.14285714 | AS110: =T111/$W111 -> 0 | ... AU110: =V111/$W111 -> 0.17857143
B111: Smitty Culverhouse | C111: 17349.188 | L111: Nero Harbisher | N111: 2 | O111: 1 | P111: 4 | Q111: 6 | R111: 4 | S111: 4 | U111: 2 | V111: 5 | W111: 28 | Y111: Ora Grennan | Z111: =Z74/SUM($Z74:$AI74) -> 0.012151177 | AA111: =AA74/SUM($Z74:$AI74) -> 0.12998631 | AB111: =AB74/SUM($Z74:$AI74) -> 0.16932896 | AC111: =AC74/SUM($Z74:$AI74) -> 0.17315072 | AD111: =AD74/SUM($Z74:$AI74) -> 0.10906473 | AE111: =AE74/SUM($Z74:$AI74) -> 0.19861314 | AF111: =AF74/SUM($Z74:$AI74) -> 0.053350701 | AG111: =AG74/SUM($Z74:$AI74) -> 0.024283748 | ... AI111: =AI74/SUM($Z74:$AI74) -> 0.1300705 | AK111: Ora Grennan | AL111: =M112/$W112 -> 0.02 | AM111: =N112/$W112 -> 0.16 | AN111: =O112/$W112 -> 0.16 | AO111: =P112/$W112 -> 0.18 | AP111: =Q112/$W112 -> 0.14 | AQ111: =R112/$W112 -> 0.14 | AR111: =S112/$W112 -> 0.08 | AS111: =T112/$W112 -> 0.02 | ... AU111: =V112/$W112 -> 0.1
B112: Tarrah Castelletti | C112: 20780.183 | L112: Ora Grennan | M112: 1 | N112: 8 | O112: 8 | P112: 9 | Q112: 7 | R112: 7 | S112: 4 | T112: 1 | V112: 5 | W112: 50 | Y112: Palm Wetherald | Z112: =Z75/SUM($Z75:$AI75) -> 0.12758787 | AA112: =AA75/SUM($Z75:$AI75) -> 0.092437377 | AB112: =AB75/SUM($Z75:$AI75) -> 0.18256363 | AC112: =AC75/SUM($Z75:$AI75) -> 0.034832182 | AD112: =AD75/SUM($Z75:$AI75) -> 0.104822 | AE112: =AE75/SUM($Z75:$AI75) -> 0.14082708 | AF112: =AF75/SUM($Z75:$AI75) -> 0.12375132 | AG112: =AG75/SUM($Z75:$AI75) -> 0.037372746 | ... AI112: =AI75/SUM($Z75:$AI75) -> 0.1558058 | AK112: Palm Wetherald | AL112: =M113/$W113 -> 0.05 | AM112: =N113/$W113 -> 0.1 | AN112: =O113/$W113 -> 0.1 | AO112: =P113/$W113 -> 0.05 | AP112: =Q113/$W113 -> 0.1 | AQ112: =R113/$W113 -> 0.2 | AR112: =S113/$W113 -> 0.15 | AS112: =T113/$W113 -> 0.05 | ... AU112: =V113/$W113 -> 0.2
B113: Wat Bowkley | C113: 19822.041 | L113: Palm Wetherald | M113: 1 | N113: 2 | O113: 2 | P113: 1 | Q113: 2 | R113: 4 | S113: 3 | T113: 1 | V113: 4 | W113: 20 | Y113: Perri Aldersley | Z113: =Z76/SUM($Z76:$AI76) -> 0 | AA113: =AA76/SUM($Z76:$AI76) -> 0 | AB113: =AB76/SUM($Z76:$AI76) -> 0.17979958 | AC113: =AC76/SUM($Z76:$AI76) -> 0.040708777 | AD113: =AD76/SUM($Z76:$AI76) -> 0.29252233 | AE113: =AE76/SUM($Z76:$AI76) -> 0.10060087 | AF113: =AF76/SUM($Z76:$AI76) -> 0.18901959 | AG113: =AG76/SUM($Z76:$AI76) -> 0.034947132 | ... AI113: =AI76/SUM($Z76:$AI76) -> 0.16240172 | AK113: Perri Aldersley | AL113: =M114/$W114 -> 0 | AM113: =N114/$W114 -> 0 | AN113: =O114/$W114 -> 0.16666667 | AO113: =P114/$W114 -> 0.083333333 | AP113: =Q114/$W114 -> 0.33333333 | AQ113: =R114/$W114 -> 0.083333333 | AR113: =S114/$W114 -> 0.083333333 | AS113: =T114/$W114 -> 0.083333333 | ... AU113: =V114/$W114 -> 0.16666667
B114: Winny Agnolo | C114: 21608.279 | L114: Perri Aldersley | O114: 2 | P114: 1 | Q114: 4 | R114: 1 | S114: 1 | T114: 1 | V114: 2 | W114: 12 | Y114: Shermy McGready | Z114: =Z77/SUM($Z77:$AI77) -> 0 | AA114: =AA77/SUM($Z77:$AI77) -> 0.11469529 | AB114: =AB77/SUM($Z77:$AI77) -> 0 | AC114: =AC77/SUM($Z77:$AI77) -> 0.14608408 | AD114: =AD77/SUM($Z77:$AI77) -> 0.26831058 | AE114: =AE77/SUM($Z77:$AI77) -> 0.19251875 | AF114: =AF77/SUM($Z77:$AI77) -> 0.028239271 | AG114: =AG77/SUM($Z77:$AI77) -> 0 | ... AI114: =AI77/SUM($Z77:$AI77) -> 0.12916836 | AK114: Shermy McGready | AL114: =M115/$W115 -> 0 | AM114: =N115/$W115 -> 0.13333333 | AN114: =O115/$W115 -> 0 | AO114: =P115/$W115 -> 0.13333333 | AP114: =Q115/$W115 -> 0.2 | AQ114: =R115/$W115 -> 0.2 | AR114: =S115/$W115 -> 0.066666667 | AS114: =T115/$W115 -> 0 | ... AU114: =V115/$W115 -> 0.13333333
B115: Grand Total | C115: 18992.428 | L115: Shermy McGready | N115: 2 | P115: 2 | Q115: 3 | R115: 3 | S115: 1 | U115: 2 | V115: 2 | W115: 15 | Y115: Smitty Culverhouse | Z115: =Z78/SUM($Z78:$AI78) -> 0.062712783 | AA115: =AA78/SUM($Z78:$AI78) -> 0.14403364 | AB115: =AB78/SUM($Z78:$AI78) -> 0.095396115 | AC115: =AC78/SUM($Z78:$AI78) -> 0.033307892 | AD115: =AD78/SUM($Z78:$AI78) -> 0.13168038 | AE115: =AE78/SUM($Z78:$AI78) -> 0.064818948 | AF115: =AF78/SUM($Z78:$AI78) -> 0.25835215 | AG115: =AG78/SUM($Z78:$AI78) -> 0.0088310031 | ... AI115: =AI78/SUM($Z78:$AI78) -> 0.095155168 | AK115: Smitty Culverhouse | AL115: =M116/$W116 -> 0.048780488 | AM115: =N116/$W116 -> 0.17073171 | AN115: =O116/$W116 -> 0.073170732 | AO115: =P116/$W116 -> 0.073170732 | AP115: =Q116/$W116 -> 0.097560976 | AQ115: =R116/$W116 -> 0.097560976 | AR115: =S116/$W116 -> 0.24390244 | AS115: =T116/$W116 -> 0.024390244 | ... AU115: =V116/$W116 -> 0.073170732
...

Sheet Sales Rep Analysis

Sheet AI Dash
B1: Do More Sales Mean More Profit? | Sales Dashboard 2019–2020
B2: Combines the MOMP Tables and MOMP analysis to test whether a higher number of orders drives higher profit. All figures link live to 'MOMP Tables' (orders placed Jan 2019 – Dec 2020, GBP).
B4: Total Orders | D4: Total Revenue | F4: Total Profit | H4: Avg Profit Margin | J4: Orders ↔ Profit (r) | L4: Order Value ↔ Profit/Sale (r) | N4: VERDICT
B5: ='MOMP Tables'!K17 -> 1000 | D5: ='MOMP Tables'!L17 -> 1.1336174e+08 | F5: ='MOMP Tables'!N17 -> 18992428 | H5: ='MOMP Tables'!S51 -> 0.16753825 | J5: =CORREL(E61:E84,G61:G84) -> 0.37141855 | L5: =CORREL(I61:I84,J61:J84) -> 0.9957895 | N5: =IF(J5<L5,"Not on its own – profit follows ORDER VALUE, not order COUNT","Yes – order volume is the main profit driver") -> Not on its own – profit follows ORDER VALUE, not order COUNT
B6: ="2019: "&TEXT('MOMP Tables'!C17,"#,##0")&" | 2020: "&TEXT('MOMP Tables'!G17,"#,##0") -> 2019: 490 | 2020: 510 | D6: ="2019: "&TEXT('MOMP Tables'!D17/1000000,"£0.00")&"m | 2020: "&TEXT('MOMP Tables'!H17/1000000,"£0.00")&"m" -> 2019: £56.62m | 2020: £56.74m | F6: ="2019: "&TEXT('MOMP Tables'!F17/1000000,"£0.00")&"m | 2020: "&TEXT('MOMP Tables'!J17/1000000,"£0.00")&"m" -> 2019: £9.49m | 2020: £9.51m | H6: ="2019: "&TEXT('MOMP Tables'!Q51,"0.0%")&" | 2020: "&TEXT('MOMP Tables'!R51,"0.0%") -> 2019: 16.8% | 2020: 16.8% | J6: ="Monthly, 24 mths | 2019: "&TEXT('MOMP Tables'!Q4,"0.00")&" 2020: "&TEXT('MOMP Tables'!R4,"0.00") -> Monthly, 24 mths | 2019: 0.45 2020: 0.37 | L6: ="Monthly, 24 mths | 2019: "&TEXT('MOMP Tables'!Q10,"0.00")&" 2020: "&TEXT('MOMP Tables'!R10,"0.00") -> Monthly, 24 mths | 2019: 1.00 2020: 0.99
B8: 2019 vs 2020 – Year-on-Year Comparison | I8: Key Findings
B9: Metric | D9: 2019 | E9: 2020 | F9: Change | G9: Change % | I9: What the data says about orders vs profit
B10: Orders | D10: ='MOMP Tables'!C17 -> 490 | E10: ='MOMP Tables'!G17 -> 510 | F10: =E10-D10 -> 20 | G10: =IF(D10=0,"",E10/D10-1) -> 0.040816327 | I10: ="① Volume up, profit flat: 2020 had "&TEXT('MOMP Tables'!G17-'MOMP Tables'!C17,"#,##0")&" more orders ("&TEXT('MOMP Tables'!G17/'MOMP Tables'!C17-1,"+0.0%")&") yet profit grew just "&TEXT('MOMP Tables'!J17/'MOMP Tables'!F17-1,"+0.0%")&" – revenue per order fell." -> ① Volume up, profit flat: 2020 had 20 more orders (+4.1%) yet profit grew just +0.2% – revenue per order fell.
B11: Revenue (£) | D11: ='MOMP Tables'!D17 -> 56617524 | E11: ='MOMP Tables'!H17 -> 56744214 | F11: =E11-D11 -> 126689.91 | G11: =IF(D11=0,"",E11/D11-1) -> 0.0022376448
B12: Profit (£) | D12: ='MOMP Tables'!F17 -> 9487277.9 | E12: ='MOMP Tables'!J17 -> 9505149.8 | F12: =E12-D12 -> 17871.94 | G12: =IF(D12=0,"",E12/D12-1) -> 0.0018837795 | I12: ="② Margin is constant: profit margin sits at ~"&TEXT('MOMP Tables'!S51,"0.0%")&" in every month of both years, so profit simply scales with the value of what is sold." -> ② Margin is constant: profit margin sits at ~16.8% in every month of both years, so profit simply scales with the value of what is sold.
B13: Profit Margin | D13: ='MOMP Tables'!Q51 -> 0.16756787 | E13: ='MOMP Tables'!R51 -> 0.1675087 | F13: =E13-D13 -> -5.9164062e-05
B14: Avg Order Value (£) | D14: ='MOMP Tables'!M33 -> 115545.97 | E14: ='MOMP Tables'!N33 -> 111263.17 | F14: =E14-D14 -> -4282.8028 | G14: =IF(D14=0,"",E14/D14-1) -> -0.037065792 | I14: ="③ Weak volume link: monthly orders vs profit correlation is only "&TEXT(J5,"0.00")&" (24 months), versus "&TEXT(L5,"0.00")&" for average order value vs profit per sale." -> ③ Weak volume link: monthly orders vs profit correlation is only 0.37 (24 months), versus 1.00 for average order value vs profit per sale.
B15: Avg Profit / Sale (£) | D15: ='MOMP Tables'!C50 -> 19361.792 | E15: ='MOMP Tables'!D50 -> 18637.549 | F15: =E15-D15 -> -724.24293 | G15: =IF(D15=0,"",E15/D15-1) -> -0.03740578
B16: Avg Monthly Profit (£) | D16: ='MOMP Tables'!Q11 -> 790606.49 | E16: ='MOMP Tables'!R11 -> 792095.82 | F16: =E16-D16 -> 1489.3283 | G16: =IF(D16=0,"",E16/D16-1) -> 0.0018837795 | I16: ="④ Peak months are high-value months: Dec ("&TEXT('MOMP Tables'!AD32,"0")&" orders) and Jun ("&TEXT('MOMP Tables'!AD26,"0")&") out-earn Jan ("&TEXT('MOMP Tables'!AD21,"0")&" orders) because Dec AOV is "&TEXT('MOMP Tables'!O32,"£#,##0")&" vs "&TEXT('MOMP Tables'!O33,"£#,##0")&" average." -> ④ Peak months are high-value months: Dec (77 orders) and Jun (90) out-earn Jan (95 orders) because Dec AOV is £189,585 vs £113,362 average.
B17: Std Dev of Monthly Orders | D17: ='MOMP Tables'!Q6 -> 5.2413951 | E17: ='MOMP Tables'!R6 -> 8.2815055 | F17: =E17-D17 -> 3.0401104
B18: Corr: Orders ↔ Profit | D18: ='MOMP Tables'!Q4 -> 0.45204688 | E18: ='MOMP Tables'!R4 -> 0.37399861 | F18: =E18-D18 -> -0.078048272 | I18: ="⑤ Categories agree: "&INDEX(M61:M70,MATCH(MAX(N61:N70),N61:N70,0))&" has the most sales ("&MAX(N61:N70)&") but "&INDEX(M61:M70,MATCH(MAX(P61:P70),P61:P70,0))&" ("&INDEX(N61:N70,MATCH(MAX(P61:P70),P61:P70,0))&" sales) earns the most per sale ("&TEXT(MAX(P61:P70),"£#,##0")&")." -> ⑤ Categories agree: Clothing has the most sales (155) but Accessories (35 sales) earns the most per sale (£22,397).
B19: Corr: Order Value ↔ Profit/Sale | D19: ='MOMP Tables'!Q10 -> 0.99727848 | E19: ='MOMP Tables'!R10 -> 0.99455161 | F19: =E19-D19 -> -0.0027268678
B20: Source: 'MOMP Tables' pivot tables & supporting statistics. Change % omitted for ratios/correlations. | I20: ="CONCLUSION: More sales do not reliably mean more profit – bigger orders do. Growth should prioritise order value (upselling, bundles, premium mix) over raw order count." -> CONCLUSION: More sales do not reliably mean more profit – bigger orders do. Growth should prioritise order value (upselling, bundles, premium mix) over raw order count.
B22: Visual Evidence
B58: Monthly Detail (chart data) – linked to 'MOMP Tables' | M58: Category View – volume vs profitability
B60: Period | C60: Year | D60: Month | E60: Orders | F60: Revenue (£) | G60: Profit (£) | H60: Profit Margin | I60: Avg Order Value (£) | J60: Avg Profit / Sale (£) | K60: Profit Rating | M60: Category | N60: No. of Sales | O60: Avg Order Value (£) | P60: Avg Profit / Sale (£) | Q60: Total Profit (£)
B61: =D61&" "&RIGHT(C61,2) -> Jan 19 | C61: ='MOMP Tables'!$C$3 -> 2019 | D61: ='MOMP Tables'!B5 -> Jan | E61: ='MOMP Tables'!C5 -> 44 | F61: ='MOMP Tables'!D5 -> 4516614.8 | G61: ='MOMP Tables'!F5 -> 724231.31 | H61: ='MOMP Tables'!Q39 -> 0.16034826 | I61: ='MOMP Tables'!M21 -> 102650.34 | J61: ='MOMP Tables'!C38 -> 16459.803 | K61: ='MOMP Tables'!W3 -> Average | M61: ='MOMP Tables'!AE5 -> Accessories | N61: ='MOMP Tables'!AN5 -> 35 | O61: ='MOMP Tables'!AP5 -> 134398.02 | P61: ='MOMP Tables'!AQ5 -> 22397.038 | Q61: =N61*P61 -> 783896.33
B62: =D62&" "&RIGHT(C62,2) -> Feb 19 | C62: ='MOMP Tables'!$C$3 -> 2019 | D62: ='MOMP Tables'!B6 -> Feb | E62: ='MOMP Tables'!C6 -> 44 | F62: ='MOMP Tables'!D6 -> 2895563.9 | G62: ='MOMP Tables'!F6 -> 493204.9 | H62: ='MOMP Tables'!Q40 -> 0.17033121 | I62: ='MOMP Tables'!M22 -> 65808.27 | J62: ='MOMP Tables'!C39 -> 11209.202 | K62: ='MOMP Tables'!W4 -> Average | M62: ='MOMP Tables'!AE6 -> Appliances | N62: ='MOMP Tables'!AN6 -> 131 | O62: ='MOMP Tables'!AP6 -> 115569.99 | P62: ='MOMP Tables'!AQ6 -> 19350.224 | Q62: =N62*P62 -> 2534879.3
B63: =D63&" "&RIGHT(C63,2) -> Mar 19 | C63: ='MOMP Tables'!$C$3 -> 2019 | D63: ='MOMP Tables'!B7 -> Mar | E63: ='MOMP Tables'!C7 -> 41 | F63: ='MOMP Tables'!D7 -> 2521828 | G63: ='MOMP Tables'!F7 -> 429420.62 | H63: ='MOMP Tables'!Q41 -> 0.17028149 | I63: ='MOMP Tables'!M23 -> 61508 | J63: ='MOMP Tables'!C40 -> 10473.674 | K63: ='MOMP Tables'!W5 -> Below Average | M63: ='MOMP Tables'!AE7 -> Beauty | N63: ='MOMP Tables'!AN7 -> 115 | O63: ='MOMP Tables'!AP7 -> 109296.21 | P63: ='MOMP Tables'!AQ7 -> 18421.108 | Q63: =N63*P63 -> 2118427.4
B64: =D64&" "&RIGHT(C64,2) -> Apr 19 | C64: ='MOMP Tables'!$C$3 -> 2019 | D64: ='MOMP Tables'!B8 -> Apr | E64: ='MOMP Tables'!C8 -> 36 | F64: ='MOMP Tables'!D8 -> 4172236.8 | G64: ='MOMP Tables'!F8 -> 692753.62 | H64: ='MOMP Tables'!Q42 -> 0.1660389 | I64: ='MOMP Tables'!M24 -> 115895.47 | J64: ='MOMP Tables'!C41 -> 19243.156 | K64: ='MOMP Tables'!W6 -> Average | M64: ='MOMP Tables'!AE8 -> Books | N64: ='MOMP Tables'!AN8 -> 117 | O64: ='MOMP Tables'!AP8 -> 112649.39 | P64: ='MOMP Tables'!AQ8 -> 19024.905 | Q64: =N64*P64 -> 2225913.9
B65: =D65&" "&RIGHT(C65,2) -> May 19 | C65: ='MOMP Tables'!$C$3 -> 2019 | D65: ='MOMP Tables'!B9 -> May | E65: ='MOMP Tables'!C9 -> 38 | F65: ='MOMP Tables'!D9 -> 3825682 | G65: ='MOMP Tables'!F9 -> 648258.3 | H65: ='MOMP Tables'!Q43 -> 0.16944908 | I65: ='MOMP Tables'!M25 -> 100675.84 | J65: ='MOMP Tables'!C42 -> 17059.429 | K65: ='MOMP Tables'!W7 -> Average | M65: ='MOMP Tables'!AE9 -> Clothing | N65: ='MOMP Tables'!AN9 -> 155 | O65: ='MOMP Tables'!AP9 -> 113946.34 | P65: ='MOMP Tables'!AQ9 -> 18980.246 | Q65: =N65*P65 -> 2941938.1
B66: =D66&" "&RIGHT(C66,2) -> Jun 19 | C66: ='MOMP Tables'!$C$3 -> 2019 | D66: ='MOMP Tables'!B10 -> Jun | E66: ='MOMP Tables'!C10 -> 47 | F66: ='MOMP Tables'!D10 -> 7692234.9 | G66: ='MOMP Tables'!F10 -> 1305278.4 | H66: ='MOMP Tables'!Q44 -> 0.16968779 | I66: ='MOMP Tables'!M26 -> 163664.57 | J66: ='MOMP Tables'!C43 -> 27771.88 | K66: ='MOMP Tables'!W8 -> Above Average | M66: ='MOMP Tables'!AE10 -> Electronics | N66: ='MOMP Tables'!AN10 -> 134 | O66: ='MOMP Tables'!AP10 -> 108075.21 | P66: ='MOMP Tables'!AQ10 -> 17918.903 | Q66: =N66*P66 -> 2401133
B67: =D67&" "&RIGHT(C67,2) -> Jul 19 | C67: ='MOMP Tables'!$C$3 -> 2019 | D67: ='MOMP Tables'!B11 -> Jul | E67: ='MOMP Tables'!C11 -> 40 | F67: ='MOMP Tables'!D11 -> 6638609.2 | G67: ='MOMP Tables'!F11 -> 1084227.4 | H67: ='MOMP Tables'!Q45 -> 0.16332147 | I67: ='MOMP Tables'!M27 -> 165965.23 | J67: ='MOMP Tables'!C44 -> 27105.685 | K67: ='MOMP Tables'!W9 -> Average | M67: ='MOMP Tables'!AE11 -> Games | N67: ='MOMP Tables'!AN11 -> 139 | O67: ='MOMP Tables'!AP11 -> 110227.51 | P67: ='MOMP Tables'!AQ11 -> 18415.797 | Q67: =N67*P67 -> 2559795.8
B68: =D68&" "&RIGHT(C68,2) -> Aug 19 | C68: ='MOMP Tables'!$C$3 -> 2019 | D68: ='MOMP Tables'!B12 -> Aug | E68: ='MOMP Tables'!C12 -> 31 | F68: ='MOMP Tables'!D12 -> 3437450.1 | G68: ='MOMP Tables'!F12 -> 580316.12 | H68: ='MOMP Tables'!Q46 -> 0.16882168 | I68: ='MOMP Tables'!M28 -> 110885.49 | J68: ='MOMP Tables'!C45 -> 18719.875 | K68: ='MOMP Tables'!W10 -> Average | M68: ='MOMP Tables'!AE12 -> Other | N68: ='MOMP Tables'!AN12 -> 29 | O68: ='MOMP Tables'!AP12 -> 112516.66 | P68: ='MOMP Tables'!AQ12 -> 18932.197 | Q68: =N68*P68 -> 549033.71
B69: =D69&" "&RIGHT(C69,2) -> Sep 19 | C69: ='MOMP Tables'!$C$3 -> 2019 | D69: ='MOMP Tables'!B13 -> Sep | E69: ='MOMP Tables'!C13 -> 49 | F69: ='MOMP Tables'!D13 -> 4870060.5 | G69: ='MOMP Tables'!F13 -> 788191.58 | H69: ='MOMP Tables'!Q47 -> 0.16184431 | I69: ='MOMP Tables'!M29 -> 99388.991 | J69: ='MOMP Tables'!C46 -> 16085.542 | K69: ='MOMP Tables'!W11 -> Average | M69: ='MOMP Tables'!AE13 -> Outdoors | N69: ='MOMP Tables'!AN13 -> 50 | O69: ='MOMP Tables'!AP13 -> 118781.51 | P69: ='MOMP Tables'!AQ13 -> 21135.25 | Q69: =N69*P69 -> 1056762.5
B70: =D70&" "&RIGHT(C70,2) -> Oct 19 | C70: ='MOMP Tables'!$C$3 -> 2019 | D70: ='MOMP Tables'!B14 -> Oct | E70: ='MOMP Tables'!C14 -> 43 | F70: ='MOMP Tables'!D14 -> 4372149.5 | G70: ='MOMP Tables'!F14 -> 744434.48 | H70: ='MOMP Tables'!Q48 -> 0.17026739 | I70: ='MOMP Tables'!M30 -> 101677.9 | J70: ='MOMP Tables'!C47 -> 17312.43 | K70: ='MOMP Tables'!W12 -> Average | M70: ='MOMP Tables'!AE14 -> Smartphones | N70: ='MOMP Tables'!AN14 -> 95 | O70: ='MOMP Tables'!AP14 -> 116859.52 | P70: ='MOMP Tables'!AQ14 -> 19164.712 | Q70: =N70*P70 -> 1820647.7
B71: =D71&" "&RIGHT(C71,2) -> Nov 19 | C71: ='MOMP Tables'!$C$3 -> 2019 | D71: ='MOMP Tables'!B15 -> Nov | E71: ='MOMP Tables'!C15 -> 33 | F71: ='MOMP Tables'!D15 -> 2961318.6 | G71: ='MOMP Tables'!F15 -> 482287.62 | H71: ='MOMP Tables'!Q49 -> 0.16286246 | I71: ='MOMP Tables'!M31 -> 89736.926 | J71: ='MOMP Tables'!C48 -> 14614.776 | K71: ='MOMP Tables'!W13 -> Average | M71: Total | N71: =SUM(N61:N70) -> 1000 | O71: ='MOMP Tables'!AP15 -> 113361.74 | P71: ='MOMP Tables'!AQ15 -> 18992.428 | Q71: =SUM(Q61:Q70) -> 18992428
B72: =D72&" "&RIGHT(C72,2) -> Dec 19 | C72: ='MOMP Tables'!$C$3 -> 2019 | D72: ='MOMP Tables'!B16 -> Dec | E72: ='MOMP Tables'!C16 -> 44 | F72: ='MOMP Tables'!D16 -> 8713776 | G72: ='MOMP Tables'!F16 -> 1514673.6 | H72: ='MOMP Tables'!Q50 -> 0.17382517 | I72: ='MOMP Tables'!M32 -> 198040.36 | J72: ='MOMP Tables'!C49 -> 34424.399 | K72: ='MOMP Tables'!W14 -> Above Average
B73: =D73&" "&RIGHT(C73,2) -> Jan 20 | C73: ='MOMP Tables'!$G$3 -> 2020 | D73: ='MOMP Tables'!B5 -> Jan | E73: ='MOMP Tables'!G5 -> 51 | F73: ='MOMP Tables'!H5 -> 5215699.8 | G73: ='MOMP Tables'!J5 -> 924639.02 | H73: ='MOMP Tables'!R39 -> 0.17727995 | I73: ='MOMP Tables'!N21 -> 102268.62 | J73: ='MOMP Tables'!D38 -> 18130.177 | K73: ='MOMP Tables'!X3 -> Average | M73: ="Correlation – category sales count vs avg profit/sale: "&TEXT(CORREL(N61:N70,P61:P70),"0.00") -> Correlation – category sales count vs avg profit/sale: -0.68
B74: =D74&" "&RIGHT(C74,2) -> Feb 20 | C74: ='MOMP Tables'!$G$3 -> 2020 | D74: ='MOMP Tables'!B6 -> Feb | E74: ='MOMP Tables'!G6 -> 28 | F74: ='MOMP Tables'!H6 -> 1959413 | G74: ='MOMP Tables'!J6 -> 315750.51 | H74: ='MOMP Tables'!R40 -> 0.16114546 | I74: ='MOMP Tables'!N22 -> 69979.036 | J74: ='MOMP Tables'!D39 -> 11276.804 | K74: ='MOMP Tables'!X4 -> Below Average | M74: ="Correlation – category AOV vs avg profit/sale: "&TEXT(CORREL(O61:O70,P61:P70),"0.00") -> Correlation – category AOV vs avg profit/sale: 0.95
B75: =D75&" "&RIGHT(C75,2) -> Mar 20 | C75: ='MOMP Tables'!$G$3 -> 2020 | D75: ='MOMP Tables'!B7 -> Mar | E75: ='MOMP Tables'!G7 -> 52 | F75: ='MOMP Tables'!H7 -> 3579943.8 | G75: ='MOMP Tables'!J7 -> 596343.77 | H75: ='MOMP Tables'!R41 -> 0.16657909 | I75: ='MOMP Tables'!N23 -> 68845.074 | J75: ='MOMP Tables'!D40 -> 11468.149 | K75: ='MOMP Tables'!X5 -> Average
B76: =D76&" "&RIGHT(C76,2) -> Apr 20 | C76: ='MOMP Tables'!$G$3 -> 2020 | D76: ='MOMP Tables'!B8 -> Apr | E76: ='MOMP Tables'!G8 -> 38 | F76: ='MOMP Tables'!H8 -> 4069097.8 | G76: ='MOMP Tables'!J8 -> 696219.46 | H76: ='MOMP Tables'!R42 -> 0.17109922 | I76: ='MOMP Tables'!N24 -> 107081.52 | J76: ='MOMP Tables'!D41 -> 18321.565 | K76: ='MOMP Tables'!X6 -> Average
B77: =D77&" "&RIGHT(C77,2) -> May 20 | C77: ='MOMP Tables'!$G$3 -> 2020 | D77: ='MOMP Tables'!B9 -> May | E77: ='MOMP Tables'!G9 -> 55 | F77: ='MOMP Tables'!H9 -> 5537943.8 | G77: ='MOMP Tables'!J9 -> 914851.65 | H77: ='MOMP Tables'!R43 -> 0.16519699 | I77: ='MOMP Tables'!N25 -> 100689.89 | J77: ='MOMP Tables'!D42 -> 16633.666 | K77: ='MOMP Tables'!X7 -> Average
B78: =D78&" "&RIGHT(C78,2) -> Jun 20 | C78: ='MOMP Tables'!$G$3 -> 2020 | D78: ='MOMP Tables'!B10 -> Jun | E78: ='MOMP Tables'!G10 -> 43 | F78: ='MOMP Tables'!H10 -> 7158137.9 | G78: ='MOMP Tables'!J10 -> 1187044.5 | H78: ='MOMP Tables'!R44 -> 0.16583146 | I78: ='MOMP Tables'!N26 -> 166468.32 | J78: ='MOMP Tables'!D43 -> 27605.685 | K78: ='MOMP Tables'!X8 -> Above Average
B79: =D79&" "&RIGHT(C79,2) -> Jul 20 | C79: ='MOMP Tables'!$G$3 -> 2020 | D79: ='MOMP Tables'!B11 -> Jul | E79: ='MOMP Tables'!G11 -> 36 | F79: ='MOMP Tables'!H11 -> 5242556.5 | G79: ='MOMP Tables'!J11 -> 839989.39 | H79: ='MOMP Tables'!R45 -> 0.16022515 | I79: ='MOMP Tables'!N27 -> 145626.57 | J79: ='MOMP Tables'!D44 -> 23333.039 | K79: ='MOMP Tables'!X9 -> Average
B80: =D80&" "&RIGHT(C80,2) -> Aug 20 | C80: ='MOMP Tables'!$G$3 -> 2020 | D80: ='MOMP Tables'!B12 -> Aug | E80: ='MOMP Tables'!G12 -> 45 | F80: ='MOMP Tables'!H12 -> 4714525.2 | G80: ='MOMP Tables'!J12 -> 768976.36 | H80: ='MOMP Tables'!R46 -> 0.16310791 | I80: ='MOMP Tables'!N28 -> 104767.23 | J80: ='MOMP Tables'!D45 -> 17088.364 | K80: ='MOMP Tables'!X10 -> Average
B81: =D81&" "&RIGHT(C81,2) -> Sep 20 | C81: ='MOMP Tables'!$G$3 -> 2020 | D81: ='MOMP Tables'!B13 -> Sep | E81: ='MOMP Tables'!G13 -> 34 | F81: ='MOMP Tables'!H13 -> 3778141.4 | G81: ='MOMP Tables'!J13 -> 663167.65 | H81: ='MOMP Tables'!R47 -> 0.17552748 | I81: ='MOMP Tables'!N29 -> 111121.81 | J81: ='MOMP Tables'!D46 -> 19504.931 | K81: ='MOMP Tables'!X11 -> Average
B82: =D82&" "&RIGHT(C82,2) -> Oct 20 | C82: ='MOMP Tables'!$G$3 -> 2020 | D82: ='MOMP Tables'!B14 -> Oct | E82: ='MOMP Tables'!G14 -> 50 | F82: ='MOMP Tables'!H14 -> 4869726.8 | G82: ='MOMP Tables'!J14 -> 839700.96 | H82: ='MOMP Tables'!R48 -> 0.17243287 | I82: ='MOMP Tables'!N30 -> 97394.537 | J82: ='MOMP Tables'!D47 -> 16794.019 | K82: ='MOMP Tables'!X12 -> Average
B83: =D83&" "&RIGHT(C83,2) -> Nov 20 | C83: ='MOMP Tables'!$G$3 -> 2020 | D83: ='MOMP Tables'!B15 -> Nov | E83: ='MOMP Tables'!G15 -> 45 | F83: ='MOMP Tables'!H15 -> 4734730.1 | G83: ='MOMP Tables'!J15 -> 787670.37 | H83: ='MOMP Tables'!R49 -> 0.16636014 | I83: ='MOMP Tables'!N31 -> 105216.22 | J83: ='MOMP Tables'!D48 -> 17503.786 | K83: ='MOMP Tables'!X13 -> Average
B84: =D84&" "&RIGHT(C84,2) -> Dec 20 | C84: ='MOMP Tables'!$G$3 -> 2020 | D84: ='MOMP Tables'!B16 -> Dec | E84: ='MOMP Tables'!G16 -> 33 | F84: ='MOMP Tables'!H16 -> 5884298.3 | G84: ='MOMP Tables'!J16 -> 970796.22 | H84: ='MOMP Tables'!R50 -> 0.1649808 | I84: ='MOMP Tables'!N32 -> 178312.07 | J84: ='MOMP Tables'!D49 -> 29418.067 | K84: ='MOMP Tables'!X14 -> Average
B85: Total / Avg | E85: =SUM(E61:E84) -> 1000 | F85: =SUM(F61:F84) -> 1.1336174e+08 | G85: =SUM(G61:G84) -> 18992428 | H85: =G85/F85 -> 0.16753825 | I85: =F85/E85 -> 113361.74 | J85: =G85/E85 -> 18992.428
